Workbook

Sheet Read Me First
A1: PredSea — Bottom-Up Growth & Series A Readiness Model
A3: How to use this workbook
A4: 1. Every BLUE cell is an input you control. Every BLACK cell is a formula — do not overwrite it.
A5: 2. Start with the 'Assumptions' tab. The most important cells are highlighted YELLOW — these are
A6: currently placeholders and materially change the output. Replace them with real sourced numbers
A7: (port authority / charter association vessel counts, actual pilot churn once you have more weeks of data).
A8: 3. 'Monthly Model' builds a 48-month (Year 1-4) cohort model: new logos, churn, seasonality, MRR, cash burn.
A9: It is capped by the addressable-vessel ceiling in Assumptions, so it cannot grow past what is countable.
A10: 4. 'Annual Summary' rolls the monthly model into the Year 1/2/3/4 view for your pitch deck and business plan.
A11: 5. 'Series A Dashboard' translates your monthly numbers into the specific metrics investors check before
A12: funding a Series A, with pass/fail thresholds you can adjust. Use this to know, month by month, how close
A13: you actually are — rather than assuming a fixed 12-month calendar date.
... A21: - Real founder-draw ramp timing (when bootstrap ends and full €65K/year draw begins) — currently a placeholder tied to Series A phase milestones.

Sheet Assumptions
A1: Assumptions — edit the BLUE cells
A3: Assumption | B3: Value | C3: Notes / source needed
A4: MARKET SIZING (addressable vessel ceilings)
A5: Addressable vessels — Balearics (Year 1 ceiling) | B5: 1200 | C5: PLACEHOLDER — replace with port authority / ANEN / charter association count
A6: Addressable vessels — + mainland Spain & Italy (Year 2 ceiling) | B6: 4500 | C6: PLACEHOLDER — sum of Y1 + additional country counts
A7: Addressable vessels — + France & Monaco (Year 3 ceiling) | B7: 9000 | C7: PLACEHOLDER — sum of Y2 + additional country counts
A8: Addressable vessels — wider West Med + adjacent segments (Year 4 ceiling) | B8: 15000 | C8: PLACEHOLDER — long-term SAM approach
A9: PRICING & MIX
A10: Premium Route price (EUR / vessel / month) | B10: 49 | C10: From business plan Section 6.1
A11: Corporate / Fleet blended price (EUR / vessel / month) | B11: 39.2 | C11: UPDATED — 20% volume discount off Premium (49 x 0.8 = 39.2), per founder guidance on typical fleet-deal discounting. Refine with first real fleet deal.
A12: % of vessels on Corporate/Fleet pricing (blend, by Year 3) | B12: 0.3 | C12: Placeholder — refine as fleet deals close
A13: GROWTH & CHURN (monthly rates by phase)
A14: Monthly logo growth rate — Months 1-6 (pilot→seed) | B14: 0.35 | C14: Small base, so % growth is naturally high — sanity-check against absolute adds in Monthly Model
A15: Monthly logo growth rate — Months 7-18 (scale/Series A) | B15: 0.14 | C15: Placeholder — benchmark against realized pilot conversion once available
A16: Monthly logo growth rate — Months 19-36 | B16: 0.08 | C16: Placeholder — growth naturally decelerates as ceiling approaches
A17: Monthly logo growth rate — Months 37-48 | B17: 0.05 | C17: Placeholder
A18: Monthly logo churn rate (of active base) | B18: 0.02 | C18: Placeholder — replace with real pilot churn after a full season
A19: SEASONALITY (% of logo base actively paying, by calendar month)
A20: Seasonal active % — Jan | B20: 0.35 | C20: Placeholder — refine once pilot shows real off-season pause/renewal behavior
A21: Seasonal active % — Feb | B21: 0.35 | C21: Placeholder — refine once pilot shows real off-season pause/renewal behavior
A22: Seasonal active % — Mar | B22: 0.55 | C22: Placeholder — refine once pilot shows real off-season pause/renewal behavior
A23: Seasonal active % — Apr | B23: 0.85 | C23: Placeholder — refine once pilot shows real off-season pause/renewal behavior
A24: Seasonal active % — May | B24: 1 | C24: Placeholder — refine once pilot shows real off-season pause/renewal behavior
A25: Seasonal active % — Jun | B25: 1 | C25: Placeholder — refine once pilot shows real off-season pause/renewal behavior
A26: Seasonal active % — Jul | B26: 1 | C26: Placeholder — refine once pilot shows real off-season pause/renewal behavior
A27: Seasonal active % — Aug | B27: 1 | C27: Placeholder — refine once pilot shows real off-season pause/renewal behavior
A28: Seasonal active % — Sep | B28: 1 | C28: Placeholder — refine once pilot shows real off-season pause/renewal behavior
A29: Seasonal active % — Oct | B29: 0.85 | C29: Placeholder — refine once pilot shows real off-season pause/renewal behavior
A30: Seasonal active % — Nov | B30: 0.45 | C30: Placeholder — refine once pilot shows real off-season pause/renewal behavior
A31: Seasonal active % — Dec | B31: 0.35 | C31: Placeholder — refine once pilot shows real off-season pause/renewal behavior
A32: UNIT ECONOMICS
A33: Gross margin % | B33: 0.85 | C33: From business plan Section 13.2
A34: CAC per vessel (EUR) | B34: 150 | C34: PLACEHOLDER — replace with real pilot BD/marketing cost per onboarded captain
A35: Average customer lifetime (months, before churn) | B35: 24 | C35: Cross-check: 1/monthly churn rate — see Series A Dashboard
A36: COSTS (annual operating burn, EUR)
A37: Year 1 annual burn — personnel, marketing & other (excl. cloud infra & AI tokens, modeled separately below) | B37: =(B81*B75+B82)*(1+B83) -> 339250 | C37: Now a formula: (founder cost x headcount + marketing budget) x (1 + contingency). All 4 years share the same baseline on purpose — team growth (sales hire, optional Caribbean hire) shows up as its own explicit, separate line in Monthly Model instead of being buried inside an escalating lump sum. Override any single year manually if you want it to diverge.
A38: Year 2 annual burn — personnel, marketing & other (excl. cloud infra & AI tokens) | B38: =B37 -> 339250 | C38: Now a formula: (founder cost x headcount + marketing budget) x (1 + contingency). All 4 years share the same baseline on purpose — team growth (sales hire, optional Caribbean hire) shows up as its own explicit, separate line in Monthly Model instead of being buried inside an escalating lump sum. Override any single year manually if you want it to diverge.
A39: Year 3 annual burn — personnel, marketing & other (excl. cloud infra & AI tokens) | B39: =B37 -> 339250 | C39: Now a formula: (founder cost x headcount + marketing budget) x (1 + contingency). All 4 years share the same baseline on purpose — team growth (sales hire, optional Caribbean hire) shows up as its own explicit, separate line in Monthly Model instead of being buried inside an escalating lump sum. Override any single year manually if you want it to diverge.
A40: Year 4 annual burn — personnel, marketing & other (excl. cloud infra & AI tokens) | B40: =B37 -> 339250 | C40: Now a formula: (founder cost x headcount + marketing budget) x (1 + contingency). All 4 years share the same baseline on purpose — team growth (sales hire, optional Caribbean hire) shows up as its own explicit, separate line in Monthly Model instead of being buried inside an escalating lump sum. Override any single year manually if you want it to diverge.
A41: SEED START POINT (pilot actuals — update monthly)
A42: Cumulative logos at Month 0 (today) | B42: 2 | C42: Actual pilot count — update as it changes
A44: CARIBBEAN EXPANSION (counter-seasonal — added per founder discussion)
A45: Caribbean launch month (Med-calendar month #, target) | B45: 13 | C45: Target ~12 months from raise close. Contingent on validation (Section 4) and Series A timing — adjust as real dates firm up.
A46: Addressable vessels — Caribbean (ceiling from launch) | B46: 2000 | C46: PLACEHOLDER — source from BVI/USVI/Grenadines/Bahamas charter association & marina counts
A47: Caribbean incremental monthly compute/infra opex from launch (EUR/month) | B47: =B68 -> 50 | C47: UPDATED — now grounded in the real Western Med per-region cost (B68 = €50/month) rather than an earlier invented €12,500/month guess. Assumes a second region costs about the same to run once built; revisit once real Caribbean usage data exists.
A48: One-off Caribbean domain setup cost (EUR, incurred at launch month) | B48: 40000 | C48: PLACEHOLDER — bathymetry acquisition/processing, grid build, initial validation run compute, local data-partnership setup (SOCIB-equivalent).
A49: Caribbean monthly logo churn rate (of active base) | B49: 0.02 | C49: PLACEHOLDER — reuses Med churn assumption; replace once real Caribbean data exists.
A51: CARIBBEAN SEASONALITY (% of Caribbean logo base actively paying, by calendar month)
A52: Seasonal active % — Caribbean — Jan | B52: 1 | C52: PLACEHOLDER — illustrative counter-seasonal curve (Caribbean high season ~Dec-Apr, hurricane-season dip Jun-Nov). Replace with real charter-calendar data before relying on this for the seasonality argument.
A53: Seasonal active % — Caribbean — Feb | B53: 1 | C53: PLACEHOLDER — illustrative counter-seasonal curve (Caribbean high season ~Dec-Apr, hurricane-season dip Jun-Nov). Replace with real charter-calendar data before relying on this for the seasonality argument.
A54: Seasonal active % — Caribbean — Mar | B54: 1 | C54: PLACEHOLDER — illustrative counter-seasonal curve (Caribbean high season ~Dec-Apr, hurricane-season dip Jun-Nov). Replace with real charter-calendar data before relying on this for the seasonality argument.
A55: Seasonal active % — Caribbean — Apr | B55: 0.9 | C55: PLACEHOLDER — illustrative counter-seasonal curve (Caribbean high season ~Dec-Apr, hurricane-season dip Jun-Nov). Replace with real charter-calendar data before relying on this for the seasonality argument.
A56: Seasonal active % — Caribbean — May | B56: 0.6 | C56: PLACEHOLDER — illustrative counter-seasonal curve (Caribbean high season ~Dec-Apr, hurricane-season dip Jun-Nov). Replace with real charter-calendar data before relying on this for the seasonality argument.
A57: Seasonal active % — Caribbean — Jun | B57: 0.4 | C57: PLACEHOLDER — illustrative counter-seasonal curve (Caribbean high season ~Dec-Apr, hurricane-season dip Jun-Nov). Replace with real charter-calendar data before relying on this for the seasonality argument.
A58: Seasonal active % — Caribbean — Jul | B58: 0.35 | C58: PLACEHOLDER — illustrative counter-seasonal curve (Caribbean high season ~Dec-Apr, hurricane-season dip Jun-Nov). Replace with real charter-calendar data before relying on this for the seasonality argument.
A59: Seasonal active % — Caribbean — Aug | B59: 0.35 | C59: PLACEHOLDER — illustrative counter-seasonal curve (Caribbean high season ~Dec-Apr, hurricane-season dip Jun-Nov). Replace with real charter-calendar data before relying on this for the seasonality argument.
A60: Seasonal active % — Caribbean — Sep | B60: 0.35 | C60: PLACEHOLDER — illustrative counter-seasonal curve (Caribbean high season ~Dec-Apr, hurricane-season dip Jun-Nov). Replace with real charter-calendar data before relying on this for the seasonality argument.
A61: Seasonal active % — Caribbean — Oct | B61: 0.4 | C61: PLACEHOLDER — illustrative counter-seasonal curve (Caribbean high season ~Dec-Apr, hurricane-season dip Jun-Nov). Replace with real charter-calendar data before relying on this for the seasonality argument.
A62: Seasonal active % — Caribbean — Nov | B62: 0.55 | C62: PLACEHOLDER — illustrative counter-seasonal curve (Caribbean high season ~Dec-Apr, hurricane-season dip Jun-Nov). Replace with real charter-calendar data before relying on this for the seasonality argument.
A63: Seasonal active % — Caribbean — Dec | B63: 0.9 | C63: PLACEHOLDER — illustrative counter-seasonal curve (Caribbean high season ~Dec-Apr, hurricane-season dip Jun-Nov). Replace with real charter-calendar data before relying on this for the seasonality argument.
A65: Caribbean seed logos at launch (first signed captains/vessels) | B65: 2 | C65: PLACEHOLDER — mirrors the Med model's actual 2-vessel pilot start; replace with the real first-Caribbean-cohort count once known.
A67: REAL COST DATA — CLOUD COMPUTE & AI TOKENS (from Charles's GCP billing export, July 2026)
A68: Cloud compute cost per active region (EUR/month) | B68: 50 | C68: REAL — current Western Med cost at 1km resolution / 5-day forecast (Compute Engine, Storage, Cloud Run, Cloud Build, Artifact Registry, BigQuery, Networking combined). Assumed to apply per additional region once built (Caribbean, etc.) — refine once a second region is live.
A69: AI token (Gemini/Vertex AI) cost today — gross, mostly build/dev usage (EUR/month) | B69: 300 | C69: REAL — Vertex AI line from GCP billing export (~€286, rounded). Currently ~94% of all cloud spend; expected to fall as the hi-res system matures and less is spent on build/iteration. Note: currently covered by Google for Startups credits — this is gross cost, not what's actually billed today.
A70: AI token cost decay half-life as system matures (months) | B70: 6 | C70: PLACEHOLDER — assumed rate at which build/dev-driven token usage shrinks. Refine once 2-3+ months of real monthly token trend exist.
A71: AI token steady-state floor — ongoing dev/maintenance usage (EUR/month) | B71: 75 | C71: PLACEHOLDER — token spend won't hit zero; some ongoing feature work continues indefinitely.
A72: AI token serving cost per active paying vessel (EUR/vessel/month) | B72: 0.35 | C72: REVISED using real Google Cloud Gemini/Vertex AI pricing (fetched cloud.google.com/vertex-ai/generative-ai/pricing): ~60 WhatsApp queries/month/vessel x ~4,000 input + 400 output tokens each. On Gemini Flash-Lite that's ~€0.09/vessel/month; on Flash it's ~€0.18; on Gemini Pro it's ~€0.70. €0.35 is a mid-range estimate — refine once you know which model tier serves production traffic and have real per-conversation token counts.
A74: TEAM & HIRING PLAN
A75: Current headcount (Ocean/Weather/AI, Conversational AI, Captain/Advisor, Product) | B75: 4 | C75: Informational — the four founders, one per functional area. No dedicated sales/BD role yet.
A76: Add a Sales/BD hire? (1 = yes, 0 = no) | B76: 1 | C76: PLACEHOLDER toggle — set to 0 to model staying at 4 founders with no dedicated sales hire.
A77: Sales/BD hire trigger month (Med-calendar month #) | B77: 13 | C77: PLACEHOLDER — default aligns with Series A / Caribbean-launch timing (month 13), when boat-show pipeline and multi-region BD load likely exceed what 4 generalist founders can cover.
A78: Sales/BD hire annual loaded cost (EUR/year) | B78: 55000 | C78: PLACEHOLDER — junior/mid B2B SaaS sales-BD hire, Spain-based, loaded cost (salary + employer costs). Refine against real market rate.
A80: FOUNDER & MARKETING BASELINE (bottom-up — replaces the old flat burn placeholders above)
A81: Founder loaded cost each (EUR/year) | B81: 65000 | C81: REAL, but a TARGET not a fixed floor — founders confirmed €65,000/year each is the ideal once the business supports it. Founders are open to €0 personal draw at the outset (see Founder Draw Ramp below).
A82: Marketing & boat-show budget (EUR/year) | B82: 35000 | C82: PLACEHOLDER — 5 boat shows (Monaco, Barcelona, Netherlands, Genoa, Fort Lauderdale) plus travel/booth costs and lead-gen. Refine with real quotes.
A83: Contingency / working-capital buffer (% of founder + marketing costs) | B83: 0.15 | C83: PLACEHOLDER — operational runway buffer per Business Plan Section 13.3.
A85: OPTIONAL: CARIBBEAN REGIONAL HIRE (explore-only, defaulted off)
A86: Add a Caribbean regional ops/BD hire at Caribbean launch? (1 = yes, 0 = no) | B86: 0 | C86: PLACEHOLDER toggle, defaulted OFF — set to 1 to explore adding a local Caribbean hire alongside the regional launch instead of running it remotely from the Balearics.
A87: Caribbean regional hire annual loaded cost (EUR/year) | B87: 45000 | C87: PLACEHOLDER — local ops/BD hire, assumed lower loaded cost than a Spain-based hire.
A89: FOUNDER DRAW RAMP (bootstrap flexibility — added per founder discussion)
A90: Founder draw — % of ideal during bootstrap phase (months 1 to ramp-start) | B90: 0 | C90: REAL — founders are open to €0 personal draw at the outset; B81's €65K/year is the ideal target once revenue supports it, not a minimum owed from month 1.
A91: Founder draw ramp — start month (Med-calendar month #) | B91: 7 | C91: PLACEHOLDER — assumed ramp begins at the start of the Scale/Series A phase (month 7). Adjust to match real revenue/fundraising timing.
A92: Founder draw ramp — month full ideal draw is reached | B92: 19 | C92: PLACEHOLDER — assumed founders reach the full €65K/year ideal draw by the start of the Post-Series A phase (month 19). Linear ramp between start and this month. Adjust as real timing firms up.

Sheet Monthly Model
A1: Month # | B1: Calendar Month | C1: Year | D1: Growth Phase | E1: SOM Ceiling | F1: Monthly Growth Rate | G1: Gross New Logos | H1: Churned Logos | I1: Cumulative Logos | J1: Seasonal Active % | K1: Effective Paying Vessels | L1: Blended Price (EUR) | M1: MRR (EUR) | N1: Monthly Opex (EUR) | O1: Gross Profit (EUR) | P1: Net Cash Flow (EUR) | Q1: Months Since Caribbean Launch | R1: Caribbean Growth Phase | S1: Caribbean SOM Ceiling | T1: Caribbean Monthly Growth Rate | U1: Caribbean Gross New Logos | V1: Caribbean Churned Logos | W1: Caribbean Cumulative Logos | X1: Caribbean Seasonal Active % | Y1: Caribbean Effective Paying Vessels | Z1: Caribbean Blended Price (EUR) | AA1: Caribbean MRR (EUR) | AB1: Caribbean Incremental Opex (EUR) | AC1: Caribbean Gross Profit (EUR) | AD1: Total Cumulative Logos (Med + Caribbean) | AE1: Total MRR (EUR) | AF1: Total Opex (EUR) | AG1: Total Gross Profit (EUR) | AH1: Total Net Cash Flow (EUR) | AI1: Total Cumulative Logos MoM growth % | AJ1: AI Token Cost — Company-wide (EUR) | AK1: Sales/BD Hire Incremental Opex (EUR) | AL1: Caribbean Regional Hire Opex (EUR)
A2: 1 | B2: Aug 2026 | C2: =IF(A2<=12,1,IF(A2<=24,2,IF(A2<=36,3,4))) -> 1 | D2: =IF(A2<=6,"P1: Pilot->Seed",IF(A2<=18,"P2: Scale/Series A",IF(A2<=36,"P3: Post-Series A","P4: Maturity"))) -> P1: Pilot->Seed | E2: =IF(C2=1,Assumptions!$B$5,IF(C2=2,Assumptions!$B$6,IF(C2=3,Assumptions!$B$7,Assumptions!$B$8))) -> 1200 | F2: =IF(A2<=6,Assumptions!$B$14,IF(A2<=18,Assumptions!$B$15,IF(A2<=36,Assumptions!$B$16,Assumptions!$B$17))) -> 0.35 | G2: =ROUND(MAX(Assumptions!$B$42,1)*F2,0) -> 1 | H2: =ROUND(Assumptions!$B$42*Assumptions!$B$18,0) -> 0 | I2: =MIN(Assumptions!$B$42+G2-H2,E2) -> 3 | J2: =Assumptions!$B$27 -> 1 | K2: =I2*J2 -> 3 | L2: =Assumptions!$B$10*(1-Assumptions!$B$12)+Assumptions!$B$11*Assumptions!$B$12 -> 46.06 | M2: =K2*L2 -> 138.18 | N2: =((IF(A2<=Assumptions!$B$91,Assumptions!$B$90,IF(A2>=Assumptions!$B$92,1,Assumptions!$B$90+(1-Assumptions!$B$90)*(A2-Assumptions!$B$91)/(Assumptions!$B$92-Assumptions!$B$91))))*Assumptions!$B$81*Assumptions!$B$75+Assumptions!$B$82)*(1+Assumptions!$B$83)/12 -> 3354.1667 | O2: =M2*Assumptions!$B$33 -> 117.453 | P2: =O2-N2 -> -3236.7137 | Q2: =IF(A2>=Assumptions!$B$45,A2-Assumptions!$B$45+1,"") | R2: =IF(Q2="","Not yet launched",IF(Q2<=6,"CP1: Launch",IF(Q2<=18,"CP2: Scale",IF(Q2<=36,"CP3: Mature","CP4: Steady")))) -> Not yet launched | S2: =IF(Q2="",0,Assumptions!$B$46) -> 0 | T2: =IF(Q2="",0,IF(Q2<=6,Assumptions!$B$14,IF(Q2<=18,Assumptions!$B$15,IF(Q2<=36,Assumptions!$B$16,Assumptions!$B$17)))) -> 0 | U2: =IF(Q2="",0,IF(Q2=1,Assumptions!$B$65,ROUND(MAX(0,1)*T2,0))) -> 0 | V2: =IF(Q2="",0,ROUND(0*Assumptions!$B$49,0)) -> 0 | W2: =IF(Q2="",0,MIN(0+U2-V2,S2)) -> 0 | X2: =IF(Q2="",0,Assumptions!$B$59) -> 0 | Y2: =W2*X2 -> 0 | Z2: =L2 -> 46.06 | AA2: =Y2*Z2 -> 0 | AB2: =IF(A2=Assumptions!$B$45,Assumptions!$B$47+Assumptions!$B$48,IF(A2>Assumptions!$B$45,Assumptions!$B$47,0)) -> 0 | AC2: =AA2*Assumptions!$B$33 -> 0 | AD2: =I2+W2 -> 3 | AE2: =M2+AA2 -> 138.18 | AF2: =N2+AB2+AJ2+AK2+AL2+Assumptions!$B$68 -> 3672.4863 | AG2: =O2+AC2 -> 117.453 | AH2: =AG2-AF2 -> -3555.0333 | AJ2: =MAX(Assumptions!$B$71,Assumptions!$B$69*0.5^(A2/Assumptions!$B$70))+Assumptions!$B$72*(K2+Y2) -> 268.31962 | AK2: =IF(AND(Assumptions!$B$76=1,A2>=Assumptions!$B$77),Assumptions!$B$78/12,0) -> 0 | AL2: =IF(AND(Assumptions!$B$86=1,Q2<>""),Assumptions!$B$87/12,0) -> 0
A3: 2 | B3: Sep 2026 | C3: =IF(A3<=12,1,IF(A3<=24,2,IF(A3<=36,3,4))) -> 1 | D3: =IF(A3<=6,"P1: Pilot->Seed",IF(A3<=18,"P2: Scale/Series A",IF(A3<=36,"P3: Post-Series A","P4: Maturity"))) -> P1: Pilot->Seed | E3: =IF(C3=1,Assumptions!$B$5,IF(C3=2,Assumptions!$B$6,IF(C3=3,Assumptions!$B$7,Assumptions!$B$8))) -> 1200 | F3: =IF(A3<=6,Assumptions!$B$14,IF(A3<=18,Assumptions!$B$15,IF(A3<=36,Assumptions!$B$16,Assumptions!$B$17))) -> 0.35 | G3: =ROUND(MAX(I2,1)*F3,0) -> 1 | H3: =ROUND(I2*Assumptions!$B$18,0) -> 0 | I3: =MIN(I2+G3-H3,E3) -> 4 | J3: =Assumptions!$B$28 -> 1 | K3: =I3*J3 -> 4 | L3: =Assumptions!$B$10*(1-Assumptions!$B$12)+Assumptions!$B$11*Assumptions!$B$12 -> 46.06 | M3: =K3*L3 -> 184.24 | N3: =((IF(A3<=Assumptions!$B$91,Assumptions!$B$90,IF(A3>=Assumptions!$B$92,1,Assumptions!$B$90+(1-Assumptions!$B$90)*(A3-Assumptions!$B$91)/(Assumptions!$B$92-Assumptions!$B$91))))*Assumptions!$B$81*Assumptions!$B$75+Assumptions!$B$82)*(1+Assumptions!$B$83)/12 -> 3354.1667 | O3: =M3*Assumptions!$B$33 -> 156.604 | P3: =O3-N3 -> -3197.5627 | Q3: =IF(A3>=Assumptions!$B$45,A3-Assumptions!$B$45+1,"") | R3: =IF(Q3="","Not yet launched",IF(Q3<=6,"CP1: Launch",IF(Q3<=18,"CP2: Scale",IF(Q3<=36,"CP3: Mature","CP4: Steady")))) -> Not yet launched | S3: =IF(Q3="",0,Assumptions!$B$46) -> 0 | T3: =IF(Q3="",0,IF(Q3<=6,Assumptions!$B$14,IF(Q3<=18,Assumptions!$B$15,IF(Q3<=36,Assumptions!$B$16,Assumptions!$B$17)))) -> 0 | U3: =IF(Q3="",0,IF(Q3=1,Assumptions!$B$65,ROUND(MAX(W2,1)*T3,0))) -> 0 | V3: =IF(Q3="",0,ROUND(W2*Assumptions!$B$49,0)) -> 0 | W3: =IF(Q3="",0,MIN(W2+U3-V3,S3)) -> 0 | X3: =IF(Q3="",0,Assumptions!$B$60) -> 0 | Y3: =W3*X3 -> 0 | Z3: =L3 -> 46.06 | AA3: =Y3*Z3 -> 0 | AB3: =IF(A3=Assumptions!$B$45,Assumptions!$B$47+Assumptions!$B$48,IF(A3>Assumptions!$B$45,Assumptions!$B$47,0)) -> 0 | AC3: =AA3*Assumptions!$B$33 -> 0 | AD3: =I3+W3 -> 4 | AE3: =M3+AA3 -> 184.24 | AF3: =N3+AB3+AJ3+AK3+AL3+Assumptions!$B$68 -> 3643.6768 | AG3: =O3+AC3 -> 156.604 | AH3: =AG3-AF3 -> -3487.0728 | AI3: =IFERROR((AD3-AD2)/AD2,"") -> 0.33333333 | AJ3: =MAX(Assumptions!$B$71,Assumptions!$B$69*0.5^(A3/Assumptions!$B$70))+Assumptions!$B$72*(K3+Y3) -> 239.51016 | AK3: =IF(AND(Assumptions!$B$76=1,A3>=Assumptions!$B$77),Assumptions!$B$78/12,0) -> 0 | AL3: =IF(AND(Assumptions!$B$86=1,Q3<>""),Assumptions!$B$87/12,0) -> 0
A4: 3 | B4: Oct 2026 | C4: =IF(A4<=12,1,IF(A4<=24,2,IF(A4<=36,3,4))) -> 1 | D4: =IF(A4<=6,"P1: Pilot->Seed",IF(A4<=18,"P2: Scale/Series A",IF(A4<=36,"P3: Post-Series A","P4: Maturity"))) -> P1: Pilot->Seed | E4: =IF(C4=1,Assumptions!$B$5,IF(C4=2,Assumptions!$B$6,IF(C4=3,Assumptions!$B$7,Assumptions!$B$8))) -> 1200 | F4: =IF(A4<=6,Assumptions!$B$14,IF(A4<=18,Assumptions!$B$15,IF(A4<=36,Assumptions!$B$16,Assumptions!$B$17))) -> 0.35 | G4: =ROUND(MAX(I3,1)*F4,0) -> 1 | H4: =ROUND(I3*Assumptions!$B$18,0) -> 0 | I4: =MIN(I3+G4-H4,E4) -> 5 | J4: =Assumptions!$B$29 -> 0.85 | K4: =I4*J4 -> 4.25 | L4: =Assumptions!$B$10*(1-Assumptions!$B$12)+Assumptions!$B$11*Assumptions!$B$12 -> 46.06 | M4: =K4*L4 -> 195.755 | N4: =((IF(A4<=Assumptions!$B$91,Assumptions!$B$90,IF(A4>=Assumptions!$B$92,1,Assumptions!$B$90+(1-Assumptions!$B$90)*(A4-Assumptions!$B$91)/(Assumptions!$B$92-Assumptions!$B$91))))*Assumptions!$B$81*Assumptions!$B$75+Assumptions!$B$82)*(1+Assumptions!$B$83)/12 -> 3354.1667 | O4: =M4*Assumptions!$B$33 -> 166.39175 | P4: =O4-N4 -> -3187.7749 | Q4: =IF(A4>=Assumptions!$B$45,A4-Assumptions!$B$45+1,"") | R4: =IF(Q4="","Not yet launched",IF(Q4<=6,"CP1: Launch",IF(Q4<=18,"CP2: Scale",IF(Q4<=36,"CP3: Mature","CP4: Steady")))) -> Not yet launched | S4: =IF(Q4="",0,Assumptions!$B$46) -> 0 | T4: =IF(Q4="",0,IF(Q4<=6,Assumptions!$B$14,IF(Q4<=18,Assumptions!$B$15,IF(Q4<=36,Assumptions!$B$16,Assumptions!$B$17)))) -> 0 | U4: =IF(Q4="",0,IF(Q4=1,Assumptions!$B$65,ROUND(MAX(W3,1)*T4,0))) -> 0 | V4: =IF(Q4="",0,ROUND(W3*Assumptions!$B$49,0)) -> 0 | W4: =IF(Q4="",0,MIN(W3+U4-V4,S4)) -> 0 | X4: =IF(Q4="",0,Assumptions!$B$61) -> 0 | Y4: =W4*X4 -> 0 | Z4: =L4 -> 46.06 | AA4: =Y4*Z4 -> 0 | AB4: =IF(A4=Assumptions!$B$45,Assumptions!$B$47+Assumptions!$B$48,IF(A4>Assumptions!$B$45,Assumptions!$B$47,0)) -> 0 | AC4: =AA4*Assumptions!$B$33 -> 0 | AD4: =I4+W4 -> 5 | AE4: =M4+AA4 -> 195.755 | AF4: =N4+AB4+AJ4+AK4+AL4+Assumptions!$B$68 -> 3617.7862 | AG4: =O4+AC4 -> 166.39175 | AH4: =AG4-AF4 -> -3451.3945 | AI4: =IFERROR((AD4-AD3)/AD3,"") -> 0.25 | AJ4: =MAX(Assumptions!$B$71,Assumptions!$B$69*0.5^(A4/Assumptions!$B$70))+Assumptions!$B$72*(K4+Y4) -> 213.61953 | AK4: =IF(AND(Assumptions!$B$76=1,A4>=Assumptions!$B$77),Assumptions!$B$78/12,0) -> 0 | AL4: =IF(AND(Assumptions!$B$86=1,Q4<>""),Assumptions!$B$87/12,0) -> 0
A5: 4 | B5: Nov 2026 | C5: =IF(A5<=12,1,IF(A5<=24,2,IF(A5<=36,3,4))) -> 1 | D5: =IF(A5<=6,"P1: Pilot->Seed",IF(A5<=18,"P2: Scale/Series A",IF(A5<=36,"P3: Post-Series A","P4: Maturity"))) -> P1: Pilot->Seed | E5: =IF(C5=1,Assumptions!$B$5,IF(C5=2,Assumptions!$B$6,IF(C5=3,Assumptions!$B$7,Assumptions!$B$8))) -> 1200 | F5: =IF(A5<=6,Assumptions!$B$14,IF(A5<=18,Assumptions!$B$15,IF(A5<=36,Assumptions!$B$16,Assumptions!$B$17))) -> 0.35 | G5: =ROUND(MAX(I4,1)*F5,0) -> 2 | H5: =ROUND(I4*Assumptions!$B$18,0) -> 0 | I5: =MIN(I4+G5-H5,E5) -> 7 | J5: =Assumptions!$B$30 -> 0.45 | K5: =I5*J5 -> 3.15 | L5: =Assumptions!$B$10*(1-Assumptions!$B$12)+Assumptions!$B$11*Assumptions!$B$12 -> 46.06 | M5: =K5*L5 -> 145.089 | N5: =((IF(A5<=Assumptions!$B$91,Assumptions!$B$90,IF(A5>=Assumptions!$B$92,1,Assumptions!$B$90+(1-Assumptions!$B$90)*(A5-Assumptions!$B$91)/(Assumptions!$B$92-Assumptions!$B$91))))*Assumptions!$B$81*Assumptions!$B$75+Assumptions!$B$82)*(1+Assumptions!$B$83)/12 -> 3354.1667 | O5: =M5*Assumptions!$B$33 -> 123.32565 | P5: =O5-N5 -> -3230.841 | Q5: =IF(A5>=Assumptions!$B$45,A5-Assumptions!$B$45+1,"") | R5: =IF(Q5="","Not yet launched",IF(Q5<=6,"CP1: Launch",IF(Q5<=18,"CP2: Scale",IF(Q5<=36,"CP3: Mature","CP4: Steady")))) -> Not yet launched | S5: =IF(Q5="",0,Assumptions!$B$46) -> 0 | T5: =IF(Q5="",0,IF(Q5<=6,Assumptions!$B$14,IF(Q5<=18,Assumptions!$B$15,IF(Q5<=36,Assumptions!$B$16,Assumptions!$B$17)))) -> 0 | U5: =IF(Q5="",0,IF(Q5=1,Assumptions!$B$65,ROUND(MAX(W4,1)*T5,0))) -> 0 | V5: =IF(Q5="",0,ROUND(W4*Assumptions!$B$49,0)) -> 0 | W5: =IF(Q5="",0,MIN(W4+U5-V5,S5)) -> 0 | X5: =IF(Q5="",0,Assumptions!$B$62) -> 0 | Y5: =W5*X5 -> 0 | Z5: =L5 -> 46.06 | AA5: =Y5*Z5 -> 0 | AB5: =IF(A5=Assumptions!$B$45,Assumptions!$B$47+Assumptions!$B$48,IF(A5>Assumptions!$B$45,Assumptions!$B$47,0)) -> 0 | AC5: =AA5*Assumptions!$B$33 -> 0 | AD5: =I5+W5 -> 7 | AE5: =M5+AA5 -> 145.089 | AF5: =N5+AB5+AJ5+AK5+AL5+Assumptions!$B$68 -> 3594.2573 | AG5: =O5+AC5 -> 123.32565 | AH5: =AG5-AF5 -> -3470.9317 | AI5: =IFERROR((AD5-AD4)/AD4,"") -> 0.4 | AJ5: =MAX(Assumptions!$B$71,Assumptions!$B$69*0.5^(A5/Assumptions!$B$70))+Assumptions!$B$72*(K5+Y5) -> 190.09066 | AK5: =IF(AND(Assumptions!$B$76=1,A5>=Assumptions!$B$77),Assumptions!$B$78/12,0) -> 0 | AL5: =IF(AND(Assumptions!$B$86=1,Q5<>""),Assumptions!$B$87/12,0) -> 0
A6: 5 | B6: Dec 2026 | C6: =IF(A6<=12,1,IF(A6<=24,2,IF(A6<=36,3,4))) -> 1 | D6: =IF(A6<=6,"P1: Pilot->Seed",IF(A6<=18,"P2: Scale/Series A",IF(A6<=36,"P3: Post-Series A","P4: Maturity"))) -> P1: Pilot->Seed | E6: =IF(C6=1,Assumptions!$B$5,IF(C6=2,Assumptions!$B$6,IF(C6=3,Assumptions!$B$7,Assumptions!$B$8))) -> 1200 | F6: =IF(A6<=6,Assumptions!$B$14,IF(A6<=18,Assumptions!$B$15,IF(A6<=36,Assumptions!$B$16,Assumptions!$B$17))) -> 0.35 | G6: =ROUND(MAX(I5,1)*F6,0) -> 2 | H6: =ROUND(I5*Assumptions!$B$18,0) -> 0 | I6: =MIN(I5+G6-H6,E6) -> 9 | J6: =Assumptions!$B$31 -> 0.35 | K6: =I6*J6 -> 3.15 | L6: =Assumptions!$B$10*(1-Assumptions!$B$12)+Assumptions!$B$11*Assumptions!$B$12 -> 46.06 | M6: =K6*L6 -> 145.089 | N6: =((IF(A6<=Assumptions!$B$91,Assumptions!$B$90,IF(A6>=Assumptions!$B$92,1,Assumptions!$B$90+(1-Assumptions!$B$90)*(A6-Assumptions!$B$91)/(Assumptions!$B$92-Assumptions!$B$91))))*Assumptions!$B$81*Assumptions!$B$75+Assumptions!$B$82)*(1+Assumptions!$B$83)/12 -> 3354.1667 | O6: =M6*Assumptions!$B$33 -> 123.32565 | P6: =O6-N6 -> -3230.841 | Q6: =IF(A6>=Assumptions!$B$45,A6-Assumptions!$B$45+1,"") | R6: =IF(Q6="","Not yet launched",IF(Q6<=6,"CP1: Launch",IF(Q6<=18,"CP2: Scale",IF(Q6<=36,"CP3: Mature","CP4: Steady")))) -> Not yet launched | S6: =IF(Q6="",0,Assumptions!$B$46) -> 0 | T6: =IF(Q6="",0,IF(Q6<=6,Assumptions!$B$14,IF(Q6<=18,Assumptions!$B$15,IF(Q6<=36,Assumptions!$B$16,Assumptions!$B$17)))) -> 0 | U6: =IF(Q6="",0,IF(Q6=1,Assumptions!$B$65,ROUND(MAX(W5,1)*T6,0))) -> 0 | V6: =IF(Q6="",0,ROUND(W5*Assumptions!$B$49,0)) -> 0 | W6: =IF(Q6="",0,MIN(W5+U6-V6,S6)) -> 0 | X6: =IF(Q6="",0,Assumptions!$B$63) -> 0 | Y6: =W6*X6 -> 0 | Z6: =L6 -> 46.06 | AA6: =Y6*Z6 -> 0 | AB6: =IF(A6=Assumptions!$B$45,Assumptions!$B$47+Assumptions!$B$48,IF(A6>Assumptions!$B$45,Assumptions!$B$47,0)) -> 0 | AC6: =AA6*Assumptions!$B$33 -> 0 | AD6: =I6+W6 -> 9 | AE6: =M6+AA6 -> 145.089 | AF6: =N6+AB6+AJ6+AK6+AL6+Assumptions!$B$68 -> 3573.6385 | AG6: =O6+AC6 -> 123.32565 | AH6: =AG6-AF6 -> -3450.3128 | AI6: =IFERROR((AD6-AD5)/AD5,"") -> 0.28571429 | AJ6: =MAX(Assumptions!$B$71,Assumptions!$B$69*0.5^(A6/Assumptions!$B$70))+Assumptions!$B$72*(K6+Y6) -> 169.47181 | AK6: =IF(AND(Assumptions!$B$76=1,A6>=Assumptions!$B$77),Assumptions!$B$78/12,0) -> 0 | AL6: =IF(AND(Assumptions!$B$86=1,Q6<>""),Assumptions!$B$87/12,0) -> 0
A7: 6 | B7: Jan 2027 | C7: =IF(A7<=12,1,IF(A7<=24,2,IF(A7<=36,3,4))) -> 1 | D7: =IF(A7<=6,"P1: Pilot->Seed",IF(A7<=18,"P2: Scale/Series A",IF(A7<=36,"P3: Post-Series A","P4: Maturity"))) -> P1: Pilot->Seed | E7: =IF(C7=1,Assumptions!$B$5,IF(C7=2,Assumptions!$B$6,IF(C7=3,Assumptions!$B$7,Assumptions!$B$8))) -> 1200 | F7: =IF(A7<=6,Assumptions!$B$14,IF(A7<=18,Assumptions!$B$15,IF(A7<=36,Assumptions!$B$16,Assumptions!$B$17))) -> 0.35 | G7: =ROUND(MAX(I6,1)*F7,0) -> 3 | H7: =ROUND(I6*Assumptions!$B$18,0) -> 0 | I7: =MIN(I6+G7-H7,E7) -> 12 | J7: =Assumptions!$B$20 -> 0.35 | K7: =I7*J7 -> 4.2 | L7: =Assumptions!$B$10*(1-Assumptions!$B$12)+Assumptions!$B$11*Assumptions!$B$12 -> 46.06 | M7: =K7*L7 -> 193.452 | N7: =((IF(A7<=Assumptions!$B$91,Assumptions!$B$90,IF(A7>=Assumptions!$B$92,1,Assumptions!$B$90+(1-Assumptions!$B$90)*(A7-Assumptions!$B$91)/(Assumptions!$B$92-Assumptions!$B$91))))*Assumptions!$B$81*Assumptions!$B$75+Assumptions!$B$82)*(1+Assumptions!$B$83)/12 -> 3354.1667 | O7: =M7*Assumptions!$B$33 -> 164.4342 | P7: =O7-N7 -> -3189.7325 | Q7: =IF(A7>=Assumptions!$B$45,A7-Assumptions!$B$45+1,"") | R7: =IF(Q7="","Not yet launched",IF(Q7<=6,"CP1: Launch",IF(Q7<=18,"CP2: Scale",IF(Q7<=36,"CP3: Mature","CP4: Steady")))) -> Not yet launched | S7: =IF(Q7="",0,Assumptions!$B$46) -> 0 | T7: =IF(Q7="",0,IF(Q7<=6,Assumptions!$B$14,IF(Q7<=18,Assumptions!$B$15,IF(Q7<=36,Assumptions!$B$16,Assumptions!$B$17)))) -> 0 | U7: =IF(Q7="",0,IF(Q7=1,Assumptions!$B$65,ROUND(MAX(W6,1)*T7,0))) -> 0 | V7: =IF(Q7="",0,ROUND(W6*Assumptions!$B$49,0)) -> 0 | W7: =IF(Q7="",0,MIN(W6+U7-V7,S7)) -> 0 | X7: =IF(Q7="",0,Assumptions!$B$52) -> 0 | Y7: =W7*X7 -> 0 | Z7: =L7 -> 46.06 | AA7: =Y7*Z7 -> 0 | AB7: =IF(A7=Assumptions!$B$45,Assumptions!$B$47+Assumptions!$B$48,IF(A7>Assumptions!$B$45,Assumptions!$B$47,0)) -> 0 | AC7: =AA7*Assumptions!$B$33 -> 0 | AD7: =I7+W7 -> 12 | AE7: =M7+AA7 -> 193.452 | AF7: =N7+AB7+AJ7+AK7+AL7+Assumptions!$B$68 -> 3555.6367 | AG7: =O7+AC7 -> 164.4342 | AH7: =AG7-AF7 -> -3391.2025 | AI7: =IFERROR((AD7-AD6)/AD6,"") -> 0.33333333 | AJ7: =MAX(Assumptions!$B$71,Assumptions!$B$69*0.5^(A7/Assumptions!$B$70))+Assumptions!$B$72*(K7+Y7) -> 151.47 | AK7: =IF(AND(Assumptions!$B$76=1,A7>=Assumptions!$B$77),Assumptions!$B$78/12,0) -> 0 | AL7: =IF(AND(Assumptions!$B$86=1,Q7<>""),Assumptions!$B$87/12,0) -> 0
A8: 7 | B8: Feb 2027 | C8: =IF(A8<=12,1,IF(A8<=24,2,IF(A8<=36,3,4))) -> 1 | D8: =IF(A8<=6,"P1: Pilot->Seed",IF(A8<=18,"P2: Scale/Series A",IF(A8<=36,"P3: Post-Series A","P4: Maturity"))) -> P2: Scale/Series A | E8: =IF(C8=1,Assumptions!$B$5,IF(C8=2,Assumptions!$B$6,IF(C8=3,Assumptions!$B$7,Assumptions!$B$8))) -> 1200 | F8: =IF(A8<=6,Assumptions!$B$14,IF(A8<=18,Assumptions!$B$15,IF(A8<=36,Assumptions!$B$16,Assumptions!$B$17))) -> 0.14 | G8: =ROUND(MAX(I7,1)*F8,0) -> 2 | H8: =ROUND(I7*Assumptions!$B$18,0) -> 0 | I8: =MIN(I7+G8-H8,E8) -> 14 | J8: =Assumptions!$B$21 -> 0.35 | K8: =I8*J8 -> 4.9 | L8: =Assumptions!$B$10*(1-Assumptions!$B$12)+Assumptions!$B$11*Assumptions!$B$12 -> 46.06 | M8: =K8*L8 -> 225.694 | N8: =((IF(A8<=Assumptions!$B$91,Assumptions!$B$90,IF(A8>=Assumptions!$B$92,1,Assumptions!$B$90+(1-Assumptions!$B$90)*(A8-Assumptions!$B$91)/(Assumptions!$B$92-Assumptions!$B$91))))*Assumptions!$B$81*Assumptions!$B$75+Assumptions!$B$82)*(1+Assumptions!$B$83)/12 -> 3354.1667 | O8: =M8*Assumptions!$B$33 -> 191.8399 | P8: =O8-N8 -> -3162.3268 | Q8: =IF(A8>=Assumptions!$B$45,A8-Assumptions!$B$45+1,"") | R8: =IF(Q8="","Not yet launched",IF(Q8<=6,"CP1: Launch",IF(Q8<=18,"CP2: Scale",IF(Q8<=36,"CP3: Mature","CP4: Steady")))) -> Not yet launched | S8: =IF(Q8="",0,Assumptions!$B$46) -> 0 | T8: =IF(Q8="",0,IF(Q8<=6,Assumptions!$B$14,IF(Q8<=18,Assumptions!$B$15,IF(Q8<=36,Assumptions!$B$16,Assumptions!$B$17)))) -> 0 | U8: =IF(Q8="",0,IF(Q8=1,Assumptions!$B$65,ROUND(MAX(W7,1)*T8,0))) -> 0 | V8: =IF(Q8="",0,ROUND(W7*Assumptions!$B$49,0)) -> 0 | W8: =IF(Q8="",0,MIN(W7+U8-V8,S8)) -> 0 | X8: =IF(Q8="",0,Assumptions!$B$53) -> 0 | Y8: =W8*X8 -> 0 | Z8: =L8 -> 46.06 | AA8: =Y8*Z8 -> 0 | AB8: =IF(A8=Assumptions!$B$45,Assumptions!$B$47+Assumptions!$B$48,IF(A8>Assumptions!$B$45,Assumptions!$B$47,0)) -> 0 | AC8: =AA8*Assumptions!$B$33 -> 0 | AD8: =I8+W8 -> 14 | AE8: =M8+AA8 -> 225.694 | AF8: =N8+AB8+AJ8+AK8+AL8+Assumptions!$B$68 -> 3539.5165 | AG8: =O8+AC8 -> 191.8399 | AH8: =AG8-AF8 -> -3347.6766 | AI8: =IFERROR((AD8-AD7)/AD7,"") -> 0.16666667 | AJ8: =MAX(Assumptions!$B$71,Assumptions!$B$69*0.5^(A8/Assumptions!$B$70))+Assumptions!$B$72*(K8+Y8) -> 135.34981 | AK8: =IF(AND(Assumptions!$B$76=1,A8>=Assumptions!$B$77),Assumptions!$B$78/12,0) -> 0 | AL8: =IF(AND(Assumptions!$B$86=1,Q8<>""),Assumptions!$B$87/12,0) -> 0
A9: 8 | B9: Mar 2027 | C9: =IF(A9<=12,1,IF(A9<=24,2,IF(A9<=36,3,4))) -> 1 | D9: =IF(A9<=6,"P1: Pilot->Seed",IF(A9<=18,"P2: Scale/Series A",IF(A9<=36,"P3: Post-Series A","P4: Maturity"))) -> P2: Scale/Series A | E9: =IF(C9=1,Assumptions!$B$5,IF(C9=2,Assumptions!$B$6,IF(C9=3,Assumptions!$B$7,Assumptions!$B$8))) -> 1200 | F9: =IF(A9<=6,Assumptions!$B$14,IF(A9<=18,Assumptions!$B$15,IF(A9<=36,Assumptions!$B$16,Assumptions!$B$17))) -> 0.14 | G9: =ROUND(MAX(I8,1)*F9,0) -> 2 | H9: =ROUND(I8*Assumptions!$B$18,0) -> 0 | I9: =MIN(I8+G9-H9,E9) -> 16 | J9: =Assumptions!$B$22 -> 0.55 | K9: =I9*J9 -> 8.8 | L9: =Assumptions!$B$10*(1-Assumptions!$B$12)+Assumptions!$B$11*Assumptions!$B$12 -> 46.06 | M9: =K9*L9 -> 405.328 | N9: =((IF(A9<=Assumptions!$B$91,Assumptions!$B$90,IF(A9>=Assumptions!$B$92,1,Assumptions!$B$90+(1-Assumptions!$B$90)*(A9-Assumptions!$B$91)/(Assumptions!$B$92-Assumptions!$B$91))))*Assumptions!$B$81*Assumptions!$B$75+Assumptions!$B$82)*(1+Assumptions!$B$83)/12 -> 5430.5556 | O9: =M9*Assumptions!$B$33 -> 344.5288 | P9: =O9-N9 -> -5086.0268 | Q9: =IF(A9>=Assumptions!$B$45,A9-Assumptions!$B$45+1,"") | R9: =IF(Q9="","Not yet launched",IF(Q9<=6,"CP1: Launch",IF(Q9<=18,"CP2: Scale",IF(Q9<=36,"CP3: Mature","CP4: Steady")))) -> Not yet launched | S9: =IF(Q9="",0,Assumptions!$B$46) -> 0 | T9: =IF(Q9="",0,IF(Q9<=6,Assumptions!$B$14,IF(Q9<=18,Assumptions!$B$15,IF(Q9<=36,Assumptions!$B$16,Assumptions!$B$17)))) -> 0 | U9: =IF(Q9="",0,IF(Q9=1,Assumptions!$B$65,ROUND(MAX(W8,1)*T9,0))) -> 0 | V9: =IF(Q9="",0,ROUND(W8*Assumptions!$B$49,0)) -> 0 | W9: =IF(Q9="",0,MIN(W8+U9-V9,S9)) -> 0 | X9: =IF(Q9="",0,Assumptions!$B$54) -> 0 | Y9: =W9*X9 -> 0 | Z9: =L9 -> 46.06 | AA9: =Y9*Z9 -> 0 | AB9: =IF(A9=Assumptions!$B$45,Assumptions!$B$47+Assumptions!$B$48,IF(A9>Assumptions!$B$45,Assumptions!$B$47,0)) -> 0 | AC9: =AA9*Assumptions!$B$33 -> 0 | AD9: =I9+W9 -> 16 | AE9: =M9+AA9 -> 405.328 | AF9: =N9+AB9+AJ9+AK9+AL9+Assumptions!$B$68 -> 5602.6906 | AG9: =O9+AC9 -> 344.5288 | AH9: =AG9-AF9 -> -5258.1618 | AI9: =IFERROR((AD9-AD8)/AD8,"") -> 0.14285714 | AJ9: =MAX(Assumptions!$B$71,Assumptions!$B$69*0.5^(A9/Assumptions!$B$70))+Assumptions!$B$72*(K9+Y9) -> 122.13508 | AK9: =IF(AND(Assumptions!$B$76=1,A9>=Assumptions!$B$77),Assumptions!$B$78/12,0) -> 0 | AL9: =IF(AND(Assumptions!$B$86=1,Q9<>""),Assumptions!$B$87/12,0) -> 0
A10: 9 | B10: Apr 2027 | C10: =IF(A10<=12,1,IF(A10<=24,2,IF(A10<=36,3,4))) -> 1 | D10: =IF(A10<=6,"P1: Pilot->Seed",IF(A10<=18,"P2: Scale/Series A",IF(A10<=36,"P3: Post-Series A","P4: Maturity"))) -> P2: Scale/Series A | E10: =IF(C10=1,Assumptions!$B$5,IF(C10=2,Assumptions!$B$6,IF(C10=3,Assumptions!$B$7,Assumptions!$B$8))) -> 1200 | F10: =IF(A10<=6,Assumptions!$B$14,IF(A10<=18,Assumptions!$B$15,IF(A10<=36,Assumptions!$B$16,Assumptions!$B$17))) -> 0.14 | G10: =ROUND(MAX(I9,1)*F10,0) -> 2 | H10: =ROUND(I9*Assumptions!$B$18,0) -> 0 | I10: =MIN(I9+G10-H10,E10) -> 18 | J10: =Assumptions!$B$23 -> 0.85 | K10: =I10*J10 -> 15.3 | L10: =Assumptions!$B$10*(1-Assumptions!$B$12)+Assumptions!$B$11*Assumptions!$B$12 -> 46.06 | M10: =K10*L10 -> 704.718 | N10: =((IF(A10<=Assumptions!$B$91,Assumptions!$B$90,IF(A10>=Assumptions!$B$92,1,Assumptions!$B$90+(1-Assumptions!$B$90)*(A10-Assumptions!$B$91)/(Assumptions!$B$92-Assumptions!$B$91))))*Assumptions!$B$81*Assumptions!$B$75+Assumptions!$B$82)*(1+Assumptions!$B$83)/12 -> 7506.9444 | O10: =M10*Assumptions!$B$33 -> 599.0103 | P10: =O10-N10 -> -6907.9341 | Q10: =IF(A10>=Assumptions!$B$45,A10-Assumptions!$B$45+1,"") | R10: =IF(Q10="","Not yet launched",IF(Q10<=6,"CP1: Launch",IF(Q10<=18,"CP2: Scale",IF(Q10<=36,"CP3: Mature","CP4: Steady")))) -> Not yet launched | S10: =IF(Q10="",0,Assumptions!$B$46) -> 0 | T10: =IF(Q10="",0,IF(Q10<=6,Assumptions!$B$14,IF(Q10<=18,Assumptions!$B$15,IF(Q10<=36,Assumptions!$B$16,Assumptions!$B$17)))) -> 0 | U10: =IF(Q10="",0,IF(Q10=1,Assumptions!$B$65,ROUND(MAX(W9,1)*T10,0))) -> 0 | V10: =IF(Q10="",0,ROUND(W9*Assumptions!$B$49,0)) -> 0 | W10: =IF(Q10="",0,MIN(W9+U10-V10,S10)) -> 0 | X10: =IF(Q10="",0,Assumptions!$B$55) -> 0 | Y10: =W10*X10 -> 0 | Z10: =L10 -> 46.06 | AA10: =Y10*Z10 -> 0 | AB10: =IF(A10=Assumptions!$B$45,Assumptions!$B$47+Assumptions!$B$48,IF(A10>Assumptions!$B$45,Assumptions!$B$47,0)) -> 0 | AC10: =AA10*Assumptions!$B$33 -> 0 | AD10: =I10+W10 -> 18 | AE10: =M10+AA10 -> 704.718 | AF10: =N10+AB10+AJ10+AK10+AL10+Assumptions!$B$68 -> 7668.3655 | AG10: =O10+AC10 -> 599.0103 | AH10: =AG10-AF10 -> -7069.3552 | AI10: =IFERROR((AD10-AD9)/AD9,"") -> 0.125 | AJ10: =MAX(Assumptions!$B$71,Assumptions!$B$69*0.5^(A10/Assumptions!$B$70))+Assumptions!$B$72*(K10+Y10) -> 111.42102 | AK10: =IF(AND(Assumptions!$B$76=1,A10>=Assumptions!$B$77),Assumptions!$B$78/12,0) -> 0 | AL10: =IF(AND(Assumptions!$B$86=1,Q10<>""),Assumptions!$B$87/12,0) -> 0
A11: 10 | B11: May 2027 | C11: =IF(A11<=12,1,IF(A11<=24,2,IF(A11<=36,3,4))) -> 1 | D11: =IF(A11<=6,"P1: Pilot->Seed",IF(A11<=18,"P2: Scale/Series A",IF(A11<=36,"P3: Post-Series A","P4: Maturity"))) -> P2: Scale/Series A | E11: =IF(C11=1,Assumptions!$B$5,IF(C11=2,Assumptions!$B$6,IF(C11=3,Assumptions!$B$7,Assumptions!$B$8))) -> 1200 | F11: =IF(A11<=6,Assumptions!$B$14,IF(A11<=18,Assumptions!$B$15,IF(A11<=36,Assumptions!$B$16,Assumptions!$B$17))) -> 0.14 | G11: =ROUND(MAX(I10,1)*F11,0) -> 3 | H11: =ROUND(I10*Assumptions!$B$18,0) -> 0 | I11: =MIN(I10+G11-H11,E11) -> 21 | J11: =Assumptions!$B$24 -> 1 | K11: =I11*J11 -> 21 | L11: =Assumptions!$B$10*(1-Assumptions!$B$12)+Assumptions!$B$11*Assumptions!$B$12 -> 46.06 | M11: =K11*L11 -> 967.26 | N11: =((IF(A11<=Assumptions!$B$91,Assumptions!$B$90,IF(A11>=Assumptions!$B$92,1,Assumptions!$B$90+(1-Assumptions!$B$90)*(A11-Assumptions!$B$91)/(Assumptions!$B$92-Assumptions!$B$91))))*Assumptions!$B$81*Assumptions!$B$75+Assumptions!$B$82)*(1+Assumptions!$B$83)/12 -> 9583.3333 | O11: =M11*Assumptions!$B$33 -> 822.171 | P11: =O11-N11 -> -8761.1623 | Q11: =IF(A11>=Assumptions!$B$45,A11-Assumptions!$B$45+1,"") | R11: =IF(Q11="","Not yet launched",IF(Q11<=6,"CP1: Launch",IF(Q11<=18,"CP2: Scale",IF(Q11<=36,"CP3: Mature","CP4: Steady")))) -> Not yet launched | S11: =IF(Q11="",0,Assumptions!$B$46) -> 0 | T11: =IF(Q11="",0,IF(Q11<=6,Assumptions!$B$14,IF(Q11<=18,Assumptions!$B$15,IF(Q11<=36,Assumptions!$B$16,Assumptions!$B$17)))) -> 0 | U11: =IF(Q11="",0,IF(Q11=1,Assumptions!$B$65,ROUND(MAX(W10,1)*T11,0))) -> 0 | V11: =IF(Q11="",0,ROUND(W10*Assumptions!$B$49,0)) -> 0 | W11: =IF(Q11="",0,MIN(W10+U11-V11,S11)) -> 0 | X11: =IF(Q11="",0,Assumptions!$B$56) -> 0 | Y11: =W11*X11 -> 0 | Z11: =L11 -> 46.06 | AA11: =Y11*Z11 -> 0 | AB11: =IF(A11=Assumptions!$B$45,Assumptions!$B$47+Assumptions!$B$48,IF(A11>Assumptions!$B$45,Assumptions!$B$47,0)) -> 0 | AC11: =AA11*Assumptions!$B$33 -> 0 | AD11: =I11+W11 -> 21 | AE11: =M11+AA11 -> 967.26 | AF11: =N11+AB11+AJ11+AK11+AL11+Assumptions!$B$68 -> 9735.1774 | AG11: =O11+AC11 -> 822.171 | AH11: =AG11-AF11 -> -8913.0064 | AI11: =IFERROR((AD11-AD10)/AD10,"") -> 0.16666667 | AJ11: =MAX(Assumptions!$B$71,Assumptions!$B$69*0.5^(A11/Assumptions!$B$70))+Assumptions!$B$72*(K11+Y11) -> 101.84408 | AK11: =IF(AND(Assumptions!$B$76=1,A11>=Assumptions!$B$77),Assumptions!$B$78/12,0) -> 0 | AL11: =IF(AND(Assumptions!$B$86=1,Q11<>""),Assumptions!$B$87/12,0) -> 0
A12: 11 | B12: Jun 2027 | C12: =IF(A12<=12,1,IF(A12<=24,2,IF(A12<=36,3,4))) -> 1 | D12: =IF(A12<=6,"P1: Pilot->Seed",IF(A12<=18,"P2: Scale/Series A",IF(A12<=36,"P3: Post-Series A","P4: Maturity"))) -> P2: Scale/Series A | E12: =IF(C12=1,Assumptions!$B$5,IF(C12=2,Assumptions!$B$6,IF(C12=3,Assumptions!$B$7,Assumptions!$B$8))) -> 1200 | F12: =IF(A12<=6,Assumptions!$B$14,IF(A12<=18,Assumptions!$B$15,IF(A12<=36,Assumptions!$B$16,Assumptions!$B$17))) -> 0.14 | G12: =ROUND(MAX(I11,1)*F12,0) -> 3 | H12: =ROUND(I11*Assumptions!$B$18,0) -> 0 | I12: =MIN(I11+G12-H12,E12) -> 24 | J12: =Assumptions!$B$25 -> 1 | K12: =I12*J12 -> 24 | L12: =Assumptions!$B$10*(1-Assumptions!$B$12)+Assumptions!$B$11*Assumptions!$B$12 -> 46.06 | M12: =K12*L12 -> 1105.44 | N12: =((IF(A12<=Assumptions!$B$91,Assumptions!$B$90,IF(A12>=Assumptions!$B$92,1,Assumptions!$B$90+(1-Assumptions!$B$90)*(A12-Assumptions!$B$91)/(Assumptions!$B$92-Assumptions!$B$91))))*Assumptions!$B$81*Assumptions!$B$75+Assumptions!$B$82)*(1+Assumptions!$B$83)/12 -> 11659.722 | O12: =M12*Assumptions!$B$33 -> 939.624 | P12: =O12-N12 -> -10720.098 | Q12: =IF(A12>=Assumptions!$B$45,A12-Assumptions!$B$45+1,"") | R12: =IF(Q12="","Not yet launched",IF(Q12<=6,"CP1: Launch",IF(Q12<=18,"CP2: Scale",IF(Q12<=36,"CP3: Mature","CP4: Steady")))) -> Not yet launched | S12: =IF(Q12="",0,Assumptions!$B$46) -> 0 | T12: =IF(Q12="",0,IF(Q12<=6,Assumptions!$B$14,IF(Q12<=18,Assumptions!$B$15,IF(Q12<=36,Assumptions!$B$16,Assumptions!$B$17)))) -> 0 | U12: =IF(Q12="",0,IF(Q12=1,Assumptions!$B$65,ROUND(MAX(W11,1)*T12,0))) -> 0 | V12: =IF(Q12="",0,ROUND(W11*Assumptions!$B$49,0)) -> 0 | W12: =IF(Q12="",0,MIN(W11+U12-V12,S12)) -> 0 | X12: =IF(Q12="",0,Assumptions!$B$57) -> 0 | Y12: =W12*X12 -> 0 | Z12: =L12 -> 46.06 | AA12: =Y12*Z12 -> 0 | AB12: =IF(A12=Assumptions!$B$45,Assumptions!$B$47+Assumptions!$B$48,IF(A12>Assumptions!$B$45,Assumptions!$B$47,0)) -> 0 | AC12: =AA12*Assumptions!$B$33 -> 0 | AD12: =I12+W12 -> 24 | AE12: =M12+AA12 -> 1105.44 | AF12: =N12+AB12+AJ12+AK12+AL12+Assumptions!$B$68 -> 11802.307 | AG12: =O12+AC12 -> 939.624 | AH12: =AG12-AF12 -> -10862.683 | AI12: =IFERROR((AD12-AD11)/AD11,"") -> 0.14285714 | AJ12: =MAX(Assumptions!$B$71,Assumptions!$B$69*0.5^(A12/Assumptions!$B$70))+Assumptions!$B$72*(K12+Y12) -> 92.584654 | AK12: =IF(AND(Assumptions!$B$76=1,A12>=Assumptions!$B$77),Assumptions!$B$78/12,0) -> 0 | AL12: =IF(AND(Assumptions!$B$86=1,Q12<>""),Assumptions!$B$87/12,0) -> 0
A13: 12 | B13: Jul 2027 | C13: =IF(A13<=12,1,IF(A13<=24,2,IF(A13<=36,3,4))) -> 1 | D13: =IF(A13<=6,"P1: Pilot->Seed",IF(A13<=18,"P2: Scale/Series A",IF(A13<=36,"P3: Post-Series A","P4: Maturity"))) -> P2: Scale/Series A | E13: =IF(C13=1,Assumptions!$B$5,IF(C13=2,Assumptions!$B$6,IF(C13=3,Assumptions!$B$7,Assumptions!$B$8))) -> 1200 | F13: =IF(A13<=6,Assumptions!$B$14,IF(A13<=18,Assumptions!$B$15,IF(A13<=36,Assumptions!$B$16,Assumptions!$B$17))) -> 0.14 | G13: =ROUND(MAX(I12,1)*F13,0) -> 3 | H13: =ROUND(I12*Assumptions!$B$18,0) -> 0 | I13: =MIN(I12+G13-H13,E13) -> 27 | J13: =Assumptions!$B$26 -> 1 | K13: =I13*J13 -> 27 | L13: =Assumptions!$B$10*(1-Assumptions!$B$12)+Assumptions!$B$11*Assumptions!$B$12 -> 46.06 | M13: =K13*L13 -> 1243.62 | N13: =((IF(A13<=Assumptions!$B$91,Assumptions!$B$90,IF(A13>=Assumptions!$B$92,1,Assumptions!$B$90+(1-Assumptions!$B$90)*(A13-Assumptions!$B$91)/(Assumptions!$B$92-Assumptions!$B$91))))*Assumptions!$B$81*Assumptions!$B$75+Assumptions!$B$82)*(1+Assumptions!$B$83)/12 -> 13736.111 | O13: =M13*Assumptions!$B$33 -> 1057.077 | P13: =O13-N13 -> -12679.034 | Q13: =IF(A13>=Assumptions!$B$45,A13-Assumptions!$B$45+1,"") | R13: =IF(Q13="","Not yet launched",IF(Q13<=6,"CP1: Launch",IF(Q13<=18,"CP2: Scale",IF(Q13<=36,"CP3: Mature","CP4: Steady")))) -> Not yet launched | S13: =IF(Q13="",0,Assumptions!$B$46) -> 0 | T13: =IF(Q13="",0,IF(Q13<=6,Assumptions!$B$14,IF(Q13<=18,Assumptions!$B$15,IF(Q13<=36,Assumptions!$B$16,Assumptions!$B$17)))) -> 0 | U13: =IF(Q13="",0,IF(Q13=1,Assumptions!$B$65,ROUND(MAX(W12,1)*T13,0))) -> 0 | V13: =IF(Q13="",0,ROUND(W12*Assumptions!$B$49,0)) -> 0 | W13: =IF(Q13="",0,MIN(W12+U13-V13,S13)) -> 0 | X13: =IF(Q13="",0,Assumptions!$B$58) -> 0 | Y13: =W13*X13 -> 0 | Z13: =L13 -> 46.06 | AA13: =Y13*Z13 -> 0 | AB13: =IF(A13=Assumptions!$B$45,Assumptions!$B$47+Assumptions!$B$48,IF(A13>Assumptions!$B$45,Assumptions!$B$47,0)) -> 0 | AC13: =AA13*Assumptions!$B$33 -> 0 | AD13: =I13+W13 -> 27 | AE13: =M13+AA13 -> 1243.62 | AF13: =N13+AB13+AJ13+AK13+AL13+Assumptions!$B$68 -> 13870.561 | AG13: =O13+AC13 -> 1057.077 | AH13: =AG13-AF13 -> -12813.484 | AI13: =IFERROR((AD13-AD12)/AD12,"") -> 0.125 | AJ13: =MAX(Assumptions!$B$71,Assumptions!$B$69*0.5^(A13/Assumptions!$B$70))+Assumptions!$B$72*(K13+Y13) -> 84.45 | AK13: =IF(AND(Assumptions!$B$76=1,A13>=Assumptions!$B$77),Assumptions!$B$78/12,0) -> 0 | AL13: =IF(AND(Assumptions!$B$86=1,Q13<>""),Assumptions!$B$87/12,0) -> 0
A14: 13 | B14: Aug 2027 | C14: =IF(A14<=12,1,IF(A14<=24,2,IF(A14<=36,3,4))) -> 2 | D14: =IF(A14<=6,"P1: Pilot->Seed",IF(A14<=18,"P2: Scale/Series A",IF(A14<=36,"P3: Post-Series A","P4: Maturity"))) -> P2: Scale/Series A | E14: =IF(C14=1,Assumptions!$B$5,IF(C14=2,Assumptions!$B$6,IF(C14=3,Assumptions!$B$7,Assumptions!$B$8))) -> 4500 | F14: =IF(A14<=6,Assumptions!$B$14,IF(A14<=18,Assumptions!$B$15,IF(A14<=36,Assumptions!$B$16,Assumptions!$B$17))) -> 0.14 | G14: =ROUND(MAX(I13,1)*F14,0) -> 4 | H14: =ROUND(I13*Assumptions!$B$18,0) -> 1 | I14: =MIN(I13+G14-H14,E14) -> 30 | J14: =Assumptions!$B$27 -> 1 | K14: =I14*J14 -> 30 | L14: =Assumptions!$B$10*(1-Assumptions!$B$12)+Assumptions!$B$11*Assumptions!$B$12 -> 46.06 | M14: =K14*L14 -> 1381.8 | N14: =((IF(A14<=Assumptions!$B$91,Assumptions!$B$90,IF(A14>=Assumptions!$B$92,1,Assumptions!$B$90+(1-Assumptions!$B$90)*(A14-Assumptions!$B$91)/(Assumptions!$B$92-Assumptions!$B$91))))*Assumptions!$B$81*Assumptions!$B$75+Assumptions!$B$82)*(1+Assumptions!$B$83)/12 -> 15812.5 | O14: =M14*Assumptions!$B$33 -> 1174.53 | P14: =O14-N14 -> -14637.97 | Q14: =IF(A14>=Assumptions!$B$45,A14-Assumptions!$B$45+1,"") -> 1 | R14: =IF(Q14="","Not yet launched",IF(Q14<=6,"CP1: Launch",IF(Q14<=18,"CP2: Scale",IF(Q14<=36,"CP3: Mature","CP4: Steady")))) -> CP1: Launch | S14: =IF(Q14="",0,Assumptions!$B$46) -> 2000 | T14: =IF(Q14="",0,IF(Q14<=6,Assumptions!$B$14,IF(Q14<=18,Assumptions!$B$15,IF(Q14<=36,Assumptions!$B$16,Assumptions!$B$17)))) -> 0.35 | U14: =IF(Q14="",0,IF(Q14=1,Assumptions!$B$65,ROUND(MAX(W13,1)*T14,0))) -> 2 | V14: =IF(Q14="",0,ROUND(W13*Assumptions!$B$49,0)) -> 0 | W14: =IF(Q14="",0,MIN(W13+U14-V14,S14)) -> 2 | X14: =IF(Q14="",0,Assumptions!$B$59) -> 0.35 | Y14: =W14*X14 -> 0.7 | Z14: =L14 -> 46.06 | AA14: =Y14*Z14 -> 32.242 | AB14: =IF(A14=Assumptions!$B$45,Assumptions!$B$47+Assumptions!$B$48,IF(A14>Assumptions!$B$45,Assumptions!$B$47,0)) -> 40050 | AC14: =AA14*Assumptions!$B$33 -> 27.4057 | AD14: =I14+W14 -> 32 | AE14: =M14+AA14 -> 1414.042 | AF14: =N14+AB14+AJ14+AK14+AL14+Assumptions!$B$68 -> 60581.578 | AG14: =O14+AC14 -> 1201.9357 | AH14: =AG14-AF14 -> -59379.643 | AI14: =IFERROR((AD14-AD13)/AD13,"") -> 0.18518519 | AJ14: =MAX(Assumptions!$B$71,Assumptions!$B$69*0.5^(A14/Assumptions!$B$70))+Assumptions!$B$72*(K14+Y14) -> 85.745 | AK14: =IF(AND(Assumptions!$B$76=1,A14>=Assumptions!$B$77),Assumptions!$B$78/12,0) -> 4583.3333 | AL14: =IF(AND(Assumptions!$B$86=1,Q14<>""),Assumptions!$B$87/12,0) -> 0
A15: 14 | B15: Sep 2027 | C15: =IF(A15<=12,1,IF(A15<=24,2,IF(A15<=36,3,4))) -> 2 | D15: =IF(A15<=6,"P1: Pilot->Seed",IF(A15<=18,"P2: Scale/Series A",IF(A15<=36,"P3: Post-Series A","P4: Maturity"))) -> P2: Scale/Series A | E15: =IF(C15=1,Assumptions!$B$5,IF(C15=2,Assumptions!$B$6,IF(C15=3,Assumptions!$B$7,Assumptions!$B$8))) -> 4500 | F15: =IF(A15<=6,Assumptions!$B$14,IF(A15<=18,Assumptions!$B$15,IF(A15<=36,Assumptions!$B$16,Assumptions!$B$17))) -> 0.14 | G15: =ROUND(MAX(I14,1)*F15,0) -> 4 | H15: =ROUND(I14*Assumptions!$B$18,0) -> 1 | I15: =MIN(I14+G15-H15,E15) -> 33 | J15: =Assumptions!$B$28 -> 1 | K15: =I15*J15 -> 33 | L15: =Assumptions!$B$10*(1-Assumptions!$B$12)+Assumptions!$B$11*Assumptions!$B$12 -> 46.06 | M15: =K15*L15 -> 1519.98 | N15: =((IF(A15<=Assumptions!$B$91,Assumptions!$B$90,IF(A15>=Assumptions!$B$92,1,Assumptions!$B$90+(1-Assumptions!$B$90)*(A15-Assumptions!$B$91)/(Assumptions!$B$92-Assumptions!$B$91))))*Assumptions!$B$81*Assumptions!$B$75+Assumptions!$B$82)*(1+Assumptions!$B$83)/12 -> 17888.889 | O15: =M15*Assumptions!$B$33 -> 1291.983 | P15: =O15-N15 -> -16596.906 | Q15: =IF(A15>=Assumptions!$B$45,A15-Assumptions!$B$45+1,"") -> 2 | R15: =IF(Q15="","Not yet launched",IF(Q15<=6,"CP1: Launch",IF(Q15<=18,"CP2: Scale",IF(Q15<=36,"CP3: Mature","CP4: Steady")))) -> CP1: Launch | S15: =IF(Q15="",0,Assumptions!$B$46) -> 2000 | T15: =IF(Q15="",0,IF(Q15<=6,Assumptions!$B$14,IF(Q15<=18,Assumptions!$B$15,IF(Q15<=36,Assumptions!$B$16,Assumptions!$B$17)))) -> 0.35 | U15: =IF(Q15="",0,IF(Q15=1,Assumptions!$B$65,ROUND(MAX(W14,1)*T15,0))) -> 1 | V15: =IF(Q15="",0,ROUND(W14*Assumptions!$B$49,0)) -> 0 | W15: =IF(Q15="",0,MIN(W14+U15-V15,S15)) -> 3 | X15: =IF(Q15="",0,Assumptions!$B$60) -> 0.35 | Y15: =W15*X15 -> 1.05 | Z15: =L15 -> 46.06 | AA15: =Y15*Z15 -> 48.363 | AB15: =IF(A15=Assumptions!$B$45,Assumptions!$B$47+Assumptions!$B$48,IF(A15>Assumptions!$B$45,Assumptions!$B$47,0)) -> 50 | AC15: =AA15*Assumptions!$B$33 -> 41.10855 | AD15: =I15+W15 -> 36 | AE15: =M15+AA15 -> 1568.343 | AF15: =N15+AB15+AJ15+AK15+AL15+Assumptions!$B$68 -> 22659.14 | AG15: =O15+AC15 -> 1333.0916 | AH15: =AG15-AF15 -> -21326.048 | AI15: =IFERROR((AD15-AD14)/AD14,"") -> 0.125 | AJ15: =MAX(Assumptions!$B$71,Assumptions!$B$69*0.5^(A15/Assumptions!$B$70))+Assumptions!$B$72*(K15+Y15) -> 86.9175 | AK15: =IF(AND(Assumptions!$B$76=1,A15>=Assumptions!$B$77),Assumptions!$B$78/12,0) -> 4583.3333 | AL15: =IF(AND(Assumptions!$B$86=1,Q15<>""),Assumptions!$B$87/12,0) -> 0
A16: 15 | B16: Oct 2027 | C16: =IF(A16<=12,1,IF(A16<=24,2,IF(A16<=36,3,4))) -> 2 | D16: =IF(A16<=6,"P1: Pilot->Seed",IF(A16<=18,"P2: Scale/Series A",IF(A16<=36,"P3: Post-Series A","P4: Maturity"))) -> P2: Scale/Series A | E16: =IF(C16=1,Assumptions!$B$5,IF(C16=2,Assumptions!$B$6,IF(C16=3,Assumptions!$B$7,Assumptions!$B$8))) -> 4500 | F16: =IF(A16<=6,Assumptions!$B$14,IF(A16<=18,Assumptions!$B$15,IF(A16<=36,Assumptions!$B$16,Assumptions!$B$17))) -> 0.14 | G16: =ROUND(MAX(I15,1)*F16,0) -> 5 | H16: =ROUND(I15*Assumptions!$B$18,0) -> 1 | I16: =MIN(I15+G16-H16,E16) -> 37 | J16: =Assumptions!$B$29 -> 0.85 | K16: =I16*J16 -> 31.45 | L16: =Assumptions!$B$10*(1-Assumptions!$B$12)+Assumptions!$B$11*Assumptions!$B$12 -> 46.06 | M16: =K16*L16 -> 1448.587 | N16: =((IF(A16<=Assumptions!$B$91,Assumptions!$B$90,IF(A16>=Assumptions!$B$92,1,Assumptions!$B$90+(1-Assumptions!$B$90)*(A16-Assumptions!$B$91)/(Assumptions!$B$92-Assumptions!$B$91))))*Assumptions!$B$81*Assumptions!$B$75+Assumptions!$B$82)*(1+Assumptions!$B$83)/12 -> 19965.278 | O16: =M16*Assumptions!$B$33 -> 1231.299 | P16: =O16-N16 -> -18733.979 | Q16: =IF(A16>=Assumptions!$B$45,A16-Assumptions!$B$45+1,"") -> 3 | R16: =IF(Q16="","Not yet launched",IF(Q16<=6,"CP1: Launch",IF(Q16<=18,"CP2: Scale",IF(Q16<=36,"CP3: Mature","CP4: Steady")))) -> CP1: Launch | S16: =IF(Q16="",0,Assumptions!$B$46) -> 2000 | T16: =IF(Q16="",0,IF(Q16<=6,Assumptions!$B$14,IF(Q16<=18,Assumptions!$B$15,IF(Q16<=36,Assumptions!$B$16,Assumptions!$B$17)))) -> 0.35 | U16: =IF(Q16="",0,IF(Q16=1,Assumptions!$B$65,ROUND(MAX(W15,1)*T16,0))) -> 1 | V16: =IF(Q16="",0,ROUND(W15*Assumptions!$B$49,0)) -> 0 | W16: =IF(Q16="",0,MIN(W15+U16-V16,S16)) -> 4 | X16: =IF(Q16="",0,Assumptions!$B$61) -> 0.4 | Y16: =W16*X16 -> 1.6 | Z16: =L16 -> 46.06 | AA16: =Y16*Z16 -> 73.696 | AB16: =IF(A16=Assumptions!$B$45,Assumptions!$B$47+Assumptions!$B$48,IF(A16>Assumptions!$B$45,Assumptions!$B$47,0)) -> 50 | AC16: =AA16*Assumptions!$B$33 -> 62.6416 | AD16: =I16+W16 -> 41 | AE16: =M16+AA16 -> 1522.283 | AF16: =N16+AB16+AJ16+AK16+AL16+Assumptions!$B$68 -> 24735.179 | AG16: =O16+AC16 -> 1293.9406 | AH16: =AG16-AF16 -> -23441.238 | AI16: =IFERROR((AD16-AD15)/AD15,"") -> 0.13888889 | AJ16: =MAX(Assumptions!$B$71,Assumptions!$B$69*0.5^(A16/Assumptions!$B$70))+Assumptions!$B$72*(K16+Y16) -> 86.5675 | AK16: =IF(AND(Assumptions!$B$76=1,A16>=Assumptions!$B$77),Assumptions!$B$78/12,0) -> 4583.3333 | AL16: =IF(AND(Assumptions!$B$86=1,Q16<>""),Assumptions!$B$87/12,0) -> 0
A17: 16 | B17: Nov 2027 | C17: =IF(A17<=12,1,IF(A17<=24,2,IF(A17<=36,3,4))) -> 2 | D17: =IF(A17<=6,"P1: Pilot->Seed",IF(A17<=18,"P2: Scale/Series A",IF(A17<=36,"P3: Post-Series A","P4: Maturity"))) -> P2: Scale/Series A | E17: =IF(C17=1,Assumptions!$B$5,IF(C17=2,Assumptions!$B$6,IF(C17=3,Assumptions!$B$7,Assumptions!$B$8))) -> 4500 | F17: =IF(A17<=6,Assumptions!$B$14,IF(A17<=18,Assumptions!$B$15,IF(A17<=36,Assumptions!$B$16,Assumptions!$B$17))) -> 0.14 | G17: =ROUND(MAX(I16,1)*F17,0) -> 5 | H17: =ROUND(I16*Assumptions!$B$18,0) -> 1 | I17: =MIN(I16+G17-H17,E17) -> 41 | J17: =Assumptions!$B$30 -> 0.45 | K17: =I17*J17 -> 18.45 | L17: =Assumptions!$B$10*(1-Assumptions!$B$12)+Assumptions!$B$11*Assumptions!$B$12 -> 46.06 | M17: =K17*L17 -> 849.807 | N17: =((IF(A17<=Assumptions!$B$91,Assumptions!$B$90,IF(A17>=Assumptions!$B$92,1,Assumptions!$B$90+(1-Assumptions!$B$90)*(A17-Assumptions!$B$91)/(Assumptions!$B$92-Assumptions!$B$91))))*Assumptions!$B$81*Assumptions!$B$75+Assumptions!$B$82)*(1+Assumptions!$B$83)/12 -> 22041.667 | O17: =M17*Assumptions!$B$33 -> 722.33595 | P17: =O17-N17 -> -21319.331 | Q17: =IF(A17>=Assumptions!$B$45,A17-Assumptions!$B$45+1,"") -> 4 | R17: =IF(Q17="","Not yet launched",IF(Q17<=6,"CP1: Launch",IF(Q17<=18,"CP2: Scale",IF(Q17<=36,"CP3: Mature","CP4: Steady")))) -> CP1: Launch | S17: =IF(Q17="",0,Assumptions!$B$46) -> 2000 | T17: =IF(Q17="",0,IF(Q17<=6,Assumptions!$B$14,IF(Q17<=18,Assumptions!$B$15,IF(Q17<=36,Assumptions!$B$16,Assumptions!$B$17)))) -> 0.35 | U17: =IF(Q17="",0,IF(Q17=1,Assumptions!$B$65,ROUND(MAX(W16,1)*T17,0))) -> 1 | V17: =IF(Q17="",0,ROUND(W16*Assumptions!$B$49,0)) -> 0 | W17: =IF(Q17="",0,MIN(W16+U17-V17,S17)) -> 5 | X17: =IF(Q17="",0,Assumptions!$B$62) -> 0.55 | Y17: =W17*X17 -> 2.75 | Z17: =L17 -> 46.06 | AA17: =Y17*Z17 -> 126.665 | AB17: =IF(A17=Assumptions!$B$45,Assumptions!$B$47+Assumptions!$B$48,IF(A17>Assumptions!$B$45,Assumptions!$B$47,0)) -> 50 | AC17: =AA17*Assumptions!$B$33 -> 107.66525 | AD17: =I17+W17 -> 46 | AE17: =M17+AA17 -> 976.472 | AF17: =N17+AB17+AJ17+AK17+AL17+Assumptions!$B$68 -> 26807.42 | AG17: =O17+AC17 -> 830.0012 | AH17: =AG17-AF17 -> -25977.419 | AI17: =IFERROR((AD17-AD16)/AD16,"") -> 0.12195122 | AJ17: =MAX(Assumptions!$B$71,Assumptions!$B$69*0.5^(A17/Assumptions!$B$70))+Assumptions!$B$72*(K17+Y17) -> 82.42 | AK17: =IF(AND(Assumptions!$B$76=1,A17>=Assumptions!$B$77),Assumptions!$B$78/12,0) -> 4583.3333 | AL17: =IF(AND(Assumptions!$B$86=1,Q17<>""),Assumptions!$B$87/12,0) -> 0
A18: 17 | B18: Dec 2027 | C18: =IF(A18<=12,1,IF(A18<=24,2,IF(A18<=36,3,4))) -> 2 | D18: =IF(A18<=6,"P1: Pilot->Seed",IF(A18<=18,"P2: Scale/Series A",IF(A18<=36,"P3: Post-Series A","P4: Maturity"))) -> P2: Scale/Series A | E18: =IF(C18=1,Assumptions!$B$5,IF(C18=2,Assumptions!$B$6,IF(C18=3,Assumptions!$B$7,Assumptions!$B$8))) -> 4500 | F18: =IF(A18<=6,Assumptions!$B$14,IF(A18<=18,Assumptions!$B$15,IF(A18<=36,Assumptions!$B$16,Assumptions!$B$17))) -> 0.14 | G18: =ROUND(MAX(I17,1)*F18,0) -> 6 | H18: =ROUND(I17*Assumptions!$B$18,0) -> 1 | I18: =MIN(I17+G18-H18,E18) -> 46 | J18: =Assumptions!$B$31 -> 0.35 | K18: =I18*J18 -> 16.1 | L18: =Assumptions!$B$10*(1-Assumptions!$B$12)+Assumptions!$B$11*Assumptions!$B$12 -> 46.06 | M18: =K18*L18 -> 741.566 | N18: =((IF(A18<=Assumptions!$B$91,Assumptions!$B$90,IF(A18>=Assumptions!$B$92,1,Assumptions!$B$90+(1-Assumptions!$B$90)*(A18-Assumptions!$B$91)/(Assumptions!$B$92-Assumptions!$B$91))))*Assumptions!$B$81*Assumptions!$B$75+Assumptions!$B$82)*(1+Assumptions!$B$83)/12 -> 24118.056 | O18: =M18*Assumptions!$B$33 -> 630.3311 | P18: =O18-N18 -> -23487.724 | Q18: =IF(A18>=Assumptions!$B$45,A18-Assumptions!$B$45+1,"") -> 5 | R18: =IF(Q18="","Not yet launched",IF(Q18<=6,"CP1: Launch",IF(Q18<=18,"CP2: Scale",IF(Q18<=36,"CP3: Mature","CP4: Steady")))) -> CP1: Launch | S18: =IF(Q18="",0,Assumptions!$B$46) -> 2000 | T18: =IF(Q18="",0,IF(Q18<=6,Assumptions!$B$14,IF(Q18<=18,Assumptions!$B$15,IF(Q18<=36,Assumptions!$B$16,Assumptions!$B$17)))) -> 0.35 | U18: =IF(Q18="",0,IF(Q18=1,Assumptions!$B$65,ROUND(MAX(W17,1)*T18,0))) -> 2 | V18: =IF(Q18="",0,ROUND(W17*Assumptions!$B$49,0)) -> 0 | W18: =IF(Q18="",0,MIN(W17+U18-V18,S18)) -> 7 | X18: =IF(Q18="",0,Assumptions!$B$63) -> 0.9 | Y18: =W18*X18 -> 6.3 | Z18: =L18 -> 46.06 | AA18: =Y18*Z18 -> 290.178 | AB18: =IF(A18=Assumptions!$B$45,Assumptions!$B$47+Assumptions!$B$48,IF(A18>Assumptions!$B$45,Assumptions!$B$47,0)) -> 50 | AC18: =AA18*Assumptions!$B$33 -> 246.6513 | AD18: =I18+W18 -> 53 | AE18: =M18+AA18 -> 1031.744 | AF18: =N18+AB18+AJ18+AK18+AL18+Assumptions!$B$68 -> 28884.229 | AG18: =O18+AC18 -> 876.9824 | AH18: =AG18-AF18 -> -28007.246 | AI18: =IFERROR((AD18-AD17)/AD17,"") -> 0.15217391 | AJ18: =MAX(Assumptions!$B$71,Assumptions!$B$69*0.5^(A18/Assumptions!$B$70))+Assumptions!$B$72*(K18+Y18) -> 82.84 | AK18: =IF(AND(Assumptions!$B$76=1,A18>=Assumptions!$B$77),Assumptions!$B$78/12,0) -> 4583.3333 | AL18: =IF(AND(Assumptions!$B$86=1,Q18<>""),Assumptions!$B$87/12,0) -> 0
A19: 18 | B19: Jan 2028 | C19: =IF(A19<=12,1,IF(A19<=24,2,IF(A19<=36,3,4))) -> 2 | D19: =IF(A19<=6,"P1: Pilot->Seed",IF(A19<=18,"P2: Scale/Series A",IF(A19<=36,"P3: Post-Series A","P4: Maturity"))) -> P2: Scale/Series A | E19: =IF(C19=1,Assumptions!$B$5,IF(C19=2,Assumptions!$B$6,IF(C19=3,Assumptions!$B$7,Assumptions!$B$8))) -> 4500 | F19: =IF(A19<=6,Assumptions!$B$14,IF(A19<=18,Assumptions!$B$15,IF(A19<=36,Assumptions!$B$16,Assumptions!$B$17))) -> 0.14 | G19: =ROUND(MAX(I18,1)*F19,0) -> 6 | H19: =ROUND(I18*Assumptions!$B$18,0) -> 1 | I19: =MIN(I18+G19-H19,E19) -> 51 | J19: =Assumptions!$B$20 -> 0.35 | K19: =I19*J19 -> 17.85 | L19: =Assumptions!$B$10*(1-Assumptions!$B$12)+Assumptions!$B$11*Assumptions!$B$12 -> 46.06 | M19: =K19*L19 -> 822.171 | N19: =((IF(A19<=Assumptions!$B$91,Assumptions!$B$90,IF(A19>=Assumptions!$B$92,1,Assumptions!$B$90+(1-Assumptions!$B$90)*(A19-Assumptions!$B$91)/(Assumptions!$B$92-Assumptions!$B$91))))*Assumptions!$B$81*Assumptions!$B$75+Assumptions!$B$82)*(1+Assumptions!$B$83)/12 -> 26194.444 | O19: =M19*Assumptions!$B$33 -> 698.84535 | P19: =O19-N19 -> -25495.599 | Q19: =IF(A19>=Assumptions!$B$45,A19-Assumptions!$B$45+1,"") -> 6 | R19: =IF(Q19="","Not yet launched",IF(Q19<=6,"CP1: Launch",IF(Q19<=18,"CP2: Scale",IF(Q19<=36,"CP3: Mature","CP4: Steady")))) -> CP1: Launch | S19: =IF(Q19="",0,Assumptions!$B$46) -> 2000 | T19: =IF(Q19="",0,IF(Q19<=6,Assumptions!$B$14,IF(Q19<=18,Assumptions!$B$15,IF(Q19<=36,Assumptions!$B$16,Assumptions!$B$17)))) -> 0.35 | U19: =IF(Q19="",0,IF(Q19=1,Assumptions!$B$65,ROUND(MAX(W18,1)*T19,0))) -> 2 | V19: =IF(Q19="",0,ROUND(W18*Assumptions!$B$49,0)) -> 0 | W19: =IF(Q19="",0,MIN(W18+U19-V19,S19)) -> 9 | X19: =IF(Q19="",0,Assumptions!$B$52) -> 1 | Y19: =W19*X19 -> 9 | Z19: =L19 -> 46.06 | AA19: =Y19*Z19 -> 414.54 | AB19: =IF(A19=Assumptions!$B$45,Assumptions!$B$47+Assumptions!$B$48,IF(A19>Assumptions!$B$45,Assumptions!$B$47,0)) -> 50 | AC19: =AA19*Assumptions!$B$33 -> 352.359 | AD19: =I19+W19 -> 60 | AE19: =M19+AA19 -> 1236.711 | AF19: =N19+AB19+AJ19+AK19+AL19+Assumptions!$B$68 -> 30962.175 | AG19: =O19+AC19 -> 1051.2043 | AH19: =AG19-AF19 -> -29910.971 | AI19: =IFERROR((AD19-AD18)/AD18,"") -> 0.13207547 | AJ19: =MAX(Assumptions!$B$71,Assumptions!$B$69*0.5^(A19/Assumptions!$B$70))+Assumptions!$B$72*(K19+Y19) -> 84.3975 | AK19: =IF(AND(Assumptions!$B$76=1,A19>=Assumptions!$B$77),Assumptions!$B$78/12,0) -> 4583.3333 | AL19: =IF(AND(Assumptions!$B$86=1,Q19<>""),Assumptions!$B$87/12,0) -> 0
A20: 19 | B20: Feb 2028 | C20: =IF(A20<=12,1,IF(A20<=24,2,IF(A20<=36,3,4))) -> 2 | D20: =IF(A20<=6,"P1: Pilot->Seed",IF(A20<=18,"P2: Scale/Series A",IF(A20<=36,"P3: Post-Series A","P4: Maturity"))) -> P3: Post-Series A | E20: =IF(C20=1,Assumptions!$B$5,IF(C20=2,Assumptions!$B$6,IF(C20=3,Assumptions!$B$7,Assumptions!$B$8))) -> 4500 | F20: =IF(A20<=6,Assumptions!$B$14,IF(A20<=18,Assumptions!$B$15,IF(A20<=36,Assumptions!$B$16,Assumptions!$B$17))) -> 0.08 | G20: =ROUND(MAX(I19,1)*F20,0) -> 4 | H20: =ROUND(I19*Assumptions!$B$18,0) -> 1 | I20: =MIN(I19+G20-H20,E20) -> 54 | J20: =Assumptions!$B$21 -> 0.35 | K20: =I20*J20 -> 18.9 | L20: =Assumptions!$B$10*(1-Assumptions!$B$12)+Assumptions!$B$11*Assumptions!$B$12 -> 46.06 | M20: =K20*L20 -> 870.534 | N20: =((IF(A20<=Assumptions!$B$91,Assumptions!$B$90,IF(A20>=Assumptions!$B$92,1,Assumptions!$B$90+(1-Assumptions!$B$90)*(A20-Assumptions!$B$91)/(Assumptions!$B$92-Assumptions!$B$91))))*Assumptions!$B$81*Assumptions!$B$75+Assumptions!$B$82)*(1+Assumptions!$B$83)/12 -> 28270.833 | O20: =M20*Assumptions!$B$33 -> 739.9539 | P20: =O20-N20 -> -27530.879 | Q20: =IF(A20>=Assumptions!$B$45,A20-Assumptions!$B$45+1,"") -> 7 | R20: =IF(Q20="","Not yet launched",IF(Q20<=6,"CP1: Launch",IF(Q20<=18,"CP2: Scale",IF(Q20<=36,"CP3: Mature","CP4: Steady")))) -> CP2: Scale | S20: =IF(Q20="",0,Assumptions!$B$46) -> 2000 | T20: =IF(Q20="",0,IF(Q20<=6,Assumptions!$B$14,IF(Q20<=18,Assumptions!$B$15,IF(Q20<=36,Assumptions!$B$16,Assumptions!$B$17)))) -> 0.14 | U20: =IF(Q20="",0,IF(Q20=1,Assumptions!$B$65,ROUND(MAX(W19,1)*T20,0))) -> 1 | V20: =IF(Q20="",0,ROUND(W19*Assumptions!$B$49,0)) -> 0 | W20: =IF(Q20="",0,MIN(W19+U20-V20,S20)) -> 10 | X20: =IF(Q20="",0,Assumptions!$B$53) -> 1 | Y20: =W20*X20 -> 10 | Z20: =L20 -> 46.06 | AA20: =Y20*Z20 -> 460.6 | AB20: =IF(A20=Assumptions!$B$45,Assumptions!$B$47+Assumptions!$B$48,IF(A20>Assumptions!$B$45,Assumptions!$B$47,0)) -> 50 | AC20: =AA20*Assumptions!$B$33 -> 391.51 | AD20: =I20+W20 -> 64 | AE20: =M20+AA20 -> 1331.134 | AF20: =N20+AB20+AJ20+AK20+AL20+Assumptions!$B$68 -> 33039.282 | AG20: =O20+AC20 -> 1131.4639 | AH20: =AG20-AF20 -> -31907.818 | AI20: =IFERROR((AD20-AD19)/AD19,"") -> 0.066666667 | AJ20: =MAX(Assumptions!$B$71,Assumptions!$B$69*0.5^(A20/Assumptions!$B$70))+Assumptions!$B$72*(K20+Y20) -> 85.115 | AK20: =IF(AND(Assumptions!$B$76=1,A20>=Assumptions!$B$77),Assumptions!$B$78/12,0) -> 4583.3333 | AL20: =IF(AND(Assumptions!$B$86=1,Q20<>""),Assumptions!$B$87/12,0) -> 0
A21: 20 | B21: Mar 2028 | C21: =IF(A21<=12,1,IF(A21<=24,2,IF(A21<=36,3,4))) -> 2 | D21: =IF(A21<=6,"P1: Pilot->Seed",IF(A21<=18,"P2: Scale/Series A",IF(A21<=36,"P3: Post-Series A","P4: Maturity"))) -> P3: Post-Series A | E21: =IF(C21=1,Assumptions!$B$5,IF(C21=2,Assumptions!$B$6,IF(C21=3,Assumptions!$B$7,Assumptions!$B$8))) -> 4500 | F21: =IF(A21<=6,Assumptions!$B$14,IF(A21<=18,Assumptions!$B$15,IF(A21<=36,Assumptions!$B$16,Assumptions!$B$17))) -> 0.08 | G21: =ROUND(MAX(I20,1)*F21,0) -> 4 | H21: =ROUND(I20*Assumptions!$B$18,0) -> 1 | I21: =MIN(I20+G21-H21,E21) -> 57 | J21: =Assumptions!$B$22 -> 0.55 | K21: =I21*J21 -> 31.35 | L21: =Assumptions!$B$10*(1-Assumptions!$B$12)+Assumptions!$B$11*Assumptions!$B$12 -> 46.06 | M21: =K21*L21 -> 1443.981 | N21: =((IF(A21<=Assumptions!$B$91,Assumptions!$B$90,IF(A21>=Assumptions!$B$92,1,Assumptions!$B$90+(1-Assumptions!$B$90)*(A21-Assumptions!$B$91)/(Assumptions!$B$92-Assumptions!$B$91))))*Assumptions!$B$81*Assumptions!$B$75+Assumptions!$B$82)*(1+Assumptions!$B$83)/12 -> 28270.833 | O21: =M21*Assumptions!$B$33 -> 1227.3838 | P21: =O21-N21 -> -27043.449 | Q21: =IF(A21>=Assumptions!$B$45,A21-Assumptions!$B$45+1,"") -> 8 | R21: =IF(Q21="","Not yet launched",IF(Q21<=6,"CP1: Launch",IF(Q21<=18,"CP2: Scale",IF(Q21<=36,"CP3: Mature","CP4: Steady")))) -> CP2: Scale | S21: =IF(Q21="",0,Assumptions!$B$46) -> 2000 | T21: =IF(Q21="",0,IF(Q21<=6,Assumptions!$B$14,IF(Q21<=18,Assumptions!$B$15,IF(Q21<=36,Assumptions!$B$16,Assumptions!$B$17)))) -> 0.14 | U21: =IF(Q21="",0,IF(Q21=1,Assumptions!$B$65,ROUND(MAX(W20,1)*T21,0))) -> 1 | V21: =IF(Q21="",0,ROUND(W20*Assumptions!$B$49,0)) -> 0 | W21: =IF(Q21="",0,MIN(W20+U21-V21,S21)) -> 11 | X21: =IF(Q21="",0,Assumptions!$B$54) -> 1 | Y21: =W21*X21 -> 11 | Z21: =L21 -> 46.06 | AA21: =Y21*Z21 -> 506.66 | AB21: =IF(A21=Assumptions!$B$45,Assumptions!$B$47+Assumptions!$B$48,IF(A21>Assumptions!$B$45,Assumptions!$B$47,0)) -> 50 | AC21: =AA21*Assumptions!$B$33 -> 430.661 | AD21: =I21+W21 -> 68 | AE21: =M21+AA21 -> 1950.641 | AF21: =N21+AB21+AJ21+AK21+AL21+Assumptions!$B$68 -> 33043.989 | AG21: =O21+AC21 -> 1658.0448 | AH21: =AG21-AF21 -> -31385.944 | AI21: =IFERROR((AD21-AD20)/AD20,"") -> 0.0625 | AJ21: =MAX(Assumptions!$B$71,Assumptions!$B$69*0.5^(A21/Assumptions!$B$70))+Assumptions!$B$72*(K21+Y21) -> 89.8225 | AK21: =IF(AND(Assumptions!$B$76=1,A21>=Assumptions!$B$77),Assumptions!$B$78/12,0) -> 4583.3333 | AL21: =IF(AND(Assumptions!$B$86=1,Q21<>""),Assumptions!$B$87/12,0) -> 0
A22: 21 | B22: Apr 2028 | C22: =IF(A22<=12,1,IF(A22<=24,2,IF(A22<=36,3,4))) -> 2 | D22: =IF(A22<=6,"P1: Pilot->Seed",IF(A22<=18,"P2: Scale/Series A",IF(A22<=36,"P3: Post-Series A","P4: Maturity"))) -> P3: Post-Series A | E22: =IF(C22=1,Assumptions!$B$5,IF(C22=2,Assumptions!$B$6,IF(C22=3,Assumptions!$B$7,Assumptions!$B$8))) -> 4500 | F22: =IF(A22<=6,Assumptions!$B$14,IF(A22<=18,Assumptions!$B$15,IF(A22<=36,Assumptions!$B$16,Assumptions!$B$17))) -> 0.08 | G22: =ROUND(MAX(I21,1)*F22,0) -> 5 | H22: =ROUND(I21*Assumptions!$B$18,0) -> 1 | I22: =MIN(I21+G22-H22,E22) -> 61 | J22: =Assumptions!$B$23 -> 0.85 | K22: =I22*J22 -> 51.85 | L22: =Assumptions!$B$10*(1-Assumptions!$B$12)+Assumptions!$B$11*Assumptions!$B$12 -> 46.06 | M22: =K22*L22 -> 2388.211 | N22: =((IF(A22<=Assumptions!$B$91,Assumptions!$B$90,IF(A22>=Assumptions!$B$92,1,Assumptions!$B$90+(1-Assumptions!$B$90)*(A22-Assumptions!$B$91)/(Assumptions!$B$92-Assumptions!$B$91))))*Assumptions!$B$81*Assumptions!$B$75+Assumptions!$B$82)*(1+Assumptions!$B$83)/12 -> 28270.833 | O22: =M22*Assumptions!$B$33 -> 2029.9794 | P22: =O22-N22 -> -26240.854 | Q22: =IF(A22>=Assumptions!$B$45,A22-Assumptions!$B$45+1,"") -> 9 | R22: =IF(Q22="","Not yet launched",IF(Q22<=6,"CP1: Launch",IF(Q22<=18,"CP2: Scale",IF(Q22<=36,"CP3: Mature","CP4: Steady")))) -> CP2: Scale | S22: =IF(Q22="",0,Assumptions!$B$46) -> 2000 | T22: =IF(Q22="",0,IF(Q22<=6,Assumptions!$B$14,IF(Q22<=18,Assumptions!$B$15,IF(Q22<=36,Assumptions!$B$16,Assumptions!$B$17)))) -> 0.14 | U22: =IF(Q22="",0,IF(Q22=1,Assumptions!$B$65,ROUND(MAX(W21,1)*T22,0))) -> 2 | V22: =IF(Q22="",0,ROUND(W21*Assumptions!$B$49,0)) -> 0 | W22: =IF(Q22="",0,MIN(W21+U22-V22,S22)) -> 13 | X22: =IF(Q22="",0,Assumptions!$B$55) -> 0.9 | Y22: =W22*X22 -> 11.7 | Z22: =L22 -> 46.06 | AA22: =Y22*Z22 -> 538.902 | AB22: =IF(A22=Assumptions!$B$45,Assumptions!$B$47+Assumptions!$B$48,IF(A22>Assumptions!$B$45,Assumptions!$B$47,0)) -> 50 | AC22: =AA22*Assumptions!$B$33 -> 458.0667 | AD22: =I22+W22 -> 74 | AE22: =M22+AA22 -> 2927.113 | AF22: =N22+AB22+AJ22+AK22+AL22+Assumptions!$B$68 -> 33051.409 | AG22: =O22+AC22 -> 2488.046 | AH22: =AG22-AF22 -> -30563.363 | AI22: =IFERROR((AD22-AD21)/AD21,"") -> 0.088235294 | AJ22: =MAX(Assumptions!$B$71,Assumptions!$B$69*0.5^(A22/Assumptions!$B$70))+Assumptions!$B$72*(K22+Y22) -> 97.2425 | AK22: =IF(AND(Assumptions!$B$76=1,A22>=Assumptions!$B$77),Assumptions!$B$78/12,0) -> 4583.3333 | AL22: =IF(AND(Assumptions!$B$86=1,Q22<>""),Assumptions!$B$87/12,0) -> 0
A23: 22 | B23: May 2028 | C23: =IF(A23<=12,1,IF(A23<=24,2,IF(A23<=36,3,4))) -> 2 | D23: =IF(A23<=6,"P1: Pilot->Seed",IF(A23<=18,"P2: Scale/Series A",IF(A23<=36,"P3: Post-Series A","P4: Maturity"))) -> P3: Post-Series A | E23: =IF(C23=1,Assumptions!$B$5,IF(C23=2,Assumptions!$B$6,IF(C23=3,Assumptions!$B$7,Assumptions!$B$8))) -> 4500 | F23: =IF(A23<=6,Assumptions!$B$14,IF(A23<=18,Assumptions!$B$15,IF(A23<=36,Assumptions!$B$16,Assumptions!$B$17))) -> 0.08 | G23: =ROUND(MAX(I22,1)*F23,0) -> 5 | H23: =ROUND(I22*Assumptions!$B$18,0) -> 1 | I23: =MIN(I22+G23-H23,E23) -> 65 | J23: =Assumptions!$B$24 -> 1 | K23: =I23*J23 -> 65 | L23: =Assumptions!$B$10*(1-Assumptions!$B$12)+Assumptions!$B$11*Assumptions!$B$12 -> 46.06 | M23: =K23*L23 -> 2993.9 | N23: =((IF(A23<=Assumptions!$B$91,Assumptions!$B$90,IF(A23>=Assumptions!$B$92,1,Assumptions!$B$90+(1-Assumptions!$B$90)*(A23-Assumptions!$B$91)/(Assumptions!$B$92-Assumptions!$B$91))))*Assumptions!$B$81*Assumptions!$B$75+Assumptions!$B$82)*(1+Assumptions!$B$83)/12 -> 28270.833 | O23: =M23*Assumptions!$B$33 -> 2544.815 | P23: =O23-N23 -> -25726.018 | Q23: =IF(A23>=Assumptions!$B$45,A23-Assumptions!$B$45+1,"") -> 10 | R23: =IF(Q23="","Not yet launched",IF(Q23<=6,"CP1: Launch",IF(Q23<=18,"CP2: Scale",IF(Q23<=36,"CP3: Mature","CP4: Steady")))) -> CP2: Scale | S23: =IF(Q23="",0,Assumptions!$B$46) -> 2000 | T23: =IF(Q23="",0,IF(Q23<=6,Assumptions!$B$14,IF(Q23<=18,Assumptions!$B$15,IF(Q23<=36,Assumptions!$B$16,Assumptions!$B$17)))) -> 0.14 | U23: =IF(Q23="",0,IF(Q23=1,Assumptions!$B$65,ROUND(MAX(W22,1)*T23,0))) -> 2 | V23: =IF(Q23="",0,ROUND(W22*Assumptions!$B$49,0)) -> 0 | W23: =IF(Q23="",0,MIN(W22+U23-V23,S23)) -> 15 | X23: =IF(Q23="",0,Assumptions!$B$56) -> 0.6 | Y23: =W23*X23 -> 9 | Z23: =L23 -> 46.06 | AA23: =Y23*Z23 -> 414.54 | AB23: =IF(A23=Assumptions!$B$45,Assumptions!$B$47+Assumptions!$B$48,IF(A23>Assumptions!$B$45,Assumptions!$B$47,0)) -> 50 | AC23: =AA23*Assumptions!$B$33 -> 352.359 | AD23: =I23+W23 -> 80 | AE23: =M23+AA23 -> 3408.44 | AF23: =N23+AB23+AJ23+AK23+AL23+Assumptions!$B$68 -> 33055.067 | AG23: =O23+AC23 -> 2897.174 | AH23: =AG23-AF23 -> -30157.893 | AI23: =IFERROR((AD23-AD22)/AD22,"") -> 0.081081081 | AJ23: =MAX(Assumptions!$B$71,Assumptions!$B$69*0.5^(A23/Assumptions!$B$70))+Assumptions!$B$72*(K23+Y23) -> 100.9 | AK23: =IF(AND(Assumptions!$B$76=1,A23>=Assumptions!$B$77),Assumptions!$B$78/12,0) -> 4583.3333 | AL23: =IF(AND(Assumptions!$B$86=1,Q23<>""),Assumptions!$B$87/12,0) -> 0
A24: 23 | B24: Jun 2028 | C24: =IF(A24<=12,1,IF(A24<=24,2,IF(A24<=36,3,4))) -> 2 | D24: =IF(A24<=6,"P1: Pilot->Seed",IF(A24<=18,"P2: Scale/Series A",IF(A24<=36,"P3: Post-Series A","P4: Maturity"))) -> P3: Post-Series A | E24: =IF(C24=1,Assumptions!$B$5,IF(C24=2,Assumptions!$B$6,IF(C24=3,Assumptions!$B$7,Assumptions!$B$8))) -> 4500 | F24: =IF(A24<=6,Assumptions!$B$14,IF(A24<=18,Assumptions!$B$15,IF(A24<=36,Assumptions!$B$16,Assumptions!$B$17))) -> 0.08 | G24: =ROUND(MAX(I23,1)*F24,0) -> 5 | H24: =ROUND(I23*Assumptions!$B$18,0) -> 1 | I24: =MIN(I23+G24-H24,E24) -> 69 | J24: =Assumptions!$B$25 -> 1 | K24: =I24*J24 -> 69 | L24: =Assumptions!$B$10*(1-Assumptions!$B$12)+Assumptions!$B$11*Assumptions!$B$12 -> 46.06 | M24: =K24*L24 -> 3178.14 | N24: =((IF(A24<=Assumptions!$B$91,Assumptions!$B$90,IF(A24>=Assumptions!$B$92,1,Assumptions!$B$90+(1-Assumptions!$B$90)*(A24-Assumptions!$B$91)/(Assumptions!$B$92-Assumptions!$B$91))))*Assumptions!$B$81*Assumptions!$B$75+Assumptions!$B$82)*(1+Assumptions!$B$83)/12 -> 28270.833 | O24: =M24*Assumptions!$B$33 -> 2701.419 | P24: =O24-N24 -> -25569.414 | Q24: =IF(A24>=Assumptions!$B$45,A24-Assumptions!$B$45+1,"") -> 11 | R24: =IF(Q24="","Not yet launched",IF(Q24<=6,"CP1: Launch",IF(Q24<=18,"CP2: Scale",IF(Q24<=36,"CP3: Mature","CP4: Steady")))) -> CP2: Scale | S24: =IF(Q24="",0,Assumptions!$B$46) -> 2000 | T24: =IF(Q24="",0,IF(Q24<=6,Assumptions!$B$14,IF(Q24<=18,Assumptions!$B$15,IF(Q24<=36,Assumptions!$B$16,Assumptions!$B$17)))) -> 0.14 | U24: =IF(Q24="",0,IF(Q24=1,Assumptions!$B$65,ROUND(MAX(W23,1)*T24,0))) -> 2 | V24: =IF(Q24="",0,ROUND(W23*Assumptions!$B$49,0)) -> 0 | W24: =IF(Q24="",0,MIN(W23+U24-V24,S24)) -> 17 | X24: =IF(Q24="",0,Assumptions!$B$57) -> 0.4 | Y24: =W24*X24 -> 6.8 | Z24: =L24 -> 46.06 | AA24: =Y24*Z24 -> 313.208 | AB24: =IF(A24=Assumptions!$B$45,Assumptions!$B$47+Assumptions!$B$48,IF(A24>Assumptions!$B$45,Assumptions!$B$47,0)) -> 50 | AC24: =AA24*Assumptions!$B$33 -> 266.2268 | AD24: =I24+W24 -> 86 | AE24: =M24+AA24 -> 3491.348 | AF24: =N24+AB24+AJ24+AK24+AL24+Assumptions!$B$68 -> 33055.697 | AG24: =O24+AC24 -> 2967.6458 | AH24: =AG24-AF24 -> -30088.051 | AI24: =IFERROR((AD24-AD23)/AD23,"") -> 0.075 | AJ24: =MAX(Assumptions!$B$71,Assumptions!$B$69*0.5^(A24/Assumptions!$B$70))+Assumptions!$B$72*(K24+Y24) -> 101.53 | AK24: =IF(AND(Assumptions!$B$76=1,A24>=Assumptions!$B$77),Assumptions!$B$78/12,0) -> 4583.3333 | AL24: =IF(AND(Assumptions!$B$86=1,Q24<>""),Assumptions!$B$87/12,0) -> 0
A25: 24 | B25: Jul 2028 | C25: =IF(A25<=12,1,IF(A25<=24,2,IF(A25<=36,3,4))) -> 2 | D25: =IF(A25<=6,"P1: Pilot->Seed",IF(A25<=18,"P2: Scale/Series A",IF(A25<=36,"P3: Post-Series A","P4: Maturity"))) -> P3: Post-Series A | E25: =IF(C25=1,Assumptions!$B$5,IF(C25=2,Assumptions!$B$6,IF(C25=3,Assumptions!$B$7,Assumptions!$B$8))) -> 4500 | F25: =IF(A25<=6,Assumptions!$B$14,IF(A25<=18,Assumptions!$B$15,IF(A25<=36,Assumptions!$B$16,Assumptions!$B$17))) -> 0.08 | G25: =ROUND(MAX(I24,1)*F25,0) -> 6 | H25: =ROUND(I24*Assumptions!$B$18,0) -> 1 | I25: =MIN(I24+G25-H25,E25) -> 74 | J25: =Assumptions!$B$26 -> 1 | K25: =I25*J25 -> 74 | L25: =Assumptions!$B$10*(1-Assumptions!$B$12)+Assumptions!$B$11*Assumptions!$B$12 -> 46.06 | M25: =K25*L25 -> 3408.44 | N25: =((IF(A25<=Assumptions!$B$91,Assumptions!$B$90,IF(A25>=Assumptions!$B$92,1,Assumptions!$B$90+(1-Assumptions!$B$90)*(A25-Assumptions!$B$91)/(Assumptions!$B$92-Assumptions!$B$91))))*Assumptions!$B$81*Assumptions!$B$75+Assumptions!$B$82)*(1+Assumptions!$B$83)/12 -> 28270.833 | O25: =M25*Assumptions!$B$33 -> 2897.174 | P25: =O25-N25 -> -25373.659 | Q25: =IF(A25>=Assumptions!$B$45,A25-Assumptions!$B$45+1,"") -> 12 | R25: =IF(Q25="","Not yet launched",IF(Q25<=6,"CP1: Launch",IF(Q25<=18,"CP2: Scale",IF(Q25<=36,"CP3: Mature","CP4: Steady")))) -> CP2: Scale | S25: =IF(Q25="",0,Assumptions!$B$46) -> 2000 | T25: =IF(Q25="",0,IF(Q25<=6,Assumptions!$B$14,IF(Q25<=18,Assumptions!$B$15,IF(Q25<=36,Assumptions!$B$16,Assumptions!$B$17)))) -> 0.14 | U25: =IF(Q25="",0,IF(Q25=1,Assumptions!$B$65,ROUND(MAX(W24,1)*T25,0))) -> 2 | V25: =IF(Q25="",0,ROUND(W24*Assumptions!$B$49,0)) -> 0 | W25: =IF(Q25="",0,MIN(W24+U25-V25,S25)) -> 19 | X25: =IF(Q25="",0,Assumptions!$B$58) -> 0.35 | Y25: =W25*X25 -> 6.65 | Z25: =L25 -> 46.06 | AA25: =Y25*Z25 -> 306.299 | AB25: =IF(A25=Assumptions!$B$45,Assumptions!$B$47+Assumptions!$B$48,IF(A25>Assumptions!$B$45,Assumptions!$B$47,0)) -> 50 | AC25: =AA25*Assumptions!$B$33 -> 260.35415 | AD25: =I25+W25 -> 93 | AE25: =M25+AA25 -> 3714.739 | AF25: =N25+AB25+AJ25+AK25+AL25+Assumptions!$B$68 -> 33057.394 | AG25: =O25+AC25 -> 3157.5282 | AH25: =AG25-AF25 -> -29899.866 | AI25: =IFERROR((AD25-AD24)/AD24,"") -> 0.081395349 | AJ25: =MAX(Assumptions!$B$71,Assumptions!$B$69*0.5^(A25/Assumptions!$B$70))+Assumptions!$B$72*(K25+Y25) -> 103.2275 | AK25: =IF(AND(Assumptions!$B$76=1,A25>=Assumptions!$B$77),Assumptions!$B$78/12,0) -> 4583.3333 | AL25: =IF(AND(Assumptions!$B$86=1,Q25<>""),Assumptions!$B$87/12,0) -> 0
A26: 25 | B26: Aug 2028 | C26: =IF(A26<=12,1,IF(A26<=24,2,IF(A26<=36,3,4))) -> 3 | D26: =IF(A26<=6,"P1: Pilot->Seed",IF(A26<=18,"P2: Scale/Series A",IF(A26<=36,"P3: Post-Series A","P4: Maturity"))) -> P3: Post-Series A | E26: =IF(C26=1,Assumptions!$B$5,IF(C26=2,Assumptions!$B$6,IF(C26=3,Assumptions!$B$7,Assumptions!$B$8))) -> 9000 | F26: =IF(A26<=6,Assumptions!$B$14,IF(A26<=18,Assumptions!$B$15,IF(A26<=36,Assumptions!$B$16,Assumptions!$B$17))) -> 0.08 | G26: =ROUND(MAX(I25,1)*F26,0) -> 6 | H26: =ROUND(I25*Assumptions!$B$18,0) -> 1 | I26: =MIN(I25+G26-H26,E26) -> 79 | J26: =Assumptions!$B$27 -> 1 | K26: =I26*J26 -> 79 | L26: =Assumptions!$B$10*(1-Assumptions!$B$12)+Assumptions!$B$11*Assumptions!$B$12 -> 46.06 | M26: =K26*L26 -> 3638.74 | N26: =((IF(A26<=Assumptions!$B$91,Assumptions!$B$90,IF(A26>=Assumptions!$B$92,1,Assumptions!$B$90+(1-Assumptions!$B$90)*(A26-Assumptions!$B$91)/(Assumptions!$B$92-Assumptions!$B$91))))*Assumptions!$B$81*Assumptions!$B$75+Assumptions!$B$82)*(1+Assumptions!$B$83)/12 -> 28270.833 | O26: =M26*Assumptions!$B$33 -> 3092.929 | P26: =O26-N26 -> -25177.904 | Q26: =IF(A26>=Assumptions!$B$45,A26-Assumptions!$B$45+1,"") -> 13 | R26: =IF(Q26="","Not yet launched",IF(Q26<=6,"CP1: Launch",IF(Q26<=18,"CP2: Scale",IF(Q26<=36,"CP3: Mature","CP4: Steady")))) -> CP2: Scale | S26: =IF(Q26="",0,Assumptions!$B$46) -> 2000 | T26: =IF(Q26="",0,IF(Q26<=6,Assumptions!$B$14,IF(Q26<=18,Assumptions!$B$15,IF(Q26<=36,Assumptions!$B$16,Assumptions!$B$17)))) -> 0.14 | U26: =IF(Q26="",0,IF(Q26=1,Assumptions!$B$65,ROUND(MAX(W25,1)*T26,0))) -> 3 | V26: =IF(Q26="",0,ROUND(W25*Assumptions!$B$49,0)) -> 0 | W26: =IF(Q26="",0,MIN(W25+U26-V26,S26)) -> 22 | X26: =IF(Q26="",0,Assumptions!$B$59) -> 0.35 | Y26: =W26*X26 -> 7.7 | Z26: =L26 -> 46.06 | AA26: =Y26*Z26 -> 354.662 | AB26: =IF(A26=Assumptions!$B$45,Assumptions!$B$47+Assumptions!$B$48,IF(A26>Assumptions!$B$45,Assumptions!$B$47,0)) -> 50 | AC26: =AA26*Assumptions!$B$33 -> 301.4627 | AD26: =I26+W26 -> 101 | AE26: =M26+AA26 -> 3993.402 | AF26: =N26+AB26+AJ26+AK26+AL26+Assumptions!$B$68 -> 33059.512 | AG26: =O26+AC26 -> 3394.3917 | AH26: =AG26-AF26 -> -29665.12 | AI26: =IFERROR((AD26-AD25)/AD25,"") -> 0.086021505 | AJ26: =MAX(Assumptions!$B$71,Assumptions!$B$69*0.5^(A26/Assumptions!$B$70))+Assumptions!$B$72*(K26+Y26) -> 105.345 | AK26: =IF(AND(Assumptions!$B$76=1,A26>=Assumptions!$B$77),Assumptions!$B$78/12,0) -> 4583.3333 | AL26: =IF(AND(Assumptions!$B$86=1,Q26<>""),Assumptions!$B$87/12,0) -> 0
A27: 26 | B27: Sep 2028 | C27: =IF(A27<=12,1,IF(A27<=24,2,IF(A27<=36,3,4))) -> 3 | D27: =IF(A27<=6,"P1: Pilot->Seed",IF(A27<=18,"P2: Scale/Series A",IF(A27<=36,"P3: Post-Series A","P4: Maturity"))) -> P3: Post-Series A | E27: =IF(C27=1,Assumptions!$B$5,IF(C27=2,Assumptions!$B$6,IF(C27=3,Assumptions!$B$7,Assumptions!$B$8))) -> 9000 | F27: =IF(A27<=6,Assumptions!$B$14,IF(A27<=18,Assumptions!$B$15,IF(A27<=36,Assumptions!$B$16,Assumptions!$B$17))) -> 0.08 | G27: =ROUND(MAX(I26,1)*F27,0) -> 6 | H27: =ROUND(I26*Assumptions!$B$18,0) -> 2 | I27: =MIN(I26+G27-H27,E27) -> 83 | J27: =Assumptions!$B$28 -> 1 | K27: =I27*J27 -> 83 | L27: =Assumptions!$B$10*(1-Assumptions!$B$12)+Assumptions!$B$11*Assumptions!$B$12 -> 46.06 | M27: =K27*L27 -> 3822.98 | N27: =((IF(A27<=Assumptions!$B$91,Assumptions!$B$90,IF(A27>=Assumptions!$B$92,1,Assumptions!$B$90+(1-Assumptions!$B$90)*(A27-Assumptions!$B$91)/(Assumptions!$B$92-Assumptions!$B$91))))*Assumptions!$B$81*Assumptions!$B$75+Assumptions!$B$82)*(1+Assumptions!$B$83)/12 -> 28270.833 | O27: =M27*Assumptions!$B$33 -> 3249.533 | P27: =O27-N27 -> -25021.3 | Q27: =IF(A27>=Assumptions!$B$45,A27-Assumptions!$B$45+1,"") -> 14 | R27: =IF(Q27="","Not yet launched",IF(Q27<=6,"CP1: Launch",IF(Q27<=18,"CP2: Scale",IF(Q27<=36,"CP3: Mature","CP4: Steady")))) -> CP2: Scale | S27: =IF(Q27="",0,Assumptions!$B$46) -> 2000 | T27: =IF(Q27="",0,IF(Q27<=6,Assumptions!$B$14,IF(Q27<=18,Assumptions!$B$15,IF(Q27<=36,Assumptions!$B$16,Assumptions!$B$17)))) -> 0.14 | U27: =IF(Q27="",0,IF(Q27=1,Assumptions!$B$65,ROUND(MAX(W26,1)*T27,0))) -> 3 | V27: =IF(Q27="",0,ROUND(W26*Assumptions!$B$49,0)) -> 0 | W27: =IF(Q27="",0,MIN(W26+U27-V27,S27)) -> 25 | X27: =IF(Q27="",0,Assumptions!$B$60) -> 0.35 | Y27: =W27*X27 -> 8.75 | Z27: =L27 -> 46.06 | AA27: =Y27*Z27 -> 403.025 | AB27: =IF(A27=Assumptions!$B$45,Assumptions!$B$47+Assumptions!$B$48,IF(A27>Assumptions!$B$45,Assumptions!$B$47,0)) -> 50 | AC27: =AA27*Assumptions!$B$33 -> 342.57125 | AD27: =I27+W27 -> 108 | AE27: =M27+AA27 -> 4226.005 | AF27: =N27+AB27+AJ27+AK27+AL27+Assumptions!$B$68 -> 33061.279 | AG27: =O27+AC27 -> 3592.1042 | AH27: =AG27-AF27 -> -29469.175 | AI27: =IFERROR((AD27-AD26)/AD26,"") -> 0.069306931 | AJ27: =MAX(Assumptions!$B$71,Assumptions!$B$69*0.5^(A27/Assumptions!$B$70))+Assumptions!$B$72*(K27+Y27) -> 107.1125 | AK27: =IF(AND(Assumptions!$B$76=1,A27>=Assumptions!$B$77),Assumptions!$B$78/12,0) -> 4583.3333 | AL27: =IF(AND(Assumptions!$B$86=1,Q27<>""),Assumptions!$B$87/12,0) -> 0
A28: 27 | B28: Oct 2028 | C28: =IF(A28<=12,1,IF(A28<=24,2,IF(A28<=36,3,4))) -> 3 | D28: =IF(A28<=6,"P1: Pilot->Seed",IF(A28<=18,"P2: Scale/Series A",IF(A28<=36,"P3: Post-Series A","P4: Maturity"))) -> P3: Post-Series A | E28: =IF(C28=1,Assumptions!$B$5,IF(C28=2,Assumptions!$B$6,IF(C28=3,Assumptions!$B$7,Assumptions!$B$8))) -> 9000 | F28: =IF(A28<=6,Assumptions!$B$14,IF(A28<=18,Assumptions!$B$15,IF(A28<=36,Assumptions!$B$16,Assumptions!$B$17))) -> 0.08 | G28: =ROUND(MAX(I27,1)*F28,0) -> 7 | H28: =ROUND(I27*Assumptions!$B$18,0) -> 2 | I28: =MIN(I27+G28-H28,E28) -> 88 | J28: =Assumptions!$B$29 -> 0.85 | K28: =I28*J28 -> 74.8 | L28: =Assumptions!$B$10*(1-Assumptions!$B$12)+Assumptions!$B$11*Assumptions!$B$12 -> 46.06 | M28: =K28*L28 -> 3445.288 | N28: =((IF(A28<=Assumptions!$B$91,Assumptions!$B$90,IF(A28>=Assumptions!$B$92,1,Assumptions!$B$90+(1-Assumptions!$B$90)*(A28-Assumptions!$B$91)/(Assumptions!$B$92-Assumptions!$B$91))))*Assumptions!$B$81*Assumptions!$B$75+Assumptions!$B$82)*(1+Assumptions!$B$83)/12 -> 28270.833 | O28: =M28*Assumptions!$B$33 -> 2928.4948 | P28: =O28-N28 -> -25342.339 | Q28: =IF(A28>=Assumptions!$B$45,A28-Assumptions!$B$45+1,"") -> 15 | R28: =IF(Q28="","Not yet launched",IF(Q28<=6,"CP1: Launch",IF(Q28<=18,"CP2: Scale",IF(Q28<=36,"CP3: Mature","CP4: Steady")))) -> CP2: Scale | S28: =IF(Q28="",0,Assumptions!$B$46) -> 2000 | T28: =IF(Q28="",0,IF(Q28<=6,Assumptions!$B$14,IF(Q28<=18,Assumptions!$B$15,IF(Q28<=36,Assumptions!$B$16,Assumptions!$B$17)))) -> 0.14 | U28: =IF(Q28="",0,IF(Q28=1,Assumptions!$B$65,ROUND(MAX(W27,1)*T28,0))) -> 4 | V28: =IF(Q28="",0,ROUND(W27*Assumptions!$B$49,0)) -> 1 | W28: =IF(Q28="",0,MIN(W27+U28-V28,S28)) -> 28 | X28: =IF(Q28="",0,Assumptions!$B$61) -> 0.4 | Y28: =W28*X28 -> 11.2 | Z28: =L28 -> 46.06 | AA28: =Y28*Z28 -> 515.872 | AB28: =IF(A28=Assumptions!$B$45,Assumptions!$B$47+Assumptions!$B$48,IF(A28>Assumptions!$B$45,Assumptions!$B$47,0)) -> 50 | AC28: =AA28*Assumptions!$B$33 -> 438.4912 | AD28: =I28+W28 -> 116 | AE28: =M28+AA28 -> 3961.16 | AF28: =N28+AB28+AJ28+AK28+AL28+Assumptions!$B$68 -> 33059.267 | AG28: =O28+AC28 -> 3366.986 | AH28: =AG28-AF28 -> -29692.281 | AI28: =IFERROR((AD28-AD27)/AD27,"") -> 0.074074074 | AJ28: =MAX(Assumptions!$B$71,Assumptions!$B$69*0.5^(A28/Assumptions!$B$70))+Assumptions!$B$72*(K28+Y28) -> 105.1 | AK28: =IF(AND(Assumptions!$B$76=1,A28>=Assumptions!$B$77),Assumptions!$B$78/12,0) -> 4583.3333 | AL28: =IF(AND(Assumptions!$B$86=1,Q28<>""),Assumptions!$B$87/12,0) -> 0
A29: 28 | B29: Nov 2028 | C29: =IF(A29<=12,1,IF(A29<=24,2,IF(A29<=36,3,4))) -> 3 | D29: =IF(A29<=6,"P1: Pilot->Seed",IF(A29<=18,"P2: Scale/Series A",IF(A29<=36,"P3: Post-Series A","P4: Maturity"))) -> P3: Post-Series A | E29: =IF(C29=1,Assumptions!$B$5,IF(C29=2,Assumptions!$B$6,IF(C29=3,Assumptions!$B$7,Assumptions!$B$8))) -> 9000 | F29: =IF(A29<=6,Assumptions!$B$14,IF(A29<=18,Assumptions!$B$15,IF(A29<=36,Assumptions!$B$16,Assumptions!$B$17))) -> 0.08 | G29: =ROUND(MAX(I28,1)*F29,0) -> 7 | H29: =ROUND(I28*Assumptions!$B$18,0) -> 2 | I29: =MIN(I28+G29-H29,E29) -> 93 | J29: =Assumptions!$B$30 -> 0.45 | K29: =I29*J29 -> 41.85 | L29: =Assumptions!$B$10*(1-Assumptions!$B$12)+Assumptions!$B$11*Assumptions!$B$12 -> 46.06 | M29: =K29*L29 -> 1927.611 | N29: =((IF(A29<=Assumptions!$B$91,Assumptions!$B$90,IF(A29>=Assumptions!$B$92,1,Assumptions!$B$90+(1-Assumptions!$B$90)*(A29-Assumptions!$B$91)/(Assumptions!$B$92-Assumptions!$B$91))))*Assumptions!$B$81*Assumptions!$B$75+Assumptions!$B$82)*(1+Assumptions!$B$83)/12 -> 28270.833 | O29: =M29*Assumptions!$B$33 -> 1638.4694 | P29: =O29-N29 -> -26632.364 | Q29: =IF(A29>=Assumptions!$B$45,A29-Assumptions!$B$45+1,"") -> 16 | R29: =IF(Q29="","Not yet launched",IF(Q29<=6,"CP1: Launch",IF(Q29<=18,"CP2: Scale",IF(Q29<=36,"CP3: Mature","CP4: Steady")))) -> CP2: Scale | S29: =IF(Q29="",0,Assumptions!$B$46) -> 2000 | T29: =IF(Q29="",0,IF(Q29<=6,Assumptions!$B$14,IF(Q29<=18,Assumptions!$B$15,IF(Q29<=36,Assumptions!$B$16,Assumptions!$B$17)))) -> 0.14 | U29: =IF(Q29="",0,IF(Q29=1,Assumptions!$B$65,ROUND(MAX(W28,1)*T29,0))) -> 4 | V29: =IF(Q29="",0,ROUND(W28*Assumptions!$B$49,0)) -> 1 | W29: =IF(Q29="",0,MIN(W28+U29-V29,S29)) -> 31 | X29: =IF(Q29="",0,Assumptions!$B$62) -> 0.55 | Y29: =W29*X29 -> 17.05 | Z29: =L29 -> 46.06 | AA29: =Y29*Z29 -> 785.323 | AB29: =IF(A29=Assumptions!$B$45,Assumptions!$B$47+Assumptions!$B$48,IF(A29>Assumptions!$B$45,Assumptions!$B$47,0)) -> 50 | AC29: =AA29*Assumptions!$B$33 -> 667.52455 | AD29: =I29+W29 -> 124 | AE29: =M29+AA29 -> 2712.934 | AF29: =N29+AB29+AJ29+AK29+AL29+Assumptions!$B$68 -> 33049.782 | AG29: =O29+AC29 -> 2305.9939 | AH29: =AG29-AF29 -> -30743.788 | AI29: =IFERROR((AD29-AD28)/AD28,"") -> 0.068965517 | AJ29: =MAX(Assumptions!$B$71,Assumptions!$B$69*0.5^(A29/Assumptions!$B$70))+Assumptions!$B$72*(K29+Y29) -> 95.615 | AK29: =IF(AND(Assumptions!$B$76=1,A29>=Assumptions!$B$77),Assumptions!$B$78/12,0) -> 4583.3333 | AL29: =IF(AND(Assumptions!$B$86=1,Q29<>""),Assumptions!$B$87/12,0) -> 0
A30: 29 | B30: Dec 2028 | C30: =IF(A30<=12,1,IF(A30<=24,2,IF(A30<=36,3,4))) -> 3 | D30: =IF(A30<=6,"P1: Pilot->Seed",IF(A30<=18,"P2: Scale/Series A",IF(A30<=36,"P3: Post-Series A","P4: Maturity"))) -> P3: Post-Series A | E30: =IF(C30=1,Assumptions!$B$5,IF(C30=2,Assumptions!$B$6,IF(C30=3,Assumptions!$B$7,Assumptions!$B$8))) -> 9000 | F30: =IF(A30<=6,Assumptions!$B$14,IF(A30<=18,Assumptions!$B$15,IF(A30<=36,Assumptions!$B$16,Assumptions!$B$17))) -> 0.08 | G30: =ROUND(MAX(I29,1)*F30,0) -> 7 | H30: =ROUND(I29*Assumptions!$B$18,0) -> 2 | I30: =MIN(I29+G30-H30,E30) -> 98 | J30: =Assumptions!$B$31 -> 0.35 | K30: =I30*J30 -> 34.3 | L30: =Assumptions!$B$10*(1-Assumptions!$B$12)+Assumptions!$B$11*Assumptions!$B$12 -> 46.06 | M30: =K30*L30 -> 1579.858 | N30: =((IF(A30<=Assumptions!$B$91,Assumptions!$B$90,IF(A30>=Assumptions!$B$92,1,Assumptions!$B$90+(1-Assumptions!$B$90)*(A30-Assumptions!$B$91)/(Assumptions!$B$92-Assumptions!$B$91))))*Assumptions!$B$81*Assumptions!$B$75+Assumptions!$B$82)*(1+Assumptions!$B$83)/12 -> 28270.833 | O30: =M30*Assumptions!$B$33 -> 1342.8793 | P30: =O30-N30 -> -26927.954 | Q30: =IF(A30>=Assumptions!$B$45,A30-Assumptions!$B$45+1,"") -> 17 | R30: =IF(Q30="","Not yet launched",IF(Q30<=6,"CP1: Launch",IF(Q30<=18,"CP2: Scale",IF(Q30<=36,"CP3: Mature","CP4: Steady")))) -> CP2: Scale | S30: =IF(Q30="",0,Assumptions!$B$46) -> 2000 | T30: =IF(Q30="",0,IF(Q30<=6,Assumptions!$B$14,IF(Q30<=18,Assumptions!$B$15,IF(Q30<=36,Assumptions!$B$16,Assumptions!$B$17)))) -> 0.14 | U30: =IF(Q30="",0,IF(Q30=1,Assumptions!$B$65,ROUND(MAX(W29,1)*T30,0))) -> 4 | V30: =IF(Q30="",0,ROUND(W29*Assumptions!$B$49,0)) -> 1 | W30: =IF(Q30="",0,MIN(W29+U30-V30,S30)) -> 34 | X30: =IF(Q30="",0,Assumptions!$B$63) -> 0.9 | Y30: =W30*X30 -> 30.6 | Z30: =L30 -> 46.06 | AA30: =Y30*Z30 -> 1409.436 | AB30: =IF(A30=Assumptions!$B$45,Assumptions!$B$47+Assumptions!$B$48,IF(A30>Assumptions!$B$45,Assumptions!$B$47,0)) -> 50 | AC30: =AA30*Assumptions!$B$33 -> 1198.0206 | AD30: =I30+W30 -> 132 | AE30: =M30+AA30 -> 2989.294 | AF30: =N30+AB30+AJ30+AK30+AL30+Assumptions!$B$68 -> 33051.882 | AG30: =O30+AC30 -> 2540.8999 | AH30: =AG30-AF30 -> -30510.982 | AI30: =IFERROR((AD30-AD29)/AD29,"") -> 0.064516129 | AJ30: =MAX(Assumptions!$B$71,Assumptions!$B$69*0.5^(A30/Assumptions!$B$70))+Assumptions!$B$72*(K30+Y30) -> 97.715 | AK30: =IF(AND(Assumptions!$B$76=1,A30>=Assumptions!$B$77),Assumptions!$B$78/12,0) -> 4583.3333 | AL30: =IF(AND(Assumptions!$B$86=1,Q30<>""),Assumptions!$B$87/12,0) -> 0
A31: 30 | B31: Jan 2029 | C31: =IF(A31<=12,1,IF(A31<=24,2,IF(A31<=36,3,4))) -> 3 | D31: =IF(A31<=6,"P1: Pilot->Seed",IF(A31<=18,"P2: Scale/Series A",IF(A31<=36,"P3: Post-Series A","P4: Maturity"))) -> P3: Post-Series A | E31: =IF(C31=1,Assumptions!$B$5,IF(C31=2,Assumptions!$B$6,IF(C31=3,Assumptions!$B$7,Assumptions!$B$8))) -> 9000 | F31: =IF(A31<=6,Assumptions!$B$14,IF(A31<=18,Assumptions!$B$15,IF(A31<=36,Assumptions!$B$16,Assumptions!$B$17))) -> 0.08 | G31: =ROUND(MAX(I30,1)*F31,0) -> 8 | H31: =ROUND(I30*Assumptions!$B$18,0) -> 2 | I31: =MIN(I30+G31-H31,E31) -> 104 | J31: =Assumptions!$B$20 -> 0.35 | K31: =I31*J31 -> 36.4 | L31: =Assumptions!$B$10*(1-Assumptions!$B$12)+Assumptions!$B$11*Assumptions!$B$12 -> 46.06 | M31: =K31*L31 -> 1676.584 | N31: =((IF(A31<=Assumptions!$B$91,Assumptions!$B$90,IF(A31>=Assumptions!$B$92,1,Assumptions!$B$90+(1-Assumptions!$B$90)*(A31-Assumptions!$B$91)/(Assumptions!$B$92-Assumptions!$B$91))))*Assumptions!$B$81*Assumptions!$B$75+Assumptions!$B$82)*(1+Assumptions!$B$83)/12 -> 28270.833 | O31: =M31*Assumptions!$B$33 -> 1425.0964 | P31: =O31-N31 -> -26845.737 | Q31: =IF(A31>=Assumptions!$B$45,A31-Assumptions!$B$45+1,"") -> 18 | R31: =IF(Q31="","Not yet launched",IF(Q31<=6,"CP1: Launch",IF(Q31<=18,"CP2: Scale",IF(Q31<=36,"CP3: Mature","CP4: Steady")))) -> CP2: Scale | S31: =IF(Q31="",0,Assumptions!$B$46) -> 2000 | T31: =IF(Q31="",0,IF(Q31<=6,Assumptions!$B$14,IF(Q31<=18,Assumptions!$B$15,IF(Q31<=36,Assumptions!$B$16,Assumptions!$B$17)))) -> 0.14 | U31: =IF(Q31="",0,IF(Q31=1,Assumptions!$B$65,ROUND(MAX(W30,1)*T31,0))) -> 5 | V31: =IF(Q31="",0,ROUND(W30*Assumptions!$B$49,0)) -> 1 | W31: =IF(Q31="",0,MIN(W30+U31-V31,S31)) -> 38 | X31: =IF(Q31="",0,Assumptions!$B$52) -> 1 | Y31: =W31*X31 -> 38 | Z31: =L31 -> 46.06 | AA31: =Y31*Z31 -> 1750.28 | AB31: =IF(A31=Assumptions!$B$45,Assumptions!$B$47+Assumptions!$B$48,IF(A31>Assumptions!$B$45,Assumptions!$B$47,0)) -> 50 | AC31: =AA31*Assumptions!$B$33 -> 1487.738 | AD31: =I31+W31 -> 142 | AE31: =M31+AA31 -> 3426.864 | AF31: =N31+AB31+AJ31+AK31+AL31+Assumptions!$B$68 -> 33055.207 | AG31: =O31+AC31 -> 2912.8344 | AH31: =AG31-AF31 -> -30142.372 | AI31: =IFERROR((AD31-AD30)/AD30,"") -> 0.075757576 | AJ31: =MAX(Assumptions!$B$71,Assumptions!$B$69*0.5^(A31/Assumptions!$B$70))+Assumptions!$B$72*(K31+Y31) -> 101.04 | AK31: =IF(AND(Assumptions!$B$76=1,A31>=Assumptions!$B$77),Assumptions!$B$78/12,0) -> 4583.3333 | AL31: =IF(AND(Assumptions!$B$86=1,Q31<>""),Assumptions!$B$87/12,0) -> 0
A32: 31 | B32: Feb 2029 | C32: =IF(A32<=12,1,IF(A32<=24,2,IF(A32<=36,3,4))) -> 3 | D32: =IF(A32<=6,"P1: Pilot->Seed",IF(A32<=18,"P2: Scale/Series A",IF(A32<=36,"P3: Post-Series A","P4: Maturity"))) -> P3: Post-Series A | E32: =IF(C32=1,Assumptions!$B$5,IF(C32=2,Assumptions!$B$6,IF(C32=3,Assumptions!$B$7,Assumptions!$B$8))) -> 9000 | F32: =IF(A32<=6,Assumptions!$B$14,IF(A32<=18,Assumptions!$B$15,IF(A32<=36,Assumptions!$B$16,Assumptions!$B$17))) -> 0.08 | G32: =ROUND(MAX(I31,1)*F32,0) -> 8 | H32: =ROUND(I31*Assumptions!$B$18,0) -> 2 | I32: =MIN(I31+G32-H32,E32) -> 110 | J32: =Assumptions!$B$21 -> 0.35 | K32: =I32*J32 -> 38.5 | L32: =Assumptions!$B$10*(1-Assumptions!$B$12)+Assumptions!$B$11*Assumptions!$B$12 -> 46.06 | M32: =K32*L32 -> 1773.31 | N32: =((IF(A32<=Assumptions!$B$91,Assumptions!$B$90,IF(A32>=Assumptions!$B$92,1,Assumptions!$B$90+(1-Assumptions!$B$90)*(A32-Assumptions!$B$91)/(Assumptions!$B$92-Assumptions!$B$91))))*Assumptions!$B$81*Assumptions!$B$75+Assumptions!$B$82)*(1+Assumptions!$B$83)/12 -> 28270.833 | O32: =M32*Assumptions!$B$33 -> 1507.3135 | P32: =O32-N32 -> -26763.52 | Q32: =IF(A32>=Assumptions!$B$45,A32-Assumptions!$B$45+1,"") -> 19 | R32: =IF(Q32="","Not yet launched",IF(Q32<=6,"CP1: Launch",IF(Q32<=18,"CP2: Scale",IF(Q32<=36,"CP3: Mature","CP4: Steady")))) -> CP3: Mature | S32: =IF(Q32="",0,Assumptions!$B$46) -> 2000 | T32: =IF(Q32="",0,IF(Q32<=6,Assumptions!$B$14,IF(Q32<=18,Assumptions!$B$15,IF(Q32<=36,Assumptions!$B$16,Assumptions!$B$17)))) -> 0.08 | U32: =IF(Q32="",0,IF(Q32=1,Assumptions!$B$65,ROUND(MAX(W31,1)*T32,0))) -> 3 | V32: =IF(Q32="",0,ROUND(W31*Assumptions!$B$49,0)) -> 1 | W32: =IF(Q32="",0,MIN(W31+U32-V32,S32)) -> 40 | X32: =IF(Q32="",0,Assumptions!$B$53) -> 1 | Y32: =W32*X32 -> 40 | Z32: =L32 -> 46.06 | AA32: =Y32*Z32 -> 1842.4 | AB32: =IF(A32=Assumptions!$B$45,Assumptions!$B$47+Assumptions!$B$48,IF(A32>Assumptions!$B$45,Assumptions!$B$47,0)) -> 50 | AC32: =AA32*Assumptions!$B$33 -> 1566.04 | AD32: =I32+W32 -> 150 | AE32: =M32+AA32 -> 3615.71 | AF32: =N32+AB32+AJ32+AK32+AL32+Assumptions!$B$68 -> 33056.642 | AG32: =O32+AC32 -> 3073.3535 | AH32: =AG32-AF32 -> -29983.288 | AI32: =IFERROR((AD32-AD31)/AD31,"") -> 0.056338028 | AJ32: =MAX(Assumptions!$B$71,Assumptions!$B$69*0.5^(A32/Assumptions!$B$70))+Assumptions!$B$72*(K32+Y32) -> 102.475 | AK32: =IF(AND(Assumptions!$B$76=1,A32>=Assumptions!$B$77),Assumptions!$B$78/12,0) -> 4583.3333 | AL32: =IF(AND(Assumptions!$B$86=1,Q32<>""),Assumptions!$B$87/12,0) -> 0
A33: 32 | B33: Mar 2029 | C33: =IF(A33<=12,1,IF(A33<=24,2,IF(A33<=36,3,4))) -> 3 | D33: =IF(A33<=6,"P1: Pilot->Seed",IF(A33<=18,"P2: Scale/Series A",IF(A33<=36,"P3: Post-Series A","P4: Maturity"))) -> P3: Post-Series A | E33: =IF(C33=1,Assumptions!$B$5,IF(C33=2,Assumptions!$B$6,IF(C33=3,Assumptions!$B$7,Assumptions!$B$8))) -> 9000 | F33: =IF(A33<=6,Assumptions!$B$14,IF(A33<=18,Assumptions!$B$15,IF(A33<=36,Assumptions!$B$16,Assumptions!$B$17))) -> 0.08 | G33: =ROUND(MAX(I32,1)*F33,0) -> 9 | H33: =ROUND(I32*Assumptions!$B$18,0) -> 2 | I33: =MIN(I32+G33-H33,E33) -> 117 | J33: =Assumptions!$B$22 -> 0.55 | K33: =I33*J33 -> 64.35 | L33: =Assumptions!$B$10*(1-Assumptions!$B$12)+Assumptions!$B$11*Assumptions!$B$12 -> 46.06 | M33: =K33*L33 -> 2963.961 | N33: =((IF(A33<=Assumptions!$B$91,Assumptions!$B$90,IF(A33>=Assumptions!$B$92,1,Assumptions!$B$90+(1-Assumptions!$B$90)*(A33-Assumptions!$B$91)/(Assumptions!$B$92-Assumptions!$B$91))))*Assumptions!$B$81*Assumptions!$B$75+Assumptions!$B$82)*(1+Assumptions!$B$83)/12 -> 28270.833 | O33: =M33*Assumptions!$B$33 -> 2519.3668 | P33: =O33-N33 -> -25751.466 | Q33: =IF(A33>=Assumptions!$B$45,A33-Assumptions!$B$45+1,"") -> 20 | R33: =IF(Q33="","Not yet launched",IF(Q33<=6,"CP1: Launch",IF(Q33<=18,"CP2: Scale",IF(Q33<=36,"CP3: Mature","CP4: Steady")))) -> CP3: Mature | S33: =IF(Q33="",0,Assumptions!$B$46) -> 2000 | T33: =IF(Q33="",0,IF(Q33<=6,Assumptions!$B$14,IF(Q33<=18,Assumptions!$B$15,IF(Q33<=36,Assumptions!$B$16,Assumptions!$B$17)))) -> 0.08 | U33: =IF(Q33="",0,IF(Q33=1,Assumptions!$B$65,ROUND(MAX(W32,1)*T33,0))) -> 3 | V33: =IF(Q33="",0,ROUND(W32*Assumptions!$B$49,0)) -> 1 | W33: =IF(Q33="",0,MIN(W32+U33-V33,S33)) -> 42 | X33: =IF(Q33="",0,Assumptions!$B$54) -> 1 | Y33: =W33*X33 -> 42 | Z33: =L33 -> 46.06 | AA33: =Y33*Z33 -> 1934.52 | AB33: =IF(A33=Assumptions!$B$45,Assumptions!$B$47+Assumptions!$B$48,IF(A33>Assumptions!$B$45,Assumptions!$B$47,0)) -> 50 | AC33: =AA33*Assumptions!$B$33 -> 1644.342 | AD33: =I33+W33 -> 159 | AE33: =M33+AA33 -> 4898.481 | AF33: =N33+AB33+AJ33+AK33+AL33+Assumptions!$B$68 -> 33066.389 | AG33: =O33+AC33 -> 4163.7088 | AH33: =AG33-AF33 -> -28902.68 | AI33: =IFERROR((AD33-AD32)/AD32,"") -> 0.06 | AJ33: =MAX(Assumptions!$B$71,Assumptions!$B$69*0.5^(A33/Assumptions!$B$70))+Assumptions!$B$72*(K33+Y33) -> 112.2225 | AK33: =IF(AND(Assumptions!$B$76=1,A33>=Assumptions!$B$77),Assumptions!$B$78/12,0) -> 4583.3333 | AL33: =IF(AND(Assumptions!$B$86=1,Q33<>""),Assumptions!$B$87/12,0) -> 0
A34: 33 | B34: Apr 2029 | C34: =IF(A34<=12,1,IF(A34<=24,2,IF(A34<=36,3,4))) -> 3 | D34: =IF(A34<=6,"P1: Pilot->Seed",IF(A34<=18,"P2: Scale/Series A",IF(A34<=36,"P3: Post-Series A","P4: Maturity"))) -> P3: Post-Series A | E34: =IF(C34=1,Assumptions!$B$5,IF(C34=2,Assumptions!$B$6,IF(C34=3,Assumptions!$B$7,Assumptions!$B$8))) -> 9000 | F34: =IF(A34<=6,Assumptions!$B$14,IF(A34<=18,Assumptions!$B$15,IF(A34<=36,Assumptions!$B$16,Assumptions!$B$17))) -> 0.08 | G34: =ROUND(MAX(I33,1)*F34,0) -> 9 | H34: =ROUND(I33*Assumptions!$B$18,0) -> 2 | I34: =MIN(I33+G34-H34,E34) -> 124 | J34: =Assumptions!$B$23 -> 0.85 | K34: =I34*J34 -> 105.4 | L34: =Assumptions!$B$10*(1-Assumptions!$B$12)+Assumptions!$B$11*Assumptions!$B$12 -> 46.06 | M34: =K34*L34 -> 4854.724 | N34: =((IF(A34<=Assumptions!$B$91,Assumptions!$B$90,IF(A34>=Assumptions!$B$92,1,Assumptions!$B$90+(1-Assumptions!$B$90)*(A34-Assumptions!$B$91)/(Assumptions!$B$92-Assumptions!$B$91))))*Assumptions!$B$81*Assumptions!$B$75+Assumptions!$B$82)*(1+Assumptions!$B$83)/12 -> 28270.833 | O34: =M34*Assumptions!$B$33 -> 4126.5154 | P34: =O34-N34 -> -24144.318 | Q34: =IF(A34>=Assumptions!$B$45,A34-Assumptions!$B$45+1,"") -> 21 | R34: =IF(Q34="","Not yet launched",IF(Q34<=6,"CP1: Launch",IF(Q34<=18,"CP2: Scale",IF(Q34<=36,"CP3: Mature","CP4: Steady")))) -> CP3: Mature | S34: =IF(Q34="",0,Assumptions!$B$46) -> 2000 | T34: =IF(Q34="",0,IF(Q34<=6,Assumptions!$B$14,IF(Q34<=18,Assumptions!$B$15,IF(Q34<=36,Assumptions!$B$16,Assumptions!$B$17)))) -> 0.08 | U34: =IF(Q34="",0,IF(Q34=1,Assumptions!$B$65,ROUND(MAX(W33,1)*T34,0))) -> 3 | V34: =IF(Q34="",0,ROUND(W33*Assumptions!$B$49,0)) -> 1 | W34: =IF(Q34="",0,MIN(W33+U34-V34,S34)) -> 44 | X34: =IF(Q34="",0,Assumptions!$B$55) -> 0.9 | Y34: =W34*X34 -> 39.6 | Z34: =L34 -> 46.06 | AA34: =Y34*Z34 -> 1823.976 | AB34: =IF(A34=Assumptions!$B$45,Assumptions!$B$47+Assumptions!$B$48,IF(A34>Assumptions!$B$45,Assumptions!$B$47,0)) -> 50 | AC34: =AA34*Assumptions!$B$33 -> 1550.3796 | AD34: =I34+W34 -> 168 | AE34: =M34+AA34 -> 6678.7 | AF34: =N34+AB34+AJ34+AK34+AL34+Assumptions!$B$68 -> 33079.917 | AG34: =O34+AC34 -> 5676.895 | AH34: =AG34-AF34 -> -27403.022 | AI34: =IFERROR((AD34-AD33)/AD33,"") -> 0.056603774 | AJ34: =MAX(Assumptions!$B$71,Assumptions!$B$69*0.5^(A34/Assumptions!$B$70))+Assumptions!$B$72*(K34+Y34) -> 125.75 | AK34: =IF(AND(Assumptions!$B$76=1,A34>=Assumptions!$B$77),Assumptions!$B$78/12,0) -> 4583.3333 | AL34: =IF(AND(Assumptions!$B$86=1,Q34<>""),Assumptions!$B$87/12,0) -> 0
A35: 34 | B35: May 2029 | C35: =IF(A35<=12,1,IF(A35<=24,2,IF(A35<=36,3,4))) -> 3 | D35: =IF(A35<=6,"P1: Pilot->Seed",IF(A35<=18,"P2: Scale/Series A",IF(A35<=36,"P3: Post-Series A","P4: Maturity"))) -> P3: Post-Series A | E35: =IF(C35=1,Assumptions!$B$5,IF(C35=2,Assumptions!$B$6,IF(C35=3,Assumptions!$B$7,Assumptions!$B$8))) -> 9000 | F35: =IF(A35<=6,Assumptions!$B$14,IF(A35<=18,Assumptions!$B$15,IF(A35<=36,Assumptions!$B$16,Assumptions!$B$17))) -> 0.08 | G35: =ROUND(MAX(I34,1)*F35,0) -> 10 | H35: =ROUND(I34*Assumptions!$B$18,0) -> 2 | I35: =MIN(I34+G35-H35,E35) -> 132 | J35: =Assumptions!$B$24 -> 1 | K35: =I35*J35 -> 132 | L35: =Assumptions!$B$10*(1-Assumptions!$B$12)+Assumptions!$B$11*Assumptions!$B$12 -> 46.06 | M35: =K35*L35 -> 6079.92 | N35: =((IF(A35<=Assumptions!$B$91,Assumptions!$B$90,IF(A35>=Assumptions!$B$92,1,Assumptions!$B$90+(1-Assumptions!$B$90)*(A35-Assumptions!$B$91)/(Assumptions!$B$92-Assumptions!$B$91))))*Assumptions!$B$81*Assumptions!$B$75+Assumptions!$B$82)*(1+Assumptions!$B$83)/12 -> 28270.833 | O35: =M35*Assumptions!$B$33 -> 5167.932 | P35: =O35-N35 -> -23102.901 | Q35: =IF(A35>=Assumptions!$B$45,A35-Assumptions!$B$45+1,"") -> 22 | R35: =IF(Q35="","Not yet launched",IF(Q35<=6,"CP1: Launch",IF(Q35<=18,"CP2: Scale",IF(Q35<=36,"CP3: Mature","CP4: Steady")))) -> CP3: Mature | S35: =IF(Q35="",0,Assumptions!$B$46) -> 2000 | T35: =IF(Q35="",0,IF(Q35<=6,Assumptions!$B$14,IF(Q35<=18,Assumptions!$B$15,IF(Q35<=36,Assumptions!$B$16,Assumptions!$B$17)))) -> 0.08 | U35: =IF(Q35="",0,IF(Q35=1,Assumptions!$B$65,ROUND(MAX(W34,1)*T35,0))) -> 4 | V35: =IF(Q35="",0,ROUND(W34*Assumptions!$B$49,0)) -> 1 | W35: =IF(Q35="",0,MIN(W34+U35-V35,S35)) -> 47 | X35: =IF(Q35="",0,Assumptions!$B$56) -> 0.6 | Y35: =W35*X35 -> 28.2 | Z35: =L35 -> 46.06 | AA35: =Y35*Z35 -> 1298.892 | AB35: =IF(A35=Assumptions!$B$45,Assumptions!$B$47+Assumptions!$B$48,IF(A35>Assumptions!$B$45,Assumptions!$B$47,0)) -> 50 | AC35: =AA35*Assumptions!$B$33 -> 1104.0582 | AD35: =I35+W35 -> 179 | AE35: =M35+AA35 -> 7378.812 | AF35: =N35+AB35+AJ35+AK35+AL35+Assumptions!$B$68 -> 33085.237 | AG35: =O35+AC35 -> 6271.9902 | AH35: =AG35-AF35 -> -26813.246 | AI35: =IFERROR((AD35-AD34)/AD34,"") -> 0.06547619 | AJ35: =MAX(Assumptions!$B$71,Assumptions!$B$69*0.5^(A35/Assumptions!$B$70))+Assumptions!$B$72*(K35+Y35) -> 131.07 | AK35: =IF(AND(Assumptions!$B$76=1,A35>=Assumptions!$B$77),Assumptions!$B$78/12,0) -> 4583.3333 | AL35: =IF(AND(Assumptions!$B$86=1,Q35<>""),Assumptions!$B$87/12,0) -> 0
A36: 35 | B36: Jun 2029 | C36: =IF(A36<=12,1,IF(A36<=24,2,IF(A36<=36,3,4))) -> 3 | D36: =IF(A36<=6,"P1: Pilot->Seed",IF(A36<=18,"P2: Scale/Series A",IF(A36<=36,"P3: Post-Series A","P4: Maturity"))) -> P3: Post-Series A | E36: =IF(C36=1,Assumptions!$B$5,IF(C36=2,Assumptions!$B$6,IF(C36=3,Assumptions!$B$7,Assumptions!$B$8))) -> 9000 | F36: =IF(A36<=6,Assumptions!$B$14,IF(A36<=18,Assumptions!$B$15,IF(A36<=36,Assumptions!$B$16,Assumptions!$B$17))) -> 0.08 | G36: =ROUND(MAX(I35,1)*F36,0) -> 11 | H36: =ROUND(I35*Assumptions!$B$18,0) -> 3 | I36: =MIN(I35+G36-H36,E36) -> 140 | J36: =Assumptions!$B$25 -> 1 | K36: =I36*J36 -> 140 | L36: =Assumptions!$B$10*(1-Assumptions!$B$12)+Assumptions!$B$11*Assumptions!$B$12 -> 46.06 | M36: =K36*L36 -> 6448.4 | N36: =((IF(A36<=Assumptions!$B$91,Assumptions!$B$90,IF(A36>=Assumptions!$B$92,1,Assumptions!$B$90+(1-Assumptions!$B$90)*(A36-Assumptions!$B$91)/(Assumptions!$B$92-Assumptions!$B$91))))*Assumptions!$B$81*Assumptions!$B$75+Assumptions!$B$82)*(1+Assumptions!$B$83)/12 -> 28270.833 | O36: =M36*Assumptions!$B$33 -> 5481.14 | P36: =O36-N36 -> -22789.693 | Q36: =IF(A36>=Assumptions!$B$45,A36-Assumptions!$B$45+1,"") -> 23 | R36: =IF(Q36="","Not yet launched",IF(Q36<=6,"CP1: Launch",IF(Q36<=18,"CP2: Scale",IF(Q36<=36,"CP3: Mature","CP4: Steady")))) -> CP3: Mature | S36: =IF(Q36="",0,Assumptions!$B$46) -> 2000 | T36: =IF(Q36="",0,IF(Q36<=6,Assumptions!$B$14,IF(Q36<=18,Assumptions!$B$15,IF(Q36<=36,Assumptions!$B$16,Assumptions!$B$17)))) -> 0.08 | U36: =IF(Q36="",0,IF(Q36=1,Assumptions!$B$65,ROUND(MAX(W35,1)*T36,0))) -> 4 | V36: =IF(Q36="",0,ROUND(W35*Assumptions!$B$49,0)) -> 1 | W36: =IF(Q36="",0,MIN(W35+U36-V36,S36)) -> 50 | X36: =IF(Q36="",0,Assumptions!$B$57) -> 0.4 | Y36: =W36*X36 -> 20 | Z36: =L36 -> 46.06 | AA36: =Y36*Z36 -> 921.2 | AB36: =IF(A36=Assumptions!$B$45,Assumptions!$B$47+Assumptions!$B$48,IF(A36>Assumptions!$B$45,Assumptions!$B$47,0)) -> 50 | AC36: =AA36*Assumptions!$B$33 -> 783.02 | AD36: =I36+W36 -> 190 | AE36: =M36+AA36 -> 7369.6 | AF36: =N36+AB36+AJ36+AK36+AL36+Assumptions!$B$68 -> 33085.167 | AG36: =O36+AC36 -> 6264.16 | AH36: =AG36-AF36 -> -26821.007 | AI36: =IFERROR((AD36-AD35)/AD35,"") -> 0.061452514 | AJ36: =MAX(Assumptions!$B$71,Assumptions!$B$69*0.5^(A36/Assumptions!$B$70))+Assumptions!$B$72*(K36+Y36) -> 131 | AK36: =IF(AND(Assumptions!$B$76=1,A36>=Assumptions!$B$77),Assumptions!$B$78/12,0) -> 4583.3333 | AL36: =IF(AND(Assumptions!$B$86=1,Q36<>""),Assumptions!$B$87/12,0) -> 0
A37: 36 | B37: Jul 2029 | C37: =IF(A37<=12,1,IF(A37<=24,2,IF(A37<=36,3,4))) -> 3 | D37: =IF(A37<=6,"P1: Pilot->Seed",IF(A37<=18,"P2: Scale/Series A",IF(A37<=36,"P3: Post-Series A","P4: Maturity"))) -> P3: Post-Series A | E37: =IF(C37=1,Assumptions!$B$5,IF(C37=2,Assumptions!$B$6,IF(C37=3,Assumptions!$B$7,Assumptions!$B$8))) -> 9000 | F37: =IF(A37<=6,Assumptions!$B$14,IF(A37<=18,Assumptions!$B$15,IF(A37<=36,Assumptions!$B$16,Assumptions!$B$17))) -> 0.08 | G37: =ROUND(MAX(I36,1)*F37,0) -> 11 | H37: =ROUND(I36*Assumptions!$B$18,0) -> 3 | I37: =MIN(I36+G37-H37,E37) -> 148 | J37: =Assumptions!$B$26 -> 1 | K37: =I37*J37 -> 148 | L37: =Assumptions!$B$10*(1-Assumptions!$B$12)+Assumptions!$B$11*Assumptions!$B$12 -> 46.06 | M37: =K37*L37 -> 6816.88 | N37: =((IF(A37<=Assumptions!$B$91,Assumptions!$B$90,IF(A37>=Assumptions!$B$92,1,Assumptions!$B$90+(1-Assumptions!$B$90)*(A37-Assumptions!$B$91)/(Assumptions!$B$92-Assumptions!$B$91))))*Assumptions!$B$81*Assumptions!$B$75+Assumptions!$B$82)*(1+Assumptions!$B$83)/12 -> 28270.833 | O37: =M37*Assumptions!$B$33 -> 5794.348 | P37: =O37-N37 -> -22476.485 | Q37: =IF(A37>=Assumptions!$B$45,A37-Assumptions!$B$45+1,"") -> 24 | R37: =IF(Q37="","Not yet launched",IF(Q37<=6,"CP1: Launch",IF(Q37<=18,"CP2: Scale",IF(Q37<=36,"CP3: Mature","CP4: Steady")))) -> CP3: Mature | S37: =IF(Q37="",0,Assumptions!$B$46) -> 2000 | T37: =IF(Q37="",0,IF(Q37<=6,Assumptions!$B$14,IF(Q37<=18,Assumptions!$B$15,IF(Q37<=36,Assumptions!$B$16,Assumptions!$B$17)))) -> 0.08 | U37: =IF(Q37="",0,IF(Q37=1,Assumptions!$B$65,ROUND(MAX(W36,1)*T37,0))) -> 4 | V37: =IF(Q37="",0,ROUND(W36*Assumptions!$B$49,0)) -> 1 | W37: =IF(Q37="",0,MIN(W36+U37-V37,S37)) -> 53 | X37: =IF(Q37="",0,Assumptions!$B$58) -> 0.35 | Y37: =W37*X37 -> 18.55 | Z37: =L37 -> 46.06 | AA37: =Y37*Z37 -> 854.413 | AB37: =IF(A37=Assumptions!$B$45,Assumptions!$B$47+Assumptions!$B$48,IF(A37>Assumptions!$B$45,Assumptions!$B$47,0)) -> 50 | AC37: =AA37*Assumptions!$B$33 -> 726.25105 | AD37: =I37+W37 -> 201 | AE37: =M37+AA37 -> 7671.293 | AF37: =N37+AB37+AJ37+AK37+AL37+Assumptions!$B$68 -> 33087.459 | AG37: =O37+AC37 -> 6520.599 | AH37: =AG37-AF37 -> -26566.86 | AI37: =IFERROR((AD37-AD36)/AD36,"") -> 0.057894737 | AJ37: =MAX(Assumptions!$B$71,Assumptions!$B$69*0.5^(A37/Assumptions!$B$70))+Assumptions!$B$72*(K37+Y37) -> 133.2925 | AK37: =IF(AND(Assumptions!$B$76=1,A37>=Assumptions!$B$77),Assumptions!$B$78/12,0) -> 4583.3333 | AL37: =IF(AND(Assumptions!$B$86=1,Q37<>""),Assumptions!$B$87/12,0) -> 0
A38: 37 | B38: Aug 2029 | C38: =IF(A38<=12,1,IF(A38<=24,2,IF(A38<=36,3,4))) -> 4 | D38: =IF(A38<=6,"P1: Pilot->Seed",IF(A38<=18,"P2: Scale/Series A",IF(A38<=36,"P3: Post-Series A","P4: Maturity"))) -> P4: Maturity | E38: =IF(C38=1,Assumptions!$B$5,IF(C38=2,Assumptions!$B$6,IF(C38=3,Assumptions!$B$7,Assumptions!$B$8))) -> 15000 | F38: =IF(A38<=6,Assumptions!$B$14,IF(A38<=18,Assumptions!$B$15,IF(A38<=36,Assumptions!$B$16,Assumptions!$B$17))) -> 0.05 | G38: =ROUND(MAX(I37,1)*F38,0) -> 7 | H38: =ROUND(I37*Assumptions!$B$18,0) -> 3 | I38: =MIN(I37+G38-H38,E38) -> 152 | J38: =Assumptions!$B$27 -> 1 | K38: =I38*J38 -> 152 | L38: =Assumptions!$B$10*(1-Assumptions!$B$12)+Assumptions!$B$11*Assumptions!$B$12 -> 46.06 | M38: =K38*L38 -> 7001.12 | N38: =((IF(A38<=Assumptions!$B$91,Assumptions!$B$90,IF(A38>=Assumptions!$B$92,1,Assumptions!$B$90+(1-Assumptions!$B$90)*(A38-Assumptions!$B$91)/(Assumptions!$B$92-Assumptions!$B$91))))*Assumptions!$B$81*Assumptions!$B$75+Assumptions!$B$82)*(1+Assumptions!$B$83)/12 -> 28270.833 | O38: =M38*Assumptions!$B$33 -> 5950.952 | P38: =O38-N38 -> -22319.881 | Q38: =IF(A38>=Assumptions!$B$45,A38-Assumptions!$B$45+1,"") -> 25 | R38: =IF(Q38="","Not yet launched",IF(Q38<=6,"CP1: Launch",IF(Q38<=18,"CP2: Scale",IF(Q38<=36,"CP3: Mature","CP4: Steady")))) -> CP3: Mature | S38: =IF(Q38="",0,Assumptions!$B$46) -> 2000 | T38: =IF(Q38="",0,IF(Q38<=6,Assumptions!$B$14,IF(Q38<=18,Assumptions!$B$15,IF(Q38<=36,Assumptions!$B$16,Assumptions!$B$17)))) -> 0.08 | U38: =IF(Q38="",0,IF(Q38=1,Assumptions!$B$65,ROUND(MAX(W37,1)*T38,0))) -> 4 | V38: =IF(Q38="",0,ROUND(W37*Assumptions!$B$49,0)) -> 1 | W38: =IF(Q38="",0,MIN(W37+U38-V38,S38)) -> 56 | X38: =IF(Q38="",0,Assumptions!$B$59) -> 0.35 | Y38: =W38*X38 -> 19.6 | Z38: =L38 -> 46.06 | AA38: =Y38*Z38 -> 902.776 | AB38: =IF(A38=Assumptions!$B$45,Assumptions!$B$47+Assumptions!$B$48,IF(A38>Assumptions!$B$45,Assumptions!$B$47,0)) -> 50 | AC38: =AA38*Assumptions!$B$33 -> 767.3596 | AD38: =I38+W38 -> 208 | AE38: =M38+AA38 -> 7903.896 | AF38: =N38+AB38+AJ38+AK38+AL38+Assumptions!$B$68 -> 33089.227 | AG38: =O38+AC38 -> 6718.3116 | AH38: =AG38-AF38 -> -26370.915 | AI38: =IFERROR((AD38-AD37)/AD37,"") -> 0.034825871 | AJ38: =MAX(Assumptions!$B$71,Assumptions!$B$69*0.5^(A38/Assumptions!$B$70))+Assumptions!$B$72*(K38+Y38) -> 135.06 | AK38: =IF(AND(Assumptions!$B$76=1,A38>=Assumptions!$B$77),Assumptions!$B$78/12,0) -> 4583.3333 | AL38: =IF(AND(Assumptions!$B$86=1,Q38<>""),Assumptions!$B$87/12,0) -> 0
A39: 38 | B39: Sep 2029 | C39: =IF(A39<=12,1,IF(A39<=24,2,IF(A39<=36,3,4))) -> 4 | D39: =IF(A39<=6,"P1: Pilot->Seed",IF(A39<=18,"P2: Scale/Series A",IF(A39<=36,"P3: Post-Series A","P4: Maturity"))) -> P4: Maturity | E39: =IF(C39=1,Assumptions!$B$5,IF(C39=2,Assumptions!$B$6,IF(C39=3,Assumptions!$B$7,Assumptions!$B$8))) -> 15000 | F39: =IF(A39<=6,Assumptions!$B$14,IF(A39<=18,Assumptions!$B$15,IF(A39<=36,Assumptions!$B$16,Assumptions!$B$17))) -> 0.05 | G39: =ROUND(MAX(I38,1)*F39,0) -> 8 | H39: =ROUND(I38*Assumptions!$B$18,0) -> 3 | I39: =MIN(I38+G39-H39,E39) -> 157 | J39: =Assumptions!$B$28 -> 1 | K39: =I39*J39 -> 157 | L39: =Assumptions!$B$10*(1-Assumptions!$B$12)+Assumptions!$B$11*Assumptions!$B$12 -> 46.06 | M39: =K39*L39 -> 7231.42 | N39: =((IF(A39<=Assumptions!$B$91,Assumptions!$B$90,IF(A39>=Assumptions!$B$92,1,Assumptions!$B$90+(1-Assumptions!$B$90)*(A39-Assumptions!$B$91)/(Assumptions!$B$92-Assumptions!$B$91))))*Assumptions!$B$81*Assumptions!$B$75+Assumptions!$B$82)*(1+Assumptions!$B$83)/12 -> 28270.833 | O39: =M39*Assumptions!$B$33 -> 6146.707 | P39: =O39-N39 -> -22124.126 | Q39: =IF(A39>=Assumptions!$B$45,A39-Assumptions!$B$45+1,"") -> 26 | R39: =IF(Q39="","Not yet launched",IF(Q39<=6,"CP1: Launch",IF(Q39<=18,"CP2: Scale",IF(Q39<=36,"CP3: Mature","CP4: Steady")))) -> CP3: Mature | S39: =IF(Q39="",0,Assumptions!$B$46) -> 2000 | T39: =IF(Q39="",0,IF(Q39<=6,Assumptions!$B$14,IF(Q39<=18,Assumptions!$B$15,IF(Q39<=36,Assumptions!$B$16,Assumptions!$B$17)))) -> 0.08 | U39: =IF(Q39="",0,IF(Q39=1,Assumptions!$B$65,ROUND(MAX(W38,1)*T39,0))) -> 4 | V39: =IF(Q39="",0,ROUND(W38*Assumptions!$B$49,0)) -> 1 | W39: =IF(Q39="",0,MIN(W38+U39-V39,S39)) -> 59 | X39: =IF(Q39="",0,Assumptions!$B$60) -> 0.35 | Y39: =W39*X39 -> 20.65 | Z39: =L39 -> 46.06 | AA39: =Y39*Z39 -> 951.139 | AB39: =IF(A39=Assumptions!$B$45,Assumptions!$B$47+Assumptions!$B$48,IF(A39>Assumptions!$B$45,Assumptions!$B$47,0)) -> 50 | AC39: =AA39*Assumptions!$B$33 -> 808.46815 | AD39: =I39+W39 -> 216 | AE39: =M39+AA39 -> 8182.559 | AF39: =N39+AB39+AJ39+AK39+AL39+Assumptions!$B$68 -> 33091.344 | AG39: =O39+AC39 -> 6955.1752 | AH39: =AG39-AF39 -> -26136.169 | AI39: =IFERROR((AD39-AD38)/AD38,"") -> 0.038461538 | AJ39: =MAX(Assumptions!$B$71,Assumptions!$B$69*0.5^(A39/Assumptions!$B$70))+Assumptions!$B$72*(K39+Y39) -> 137.1775 | AK39: =IF(AND(Assumptions!$B$76=1,A39>=Assumptions!$B$77),Assumptions!$B$78/12,0) -> 4583.3333 | AL39: =IF(AND(Assumptions!$B$86=1,Q39<>""),Assumptions!$B$87/12,0) -> 0
A40: 39 | B40: Oct 2029 | C40: =IF(A40<=12,1,IF(A40<=24,2,IF(A40<=36,3,4))) -> 4 | D40: =IF(A40<=6,"P1: Pilot->Seed",IF(A40<=18,"P2: Scale/Series A",IF(A40<=36,"P3: Post-Series A","P4: Maturity"))) -> P4: Maturity | E40: =IF(C40=1,Assumptions!$B$5,IF(C40=2,Assumptions!$B$6,IF(C40=3,Assumptions!$B$7,Assumptions!$B$8))) -> 15000 | F40: =IF(A40<=6,Assumptions!$B$14,IF(A40<=18,Assumptions!$B$15,IF(A40<=36,Assumptions!$B$16,Assumptions!$B$17))) -> 0.05 | G40: =ROUND(MAX(I39,1)*F40,0) -> 8 | H40: =ROUND(I39*Assumptions!$B$18,0) -> 3 | I40: =MIN(I39+G40-H40,E40) -> 162 | J40: =Assumptions!$B$29 -> 0.85 | K40: =I40*J40 -> 137.7 | L40: =Assumptions!$B$10*(1-Assumptions!$B$12)+Assumptions!$B$11*Assumptions!$B$12 -> 46.06 | M40: =K40*L40 -> 6342.462 | N40: =((IF(A40<=Assumptions!$B$91,Assumptions!$B$90,IF(A40>=Assumptions!$B$92,1,Assumptions!$B$90+(1-Assumptions!$B$90)*(A40-Assumptions!$B$91)/(Assumptions!$B$92-Assumptions!$B$91))))*Assumptions!$B$81*Assumptions!$B$75+Assumptions!$B$82)*(1+Assumptions!$B$83)/12 -> 28270.833 | O40: =M40*Assumptions!$B$33 -> 5391.0927 | P40: =O40-N40 -> -22879.741 | Q40: =IF(A40>=Assumptions!$B$45,A40-Assumptions!$B$45+1,"") -> 27 | R40: =IF(Q40="","Not yet launched",IF(Q40<=6,"CP1: Launch",IF(Q40<=18,"CP2: Scale",IF(Q40<=36,"CP3: Mature","CP4: Steady")))) -> CP3: Mature | S40: =IF(Q40="",0,Assumptions!$B$46) -> 2000 | T40: =IF(Q40="",0,IF(Q40<=6,Assumptions!$B$14,IF(Q40<=18,Assumptions!$B$15,IF(Q40<=36,Assumptions!$B$16,Assumptions!$B$17)))) -> 0.08 | U40: =IF(Q40="",0,IF(Q40=1,Assumptions!$B$65,ROUND(MAX(W39,1)*T40,0))) -> 5 | V40: =IF(Q40="",0,ROUND(W39*Assumptions!$B$49,0)) -> 1 | W40: =IF(Q40="",0,MIN(W39+U40-V40,S40)) -> 63 | X40: =IF(Q40="",0,Assumptions!$B$61) -> 0.4 | Y40: =W40*X40 -> 25.2 | Z40: =L40 -> 46.06 | AA40: =Y40*Z40 -> 1160.712 | AB40: =IF(A40=Assumptions!$B$45,Assumptions!$B$47+Assumptions!$B$48,IF(A40>Assumptions!$B$45,Assumptions!$B$47,0)) -> 50 | AC40: =AA40*Assumptions!$B$33 -> 986.6052 | AD40: =I40+W40 -> 225 | AE40: =M40+AA40 -> 7503.174 | AF40: =N40+AB40+AJ40+AK40+AL40+Assumptions!$B$68 -> 33086.182 | AG40: =O40+AC40 -> 6377.6979 | AH40: =AG40-AF40 -> -26708.484 | AI40: =IFERROR((AD40-AD39)/AD39,"") -> 0.041666667 | AJ40: =MAX(Assumptions!$B$71,Assumptions!$B$69*0.5^(A40/Assumptions!$B$70))+Assumptions!$B$72*(K40+Y40) -> 132.015 | AK40: =IF(AND(Assumptions!$B$76=1,A40>=Assumptions!$B$77),Assumptions!$B$78/12,0) -> 4583.3333 | AL40: =IF(AND(Assumptions!$B$86=1,Q40<>""),Assumptions!$B$87/12,0) -> 0
A41: 40 | B41: Nov 2029 | C41: =IF(A41<=12,1,IF(A41<=24,2,IF(A41<=36,3,4))) -> 4 | D41: =IF(A41<=6,"P1: Pilot->Seed",IF(A41<=18,"P2: Scale/Series A",IF(A41<=36,"P3: Post-Series A","P4: Maturity"))) -> P4: Maturity | E41: =IF(C41=1,Assumptions!$B$5,IF(C41=2,Assumptions!$B$6,IF(C41=3,Assumptions!$B$7,Assumptions!$B$8))) -> 15000 | F41: =IF(A41<=6,Assumptions!$B$14,IF(A41<=18,Assumptions!$B$15,IF(A41<=36,Assumptions!$B$16,Assumptions!$B$17))) -> 0.05 | G41: =ROUND(MAX(I40,1)*F41,0) -> 8 | H41: =ROUND(I40*Assumptions!$B$18,0) -> 3 | I41: =MIN(I40+G41-H41,E41) -> 167 | J41: =Assumptions!$B$30 -> 0.45 | K41: =I41*J41 -> 75.15 | L41: =Assumptions!$B$10*(1-Assumptions!$B$12)+Assumptions!$B$11*Assumptions!$B$12 -> 46.06 | M41: =K41*L41 -> 3461.409 | N41: =((IF(A41<=Assumptions!$B$91,Assumptions!$B$90,IF(A41>=Assumptions!$B$92,1,Assumptions!$B$90+(1-Assumptions!$B$90)*(A41-Assumptions!$B$91)/(Assumptions!$B$92-Assumptions!$B$91))))*Assumptions!$B$81*Assumptions!$B$75+Assumptions!$B$82)*(1+Assumptions!$B$83)/12 -> 28270.833 | O41: =M41*Assumptions!$B$33 -> 2942.1977 | P41: =O41-N41 -> -25328.636 | Q41: =IF(A41>=Assumptions!$B$45,A41-Assumptions!$B$45+1,"") -> 28 | R41: =IF(Q41="","Not yet launched",IF(Q41<=6,"CP1: Launch",IF(Q41<=18,"CP2: Scale",IF(Q41<=36,"CP3: Mature","CP4: Steady")))) -> CP3: Mature | S41: =IF(Q41="",0,Assumptions!$B$46) -> 2000 | T41: =IF(Q41="",0,IF(Q41<=6,Assumptions!$B$14,IF(Q41<=18,Assumptions!$B$15,IF(Q41<=36,Assumptions!$B$16,Assumptions!$B$17)))) -> 0.08 | U41: =IF(Q41="",0,IF(Q41=1,Assumptions!$B$65,ROUND(MAX(W40,1)*T41,0))) -> 5 | V41: =IF(Q41="",0,ROUND(W40*Assumptions!$B$49,0)) -> 1 | W41: =IF(Q41="",0,MIN(W40+U41-V41,S41)) -> 67 | X41: =IF(Q41="",0,Assumptions!$B$62) -> 0.55 | Y41: =W41*X41 -> 36.85 | Z41: =L41 -> 46.06 | AA41: =Y41*Z41 -> 1697.311 | AB41: =IF(A41=Assumptions!$B$45,Assumptions!$B$47+Assumptions!$B$48,IF(A41>Assumptions!$B$45,Assumptions!$B$47,0)) -> 50 | AC41: =AA41*Assumptions!$B$33 -> 1442.7143 | AD41: =I41+W41 -> 234 | AE41: =M41+AA41 -> 5158.72 | AF41: =N41+AB41+AJ41+AK41+AL41+Assumptions!$B$68 -> 33068.367 | AG41: =O41+AC41 -> 4384.912 | AH41: =AG41-AF41 -> -28683.455 | AI41: =IFERROR((AD41-AD40)/AD40,"") -> 0.04 | AJ41: =MAX(Assumptions!$B$71,Assumptions!$B$69*0.5^(A41/Assumptions!$B$70))+Assumptions!$B$72*(K41+Y41) -> 114.2 | AK41: =IF(AND(Assumptions!$B$76=1,A41>=Assumptions!$B$77),Assumptions!$B$78/12,0) -> 4583.3333 | AL41: =IF(AND(Assumptions!$B$86=1,Q41<>""),Assumptions!$B$87/12,0) -> 0
A42: 41 | B42: Dec 2029 | C42: =IF(A42<=12,1,IF(A42<=24,2,IF(A42<=36,3,4))) -> 4 | D42: =IF(A42<=6,"P1: Pilot->Seed",IF(A42<=18,"P2: Scale/Series A",IF(A42<=36,"P3: Post-Series A","P4: Maturity"))) -> P4: Maturity | E42: =IF(C42=1,Assumptions!$B$5,IF(C42=2,Assumptions!$B$6,IF(C42=3,Assumptions!$B$7,Assumptions!$B$8))) -> 15000 | F42: =IF(A42<=6,Assumptions!$B$14,IF(A42<=18,Assumptions!$B$15,IF(A42<=36,Assumptions!$B$16,Assumptions!$B$17))) -> 0.05 | G42: =ROUND(MAX(I41,1)*F42,0) -> 8 | H42: =ROUND(I41*Assumptions!$B$18,0) -> 3 | I42: =MIN(I41+G42-H42,E42) -> 172 | J42: =Assumptions!$B$31 -> 0.35 | K42: =I42*J42 -> 60.2 | L42: =Assumptions!$B$10*(1-Assumptions!$B$12)+Assumptions!$B$11*Assumptions!$B$12 -> 46.06 | M42: =K42*L42 -> 2772.812 | N42: =((IF(A42<=Assumptions!$B$91,Assumptions!$B$90,IF(A42>=Assumptions!$B$92,1,Assumptions!$B$90+(1-Assumptions!$B$90)*(A42-Assumptions!$B$91)/(Assumptions!$B$92-Assumptions!$B$91))))*Assumptions!$B$81*Assumptions!$B$75+Assumptions!$B$82)*(1+Assumptions!$B$83)/12 -> 28270.833 | O42: =M42*Assumptions!$B$33 -> 2356.8902 | P42: =O42-N42 -> -25913.943 | Q42: =IF(A42>=Assumptions!$B$45,A42-Assumptions!$B$45+1,"") -> 29 | R42: =IF(Q42="","Not yet launched",IF(Q42<=6,"CP1: Launch",IF(Q42<=18,"CP2: Scale",IF(Q42<=36,"CP3: Mature","CP4: Steady")))) -> CP3: Mature | S42: =IF(Q42="",0,Assumptions!$B$46) -> 2000 | T42: =IF(Q42="",0,IF(Q42<=6,Assumptions!$B$14,IF(Q42<=18,Assumptions!$B$15,IF(Q42<=36,Assumptions!$B$16,Assumptions!$B$17)))) -> 0.08 | U42: =IF(Q42="",0,IF(Q42=1,Assumptions!$B$65,ROUND(MAX(W41,1)*T42,0))) -> 5 | V42: =IF(Q42="",0,ROUND(W41*Assumptions!$B$49,0)) -> 1 | W42: =IF(Q42="",0,MIN(W41+U42-V42,S42)) -> 71 | X42: =IF(Q42="",0,Assumptions!$B$63) -> 0.9 | Y42: =W42*X42 -> 63.9 | Z42: =L42 -> 46.06 | AA42: =Y42*Z42 -> 2943.234 | AB42: =IF(A42=Assumptions!$B$45,Assumptions!$B$47+Assumptions!$B$48,IF(A42>Assumptions!$B$45,Assumptions!$B$47,0)) -> 50 | AC42: =AA42*Assumptions!$B$33 -> 2501.7489 | AD42: =I42+W42 -> 243 | AE42: =M42+AA42 -> 5716.046 | AF42: =N42+AB42+AJ42+AK42+AL42+Assumptions!$B$68 -> 33072.602 | AG42: =O42+AC42 -> 4858.6391 | AH42: =AG42-AF42 -> -28213.963 | AI42: =IFERROR((AD42-AD41)/AD41,"") -> 0.038461538 | AJ42: =MAX(Assumptions!$B$71,Assumptions!$B$69*0.5^(A42/Assumptions!$B$70))+Assumptions!$B$72*(K42+Y42) -> 118.435 | AK42: =IF(AND(Assumptions!$B$76=1,A42>=Assumptions!$B$77),Assumptions!$B$78/12,0) -> 4583.3333 | AL42: =IF(AND(Assumptions!$B$86=1,Q42<>""),Assumptions!$B$87/12,0) -> 0
A43: 42 | B43: Jan 2030 | C43: =IF(A43<=12,1,IF(A43<=24,2,IF(A43<=36,3,4))) -> 4 | D43: =IF(A43<=6,"P1: Pilot->Seed",IF(A43<=18,"P2: Scale/Series A",IF(A43<=36,"P3: Post-Series A","P4: Maturity"))) -> P4: Maturity | E43: =IF(C43=1,Assumptions!$B$5,IF(C43=2,Assumptions!$B$6,IF(C43=3,Assumptions!$B$7,Assumptions!$B$8))) -> 15000 | F43: =IF(A43<=6,Assumptions!$B$14,IF(A43<=18,Assumptions!$B$15,IF(A43<=36,Assumptions!$B$16,Assumptions!$B$17))) -> 0.05 | G43: =ROUND(MAX(I42,1)*F43,0) -> 9 | H43: =ROUND(I42*Assumptions!$B$18,0) -> 3 | I43: =MIN(I42+G43-H43,E43) -> 178 | J43: =Assumptions!$B$20 -> 0.35 | K43: =I43*J43 -> 62.3 | L43: =Assumptions!$B$10*(1-Assumptions!$B$12)+Assumptions!$B$11*Assumptions!$B$12 -> 46.06 | M43: =K43*L43 -> 2869.538 | N43: =((IF(A43<=Assumptions!$B$91,Assumptions!$B$90,IF(A43>=Assumptions!$B$92,1,Assumptions!$B$90+(1-Assumptions!$B$90)*(A43-Assumptions!$B$91)/(Assumptions!$B$92-Assumptions!$B$91))))*Assumptions!$B$81*Assumptions!$B$75+Assumptions!$B$82)*(1+Assumptions!$B$83)/12 -> 28270.833 | O43: =M43*Assumptions!$B$33 -> 2439.1073 | P43: =O43-N43 -> -25831.726 | Q43: =IF(A43>=Assumptions!$B$45,A43-Assumptions!$B$45+1,"") -> 30 | R43: =IF(Q43="","Not yet launched",IF(Q43<=6,"CP1: Launch",IF(Q43<=18,"CP2: Scale",IF(Q43<=36,"CP3: Mature","CP4: Steady")))) -> CP3: Mature | S43: =IF(Q43="",0,Assumptions!$B$46) -> 2000 | T43: =IF(Q43="",0,IF(Q43<=6,Assumptions!$B$14,IF(Q43<=18,Assumptions!$B$15,IF(Q43<=36,Assumptions!$B$16,Assumptions!$B$17)))) -> 0.08 | U43: =IF(Q43="",0,IF(Q43=1,Assumptions!$B$65,ROUND(MAX(W42,1)*T43,0))) -> 6 | V43: =IF(Q43="",0,ROUND(W42*Assumptions!$B$49,0)) -> 1 | W43: =IF(Q43="",0,MIN(W42+U43-V43,S43)) -> 76 | X43: =IF(Q43="",0,Assumptions!$B$52) -> 1 | Y43: =W43*X43 -> 76 | Z43: =L43 -> 46.06 | AA43: =Y43*Z43 -> 3500.56 | AB43: =IF(A43=Assumptions!$B$45,Assumptions!$B$47+Assumptions!$B$48,IF(A43>Assumptions!$B$45,Assumptions!$B$47,0)) -> 50 | AC43: =AA43*Assumptions!$B$33 -> 2975.476 | AD43: =I43+W43 -> 254 | AE43: =M43+AA43 -> 6370.098 | AF43: =N43+AB43+AJ43+AK43+AL43+Assumptions!$B$68 -> 33077.572 | AG43: =O43+AC43 -> 5414.5833 | AH43: =AG43-AF43 -> -27662.988 | AI43: =IFERROR((AD43-AD42)/AD42,"") -> 0.04526749 | AJ43: =MAX(Assumptions!$B$71,Assumptions!$B$69*0.5^(A43/Assumptions!$B$70))+Assumptions!$B$72*(K43+Y43) -> 123.405 | AK43: =IF(AND(Assumptions!$B$76=1,A43>=Assumptions!$B$77),Assumptions!$B$78/12,0) -> 4583.3333 | AL43: =IF(AND(Assumptions!$B$86=1,Q43<>""),Assumptions!$B$87/12,0) -> 0
A44: 43 | B44: Feb 2030 | C44: =IF(A44<=12,1,IF(A44<=24,2,IF(A44<=36,3,4))) -> 4 | D44: =IF(A44<=6,"P1: Pilot->Seed",IF(A44<=18,"P2: Scale/Series A",IF(A44<=36,"P3: Post-Series A","P4: Maturity"))) -> P4: Maturity | E44: =IF(C44=1,Assumptions!$B$5,IF(C44=2,Assumptions!$B$6,IF(C44=3,Assumptions!$B$7,Assumptions!$B$8))) -> 15000 | F44: =IF(A44<=6,Assumptions!$B$14,IF(A44<=18,Assumptions!$B$15,IF(A44<=36,Assumptions!$B$16,Assumptions!$B$17))) -> 0.05 | G44: =ROUND(MAX(I43,1)*F44,0) -> 9 | H44: =ROUND(I43*Assumptions!$B$18,0) -> 4 | I44: =MIN(I43+G44-H44,E44) -> 183 | J44: =Assumptions!$B$21 -> 0.35 | K44: =I44*J44 -> 64.05 | L44: =Assumptions!$B$10*(1-Assumptions!$B$12)+Assumptions!$B$11*Assumptions!$B$12 -> 46.06 | M44: =K44*L44 -> 2950.143 | N44: =((IF(A44<=Assumptions!$B$91,Assumptions!$B$90,IF(A44>=Assumptions!$B$92,1,Assumptions!$B$90+(1-Assumptions!$B$90)*(A44-Assumptions!$B$91)/(Assumptions!$B$92-Assumptions!$B$91))))*Assumptions!$B$81*Assumptions!$B$75+Assumptions!$B$82)*(1+Assumptions!$B$83)/12 -> 28270.833 | O44: =M44*Assumptions!$B$33 -> 2507.6215 | P44: =O44-N44 -> -25763.212 | Q44: =IF(A44>=Assumptions!$B$45,A44-Assumptions!$B$45+1,"") -> 31 | R44: =IF(Q44="","Not yet launched",IF(Q44<=6,"CP1: Launch",IF(Q44<=18,"CP2: Scale",IF(Q44<=36,"CP3: Mature","CP4: Steady")))) -> CP3: Mature | S44: =IF(Q44="",0,Assumptions!$B$46) -> 2000 | T44: =IF(Q44="",0,IF(Q44<=6,Assumptions!$B$14,IF(Q44<=18,Assumptions!$B$15,IF(Q44<=36,Assumptions!$B$16,Assumptions!$B$17)))) -> 0.08 | U44: =IF(Q44="",0,IF(Q44=1,Assumptions!$B$65,ROUND(MAX(W43,1)*T44,0))) -> 6 | V44: =IF(Q44="",0,ROUND(W43*Assumptions!$B$49,0)) -> 2 | W44: =IF(Q44="",0,MIN(W43+U44-V44,S44)) -> 80 | X44: =IF(Q44="",0,Assumptions!$B$53) -> 1 | Y44: =W44*X44 -> 80 | Z44: =L44 -> 46.06 | AA44: =Y44*Z44 -> 3684.8 | AB44: =IF(A44=Assumptions!$B$45,Assumptions!$B$47+Assumptions!$B$48,IF(A44>Assumptions!$B$45,Assumptions!$B$47,0)) -> 50 | AC44: =AA44*Assumptions!$B$33 -> 3132.08 | AD44: =I44+W44 -> 263 | AE44: =M44+AA44 -> 6634.943 | AF44: =N44+AB44+AJ44+AK44+AL44+Assumptions!$B$68 -> 33079.584 | AG44: =O44+AC44 -> 5639.7015 | AH44: =AG44-AF44 -> -27439.883 | AI44: =IFERROR((AD44-AD43)/AD43,"") -> 0.035433071 | AJ44: =MAX(Assumptions!$B$71,Assumptions!$B$69*0.5^(A44/Assumptions!$B$70))+Assumptions!$B$72*(K44+Y44) -> 125.4175 | AK44: =IF(AND(Assumptions!$B$76=1,A44>=Assumptions!$B$77),Assumptions!$B$78/12,0) -> 4583.3333 | AL44: =IF(AND(Assumptions!$B$86=1,Q44<>""),Assumptions!$B$87/12,0) -> 0
A45: 44 | B45: Mar 2030 | C45: =IF(A45<=12,1,IF(A45<=24,2,IF(A45<=36,3,4))) -> 4 | D45: =IF(A45<=6,"P1: Pilot->Seed",IF(A45<=18,"P2: Scale/Series A",IF(A45<=36,"P3: Post-Series A","P4: Maturity"))) -> P4: Maturity | E45: =IF(C45=1,Assumptions!$B$5,IF(C45=2,Assumptions!$B$6,IF(C45=3,Assumptions!$B$7,Assumptions!$B$8))) -> 15000 | F45: =IF(A45<=6,Assumptions!$B$14,IF(A45<=18,Assumptions!$B$15,IF(A45<=36,Assumptions!$B$16,Assumptions!$B$17))) -> 0.05 | G45: =ROUND(MAX(I44,1)*F45,0) -> 9 | H45: =ROUND(I44*Assumptions!$B$18,0) -> 4 | I45: =MIN(I44+G45-H45,E45) -> 188 | J45: =Assumptions!$B$22 -> 0.55 | K45: =I45*J45 -> 103.4 | L45: =Assumptions!$B$10*(1-Assumptions!$B$12)+Assumptions!$B$11*Assumptions!$B$12 -> 46.06 | M45: =K45*L45 -> 4762.604 | N45: =((IF(A45<=Assumptions!$B$91,Assumptions!$B$90,IF(A45>=Assumptions!$B$92,1,Assumptions!$B$90+(1-Assumptions!$B$90)*(A45-Assumptions!$B$91)/(Assumptions!$B$92-Assumptions!$B$91))))*Assumptions!$B$81*Assumptions!$B$75+Assumptions!$B$82)*(1+Assumptions!$B$83)/12 -> 28270.833 | O45: =M45*Assumptions!$B$33 -> 4048.2134 | P45: =O45-N45 -> -24222.62 | Q45: =IF(A45>=Assumptions!$B$45,A45-Assumptions!$B$45+1,"") -> 32 | R45: =IF(Q45="","Not yet launched",IF(Q45<=6,"CP1: Launch",IF(Q45<=18,"CP2: Scale",IF(Q45<=36,"CP3: Mature","CP4: Steady")))) -> CP3: Mature | S45: =IF(Q45="",0,Assumptions!$B$46) -> 2000 | T45: =IF(Q45="",0,IF(Q45<=6,Assumptions!$B$14,IF(Q45<=18,Assumptions!$B$15,IF(Q45<=36,Assumptions!$B$16,Assumptions!$B$17)))) -> 0.08 | U45: =IF(Q45="",0,IF(Q45=1,Assumptions!$B$65,ROUND(MAX(W44,1)*T45,0))) -> 6 | V45: =IF(Q45="",0,ROUND(W44*Assumptions!$B$49,0)) -> 2 | W45: =IF(Q45="",0,MIN(W44+U45-V45,S45)) -> 84 | X45: =IF(Q45="",0,Assumptions!$B$54) -> 1 | Y45: =W45*X45 -> 84 | Z45: =L45 -> 46.06 | AA45: =Y45*Z45 -> 3869.04 | AB45: =IF(A45=Assumptions!$B$45,Assumptions!$B$47+Assumptions!$B$48,IF(A45>Assumptions!$B$45,Assumptions!$B$47,0)) -> 50 | AC45: =AA45*Assumptions!$B$33 -> 3288.684 | AD45: =I45+W45 -> 272 | AE45: =M45+AA45 -> 8631.644 | AF45: =N45+AB45+AJ45+AK45+AL45+Assumptions!$B$68 -> 33094.757 | AG45: =O45+AC45 -> 7336.8974 | AH45: =AG45-AF45 -> -25757.859 | AI45: =IFERROR((AD45-AD44)/AD44,"") -> 0.034220532 | AJ45: =MAX(Assumptions!$B$71,Assumptions!$B$69*0.5^(A45/Assumptions!$B$70))+Assumptions!$B$72*(K45+Y45) -> 140.59 | AK45: =IF(AND(Assumptions!$B$76=1,A45>=Assumptions!$B$77),Assumptions!$B$78/12,0) -> 4583.3333 | AL45: =IF(AND(Assumptions!$B$86=1,Q45<>""),Assumptions!$B$87/12,0) -> 0
A46: 45 | B46: Apr 2030 | C46: =IF(A46<=12,1,IF(A46<=24,2,IF(A46<=36,3,4))) -> 4 | D46: =IF(A46<=6,"P1: Pilot->Seed",IF(A46<=18,"P2: Scale/Series A",IF(A46<=36,"P3: Post-Series A","P4: Maturity"))) -> P4: Maturity | E46: =IF(C46=1,Assumptions!$B$5,IF(C46=2,Assumptions!$B$6,IF(C46=3,Assumptions!$B$7,Assumptions!$B$8))) -> 15000 | F46: =IF(A46<=6,Assumptions!$B$14,IF(A46<=18,Assumptions!$B$15,IF(A46<=36,Assumptions!$B$16,Assumptions!$B$17))) -> 0.05 | G46: =ROUND(MAX(I45,1)*F46,0) -> 9 | H46: =ROUND(I45*Assumptions!$B$18,0) -> 4 | I46: =MIN(I45+G46-H46,E46) -> 193 | J46: =Assumptions!$B$23 -> 0.85 | K46: =I46*J46 -> 164.05 | L46: =Assumptions!$B$10*(1-Assumptions!$B$12)+Assumptions!$B$11*Assumptions!$B$12 -> 46.06 | M46: =K46*L46 -> 7556.143 | N46: =((IF(A46<=Assumptions!$B$91,Assumptions!$B$90,IF(A46>=Assumptions!$B$92,1,Assumptions!$B$90+(1-Assumptions!$B$90)*(A46-Assumptions!$B$91)/(Assumptions!$B$92-Assumptions!$B$91))))*Assumptions!$B$81*Assumptions!$B$75+Assumptions!$B$82)*(1+Assumptions!$B$83)/12 -> 28270.833 | O46: =M46*Assumptions!$B$33 -> 6422.7216 | P46: =O46-N46 -> -21848.112 | Q46: =IF(A46>=Assumptions!$B$45,A46-Assumptions!$B$45+1,"") -> 33 | R46: =IF(Q46="","Not yet launched",IF(Q46<=6,"CP1: Launch",IF(Q46<=18,"CP2: Scale",IF(Q46<=36,"CP3: Mature","CP4: Steady")))) -> CP3: Mature | S46: =IF(Q46="",0,Assumptions!$B$46) -> 2000 | T46: =IF(Q46="",0,IF(Q46<=6,Assumptions!$B$14,IF(Q46<=18,Assumptions!$B$15,IF(Q46<=36,Assumptions!$B$16,Assumptions!$B$17)))) -> 0.08 | U46: =IF(Q46="",0,IF(Q46=1,Assumptions!$B$65,ROUND(MAX(W45,1)*T46,0))) -> 7 | V46: =IF(Q46="",0,ROUND(W45*Assumptions!$B$49,0)) -> 2 | W46: =IF(Q46="",0,MIN(W45+U46-V46,S46)) -> 89 | X46: =IF(Q46="",0,Assumptions!$B$55) -> 0.9 | Y46: =W46*X46 -> 80.1 | Z46: =L46 -> 46.06 | AA46: =Y46*Z46 -> 3689.406 | AB46: =IF(A46=Assumptions!$B$45,Assumptions!$B$47+Assumptions!$B$48,IF(A46>Assumptions!$B$45,Assumptions!$B$47,0)) -> 50 | AC46: =AA46*Assumptions!$B$33 -> 3135.9951 | AD46: =I46+W46 -> 282 | AE46: =M46+AA46 -> 11245.549 | AF46: =N46+AB46+AJ46+AK46+AL46+Assumptions!$B$68 -> 33114.619 | AG46: =O46+AC46 -> 9558.7167 | AH46: =AG46-AF46 -> -23555.903 | AI46: =IFERROR((AD46-AD45)/AD45,"") -> 0.036764706 | AJ46: =MAX(Assumptions!$B$71,Assumptions!$B$69*0.5^(A46/Assumptions!$B$70))+Assumptions!$B$72*(K46+Y46) -> 160.4525 | AK46: =IF(AND(Assumptions!$B$76=1,A46>=Assumptions!$B$77),Assumptions!$B$78/12,0) -> 4583.3333 | AL46: =IF(AND(Assumptions!$B$86=1,Q46<>""),Assumptions!$B$87/12,0) -> 0
A47: 46 | B47: May 2030 | C47: =IF(A47<=12,1,IF(A47<=24,2,IF(A47<=36,3,4))) -> 4 | D47: =IF(A47<=6,"P1: Pilot->Seed",IF(A47<=18,"P2: Scale/Series A",IF(A47<=36,"P3: Post-Series A","P4: Maturity"))) -> P4: Maturity | E47: =IF(C47=1,Assumptions!$B$5,IF(C47=2,Assumptions!$B$6,IF(C47=3,Assumptions!$B$7,Assumptions!$B$8))) -> 15000 | F47: =IF(A47<=6,Assumptions!$B$14,IF(A47<=18,Assumptions!$B$15,IF(A47<=36,Assumptions!$B$16,Assumptions!$B$17))) -> 0.05 | G47: =ROUND(MAX(I46,1)*F47,0) -> 10 | H47: =ROUND(I46*Assumptions!$B$18,0) -> 4 | I47: =MIN(I46+G47-H47,E47) -> 199 | J47: =Assumptions!$B$24 -> 1 | K47: =I47*J47 -> 199 | L47: =Assumptions!$B$10*(1-Assumptions!$B$12)+Assumptions!$B$11*Assumptions!$B$12 -> 46.06 | M47: =K47*L47 -> 9165.94 | N47: =((IF(A47<=Assumptions!$B$91,Assumptions!$B$90,IF(A47>=Assumptions!$B$92,1,Assumptions!$B$90+(1-Assumptions!$B$90)*(A47-Assumptions!$B$91)/(Assumptions!$B$92-Assumptions!$B$91))))*Assumptions!$B$81*Assumptions!$B$75+Assumptions!$B$82)*(1+Assumptions!$B$83)/12 -> 28270.833 | O47: =M47*Assumptions!$B$33 -> 7791.049 | P47: =O47-N47 -> -20479.784 | Q47: =IF(A47>=Assumptions!$B$45,A47-Assumptions!$B$45+1,"") -> 34 | R47: =IF(Q47="","Not yet launched",IF(Q47<=6,"CP1: Launch",IF(Q47<=18,"CP2: Scale",IF(Q47<=36,"CP3: Mature","CP4: Steady")))) -> CP3: Mature | S47: =IF(Q47="",0,Assumptions!$B$46) -> 2000 | T47: =IF(Q47="",0,IF(Q47<=6,Assumptions!$B$14,IF(Q47<=18,Assumptions!$B$15,IF(Q47<=36,Assumptions!$B$16,Assumptions!$B$17)))) -> 0.08 | U47: =IF(Q47="",0,IF(Q47=1,Assumptions!$B$65,ROUND(MAX(W46,1)*T47,0))) -> 7 | V47: =IF(Q47="",0,ROUND(W46*Assumptions!$B$49,0)) -> 2 | W47: =IF(Q47="",0,MIN(W46+U47-V47,S47)) -> 94 | X47: =IF(Q47="",0,Assumptions!$B$56) -> 0.6 | Y47: =W47*X47 -> 56.4 | Z47: =L47 -> 46.06 | AA47: =Y47*Z47 -> 2597.784 | AB47: =IF(A47=Assumptions!$B$45,Assumptions!$B$47+Assumptions!$B$48,IF(A47>Assumptions!$B$45,Assumptions!$B$47,0)) -> 50 | AC47: =AA47*Assumptions!$B$33 -> 2208.1164 | AD47: =I47+W47 -> 293 | AE47: =M47+AA47 -> 11763.724 | AF47: =N47+AB47+AJ47+AK47+AL47+Assumptions!$B$68 -> 33118.557 | AG47: =O47+AC47 -> 9999.1654 | AH47: =AG47-AF47 -> -23119.391 | AI47: =IFERROR((AD47-AD46)/AD46,"") -> 0.039007092 | AJ47: =MAX(Assumptions!$B$71,Assumptions!$B$69*0.5^(A47/Assumptions!$B$70))+Assumptions!$B$72*(K47+Y47) -> 164.39 | AK47: =IF(AND(Assumptions!$B$76=1,A47>=Assumptions!$B$77),Assumptions!$B$78/12,0) -> 4583.3333 | AL47: =IF(AND(Assumptions!$B$86=1,Q47<>""),Assumptions!$B$87/12,0) -> 0
A48: 47 | B48: Jun 2030 | C48: =IF(A48<=12,1,IF(A48<=24,2,IF(A48<=36,3,4))) -> 4 | D48: =IF(A48<=6,"P1: Pilot->Seed",IF(A48<=18,"P2: Scale/Series A",IF(A48<=36,"P3: Post-Series A","P4: Maturity"))) -> P4: Maturity | E48: =IF(C48=1,Assumptions!$B$5,IF(C48=2,Assumptions!$B$6,IF(C48=3,Assumptions!$B$7,Assumptions!$B$8))) -> 15000 | F48: =IF(A48<=6,Assumptions!$B$14,IF(A48<=18,Assumptions!$B$15,IF(A48<=36,Assumptions!$B$16,Assumptions!$B$17))) -> 0.05 | G48: =ROUND(MAX(I47,1)*F48,0) -> 10 | H48: =ROUND(I47*Assumptions!$B$18,0) -> 4 | I48: =MIN(I47+G48-H48,E48) -> 205 | J48: =Assumptions!$B$25 -> 1 | K48: =I48*J48 -> 205 | L48: =Assumptions!$B$10*(1-Assumptions!$B$12)+Assumptions!$B$11*Assumptions!$B$12 -> 46.06 | M48: =K48*L48 -> 9442.3 | N48: =((IF(A48<=Assumptions!$B$91,Assumptions!$B$90,IF(A48>=Assumptions!$B$92,1,Assumptions!$B$90+(1-Assumptions!$B$90)*(A48-Assumptions!$B$91)/(Assumptions!$B$92-Assumptions!$B$91))))*Assumptions!$B$81*Assumptions!$B$75+Assumptions!$B$82)*(1+Assumptions!$B$83)/12 -> 28270.833 | O48: =M48*Assumptions!$B$33 -> 8025.955 | P48: =O48-N48 -> -20244.878 | Q48: =IF(A48>=Assumptions!$B$45,A48-Assumptions!$B$45+1,"") -> 35 | R48: =IF(Q48="","Not yet launched",IF(Q48<=6,"CP1: Launch",IF(Q48<=18,"CP2: Scale",IF(Q48<=36,"CP3: Mature","CP4: Steady")))) -> CP3: Mature | S48: =IF(Q48="",0,Assumptions!$B$46) -> 2000 | T48: =IF(Q48="",0,IF(Q48<=6,Assumptions!$B$14,IF(Q48<=18,Assumptions!$B$15,IF(Q48<=36,Assumptions!$B$16,Assumptions!$B$17)))) -> 0.08 | U48: =IF(Q48="",0,IF(Q48=1,Assumptions!$B$65,ROUND(MAX(W47,1)*T48,0))) -> 8 | V48: =IF(Q48="",0,ROUND(W47*Assumptions!$B$49,0)) -> 2 | W48: =IF(Q48="",0,MIN(W47+U48-V48,S48)) -> 100 | X48: =IF(Q48="",0,Assumptions!$B$57) -> 0.4 | Y48: =W48*X48 -> 40 | Z48: =L48 -> 46.06 | AA48: =Y48*Z48 -> 1842.4 | AB48: =IF(A48=Assumptions!$B$45,Assumptions!$B$47+Assumptions!$B$48,IF(A48>Assumptions!$B$45,Assumptions!$B$47,0)) -> 50 | AC48: =AA48*Assumptions!$B$33 -> 1566.04 | AD48: =I48+W48 -> 305 | AE48: =M48+AA48 -> 11284.7 | AF48: =N48+AB48+AJ48+AK48+AL48+Assumptions!$B$68 -> 33114.917 | AG48: =O48+AC48 -> 9591.995 | AH48: =AG48-AF48 -> -23522.922 | AI48: =IFERROR((AD48-AD47)/AD47,"") -> 0.040955631 | AJ48: =MAX(Assumptions!$B$71,Assumptions!$B$69*0.5^(A48/Assumptions!$B$70))+Assumptions!$B$72*(K48+Y48) -> 160.75 | AK48: =IF(AND(Assumptions!$B$76=1,A48>=Assumptions!$B$77),Assumptions!$B$78/12,0) -> 4583.3333 | AL48: =IF(AND(Assumptions!$B$86=1,Q48<>""),Assumptions!$B$87/12,0) -> 0
A49: 48 | B49: Jul 2030 | C49: =IF(A49<=12,1,IF(A49<=24,2,IF(A49<=36,3,4))) -> 4 | D49: =IF(A49<=6,"P1: Pilot->Seed",IF(A49<=18,"P2: Scale/Series A",IF(A49<=36,"P3: Post-Series A","P4: Maturity"))) -> P4: Maturity | E49: =IF(C49=1,Assumptions!$B$5,IF(C49=2,Assumptions!$B$6,IF(C49=3,Assumptions!$B$7,Assumptions!$B$8))) -> 15000 | F49: =IF(A49<=6,Assumptions!$B$14,IF(A49<=18,Assumptions!$B$15,IF(A49<=36,Assumptions!$B$16,Assumptions!$B$17))) -> 0.05 | G49: =ROUND(MAX(I48,1)*F49,0) -> 10 | H49: =ROUND(I48*Assumptions!$B$18,0) -> 4 | I49: =MIN(I48+G49-H49,E49) -> 211 | J49: =Assumptions!$B$26 -> 1 | K49: =I49*J49 -> 211 | L49: =Assumptions!$B$10*(1-Assumptions!$B$12)+Assumptions!$B$11*Assumptions!$B$12 -> 46.06 | M49: =K49*L49 -> 9718.66 | N49: =((IF(A49<=Assumptions!$B$91,Assumptions!$B$90,IF(A49>=Assumptions!$B$92,1,Assumptions!$B$90+(1-Assumptions!$B$90)*(A49-Assumptions!$B$91)/(Assumptions!$B$92-Assumptions!$B$91))))*Assumptions!$B$81*Assumptions!$B$75+Assumptions!$B$82)*(1+Assumptions!$B$83)/12 -> 28270.833 | O49: =M49*Assumptions!$B$33 -> 8260.861 | P49: =O49-N49 -> -20009.972 | Q49: =IF(A49>=Assumptions!$B$45,A49-Assumptions!$B$45+1,"") -> 36 | R49: =IF(Q49="","Not yet launched",IF(Q49<=6,"CP1: Launch",IF(Q49<=18,"CP2: Scale",IF(Q49<=36,"CP3: Mature","CP4: Steady")))) -> CP3: Mature | S49: =IF(Q49="",0,Assumptions!$B$46) -> 2000 | T49: =IF(Q49="",0,IF(Q49<=6,Assumptions!$B$14,IF(Q49<=18,Assumptions!$B$15,IF(Q49<=36,Assumptions!$B$16,Assumptions!$B$17)))) -> 0.08 | U49: =IF(Q49="",0,IF(Q49=1,Assumptions!$B$65,ROUND(MAX(W48,1)*T49,0))) -> 8 | V49: =IF(Q49="",0,ROUND(W48*Assumptions!$B$49,0)) -> 2 | W49: =IF(Q49="",0,MIN(W48+U49-V49,S49)) -> 106 | X49: =IF(Q49="",0,Assumptions!$B$58) -> 0.35 | Y49: =W49*X49 -> 37.1 | Z49: =L49 -> 46.06 | AA49: =Y49*Z49 -> 1708.826 | AB49: =IF(A49=Assumptions!$B$45,Assumptions!$B$47+Assumptions!$B$48,IF(A49>Assumptions!$B$45,Assumptions!$B$47,0)) -> 50 | AC49: =AA49*Assumptions!$B$33 -> 1452.5021 | AD49: =I49+W49 -> 317 | AE49: =M49+AA49 -> 11427.486 | AF49: =N49+AB49+AJ49+AK49+AL49+Assumptions!$B$68 -> 33116.002 | AG49: =O49+AC49 -> 9713.3631 | AH49: =AG49-AF49 -> -23402.639 | AI49: =IFERROR((AD49-AD48)/AD48,"") -> 0.039344262 | AJ49: =MAX(Assumptions!$B$71,Assumptions!$B$69*0.5^(A49/Assumptions!$B$70))+Assumptions!$B$72*(K49+Y49) -> 161.835 | AK49: =IF(AND(Assumptions!$B$76=1,A49>=Assumptions!$B$77),Assumptions!$B$78/12,0) -> 4583.3333 | AL49: =IF(AND(Assumptions!$B$86=1,Q49<>""),Assumptions!$B$87/12,0) -> 0

Sheet Annual Summary
A1: Annual Summary (rolled up from Monthly Model)
A3: Metric | B3: Year 1 | C3: Year 2 | D3: Year 3 | E3: Year 4
A4: Logos at year-end (Dec) | B4: ='Monthly Model'!AD13 -> 27 | C4: ='Monthly Model'!AD25 -> 93 | D4: ='Monthly Model'!AD37 -> 201 | E4: ='Monthly Model'!AD49 -> 317
A5: Average monthly logos (year) | B5: =AVERAGE('Monthly Model'!AD2:AD13) -> 13.333333 | C5: =AVERAGE('Monthly Model'!AD14:AD25) -> 61.083333 | D5: =AVERAGE('Monthly Model'!AD26:AD37) -> 147.5 | E5: =AVERAGE('Monthly Model'!AD38:AD49) -> 259.33333
A6: December MRR (run-rate month) | B6: ='Monthly Model'!AE13 -> 1243.62 | C6: ='Monthly Model'!AE25 -> 3714.739 | D6: ='Monthly Model'!AE37 -> 7671.293 | E6: ='Monthly Model'!AE49 -> 11427.486
A7: ARR (Dec MRR x 12 — run-rate) | B7: =('Monthly Model'!AE13)*12 -> 14923.44 | C7: =('Monthly Model'!AE25)*12 -> 44576.868 | D7: =('Monthly Model'!AE37)*12 -> 92055.516 | E7: =('Monthly Model'!AE49)*12 -> 137129.83
A8: Average annual revenue (sum of monthly MRR) | B8: =SUM('Monthly Model'!AE2:AE13) -> 5653.865 | C8: =SUM('Monthly Model'!AE14:AE25) -> 24573.01 | D8: =SUM('Monthly Model'!AE26:AE37) -> 58922.255 | E8: =SUM('Monthly Model'!AE38:AE49) -> 101822.54
A9: Annual opex (burn) | B9: =SUM('Monthly Model'!AF2:AF13) -> 73876.1 | C9: =SUM('Monthly Model'!AF14:AF25) -> 392932.56 | D9: =SUM('Monthly Model'!AF26:AF37) -> 396797.74 | E9: =SUM('Monthly Model'!AF38:AF49) -> 397123.73
A10: Annual gross profit | B10: =SUM('Monthly Model'!AG2:AG13) -> 4805.7852 | C10: =SUM('Monthly Model'!AG14:AG25) -> 20887.058 | D10: =SUM('Monthly Model'!AG26:AG37) -> 50083.917 | E10: =SUM('Monthly Model'!AG38:AG49) -> 86549.158
A11: Net cash flow (annual) | B11: =SUM('Monthly Model'!AH2:AH13) -> -69070.314 | C11: =SUM('Monthly Model'!AH14:AH25) -> -372045.5 | D11: =SUM('Monthly Model'!AH26:AH37) -> -346713.82 | E11: =SUM('Monthly Model'!AH38:AH49) -> -310574.57
A12: Burn multiple (opex / avg annual revenue) | B12: =SUM('Monthly Model'!AF2:AF13)/SUM('Monthly Model'!AE2:AE13) -> 13.066477 | C12: =SUM('Monthly Model'!AF14:AF25)/SUM('Monthly Model'!AE14:AE25) -> 15.990412 | D12: =SUM('Monthly Model'!AF26:AF37)/SUM('Monthly Model'!AE26:AE37) -> 6.7342592 | E12: =SUM('Monthly Model'!AF38:AF49)/SUM('Monthly Model'!AE38:AE49) -> 3.9001554
A13: — of which: Caribbean logos (year-end) | B13: ='Monthly Model'!W13 -> 0 | C13: ='Monthly Model'!W25 -> 19 | D13: ='Monthly Model'!W37 -> 53 | E13: ='Monthly Model'!W49 -> 106
A14: — of which: Caribbean MRR (Dec, run-rate month, EUR) | B14: ='Monthly Model'!AA13 -> 0 | C14: ='Monthly Model'!AA25 -> 306.299 | D14: ='Monthly Model'!AA37 -> 854.413 | E14: ='Monthly Model'!AA49 -> 1708.826
A16: ARR run-rate = December's monthly recurring revenue annualized (Med + Caribbean combined). Because of seasonality, this is materially lower than a summer-month run-rate — use the average annual revenue line for realistic ARR claims.
A17: Caribbean figures assume a launch at the month set in Assumptions (Caribbean launch month) and are built on placeholder ceiling/opex/seasonality inputs — replace with sourced data before quoting externally.
A18: — of which: AI token cost (annual, EUR) | B18: =SUM('Monthly Model'!AJ2:AJ13) -> 1880.2664 | C18: =SUM('Monthly Model'!AJ14:AJ25) -> 1086.725 | D18: =SUM('Monthly Model'!AJ26:AJ37) -> 1347.7375 | E18: =SUM('Monthly Model'!AJ38:AJ49) -> 1673.7275
A19: — of which: Sales/BD hire cost (annual, EUR) | B19: =SUM('Monthly Model'!AK2:AK13) -> 0 | C19: =SUM('Monthly Model'!AK14:AK25) -> 55000 | D19: =SUM('Monthly Model'!AK26:AK37) -> 55000 | E19: =SUM('Monthly Model'!AK38:AK49) -> 55000
A20: — of which: Caribbean regional hire cost (annual, EUR) | B20: =SUM('Monthly Model'!AL2:AL13) -> 0 | C20: =SUM('Monthly Model'!AL14:AL25) -> 0 | D20: =SUM('Monthly Model'!AL26:AL37) -> 0 | E20: =SUM('Monthly Model'!AL38:AL49) -> 0
A21: AI token cost now splits into a declining build/dev component (half-life in Assumptions) and a growing per-vessel serving component — so it shrinks as the system matures but never hits zero, and rises again as the customer base grows. Cloud compute assumes €50/month per active region (real Western Med figure), not a placeholder.

Sheet Series A Dashboard
A1: Series A Readiness — checked at Month 12 (edit target month below)
A2: Target month to evaluate (1-48) | B2: 12
A4: Metric | B4: Actual (model) | C4: Threshold | D4: Status / notes
A5: Cumulative logos (Med + Caribbean) | B5: =INDEX('Monthly Model'!AD:AD,$B$2+1) -> 27 | C5: 150 | D5: =IF(B5>=C5,"On track","Behind — reassess growth-rate assumptions") -> Behind — reassess growth-rate assumptions
A6: MRR at target month (EUR, Med + Caribbean) | B6: =INDEX('Monthly Model'!AE:AE,$B$2+1) -> 1243.62 | C6: 15000 | D6: =IF(B6>=C6,"On track","Behind threshold") -> Behind threshold
A7: Annualized run-rate (MRR x 12, EUR) | B7: =B6*12 -> 14923.44 | C7: 180000 | D7: =IF(B7>=C7,"On track","Below typical vertical-SaaS Series A entry range") -> Below typical vertical-SaaS Series A entry range
A8: Trailing-3-month average MoM TOTAL logo growth % | B8: =AVERAGE(INDEX('Monthly Model'!AI:AI,$B$2-1):INDEX('Monthly Model'!AI:AI,$B$2+1)) -> 0.14484127 | C8: 0.1 | D8: =IF(B8>=C8,"On track","Growth decelerating faster than target") -> On track
A9: Monthly logo churn % | B9: =Assumptions!$B$18 -> 0.02 | C9: 0.03 | D9: =IF(B9<=C9,"On track (lower is better)","Churn above acceptable threshold") -> On track (lower is better)
A10: Blended monthly price (EUR) | B10: =Assumptions!$B$10*(1-Assumptions!$B$12)+Assumptions!$B$11*Assumptions!$B$12 -> 46.06 | C10: n/a | D10: Reference only — feeds LTV calc below
A11: Customer lifetime (months) = 1/churn | B11: =1/B9 -> 50 | C11: n/a | D11: Cross-check against Assumptions tab lifetime input
A12: LTV per vessel (EUR) = price x gross margin x lifetime | B12: =B10*Assumptions!$B$33*B11 -> 1957.55 | C12: n/a
A13: CAC per vessel (EUR) | B13: =Assumptions!$B$34 -> 150 | C13: n/a | D13: Replace with real pilot BD/marketing cost per logo
A14: LTV : CAC ratio | B14: =B12/B13 -> 13.050333 | C14: 3 | D14: =IF(B14>=C14,"On track (3x+ is the common benchmark)","Below typical investor benchmark") -> On track (3x+ is the common benchmark)
A15: CAC payback period (months) | B15: =B13/(B10*Assumptions!$B$33) -> 3.8313198 | C15: 12 | D15: =IF(B15<=C15,"On track (12mo is a common benchmark)","Payback slower than typical benchmark") -> On track (12mo is a common benchmark)
A17: Threshold cells (yellow) are common vertical-SaaS seed-to-Series-A benchmarks, not universal rules — adjust to
A18: match feedback from the specific investors you talk to. Typical current-market ranges: €10-30k+ MRR with clear
A19: month-over-month growth, LTV:CAC of 3x or higher, CAC payback under ~12 months, and net logo retention above 90%.
A20: Seed-to-Series-A timing has widened across the market in recent years (often 18-24 months) — treat a 12-month
A21: target as an ambitious, metrics-triggered goal, not a fixed calendar promise to investors.
A22: From month 13 onward (Caribbean launch target), the logo/MRR/growth figures above are Med + Caribbean combined — see Annual Summary rows 13-14 for the Caribbean-only breakdown.
